Workbook

Sheet Start Here
A1: Debt Free Plan
A2: See your debt-free date and exactly what to pay each month
B4: YOUR SETTINGS
B5: Total you can pay toward debt each month | C5: 1200 | D5: Include all minimum payments plus any extra you can afford.
B6: Plan start month | C6: 46296 | D6: The first month you'll follow this plan.
B7: Payoff method | C7: Avalanche | D7: Avalanche = highest interest first (saves the most). Snowball = smallest balance first (fastest wins).
B10: HOW TO USE
B11: 1. List your debts on the My Debts tab: name, balance, interest rate (APR) and minimum payment.
B12: 2. Enter your monthly debt budget above (yellow cells = type here).
B13: 3. Open My Plan to see your debt-free date, total interest, and what to pay this month.
B14: 4. Pick Avalanche or Snowball above. My Plan compares both so you can see the difference.
B15: 5. Each month, pay the amounts shown. When one debt is paid off, its payment rolls to the next.
B16: 6. Update balances every few months so the plan stays accurate.
B17: Tip: in Google Sheets, open the file from Google Drive or use File > Import.
B19: Estimates assume fixed interest rates and on-time payments, with no new charges. Not financial advice.

Sheet My Plan
A1: My Plan
B2: ="Your "&LOWER('Start Here'!$C$7)&" plan · starting "&TEXT('Start Here'!$C$6,"mmmm yyyy") -> Your avalanche plan · starting October 2026
B3: =IF('Start Here'!$C$5<'My Debts'!$E$16,"⚠ Your monthly budget is less than your minimum payments ("&TEXT('My Debts'!$E$16,"$#,##0")&"). This plan assumes you still pay every minimum. Raise your budget on Start Here.","")
B5: DEBT-FREE DATE | D5: MONTHS TO GO | G5: TOTAL INTEREST | I5: TOTAL YOU'LL PAY
B6: =IF(IF('Start Here'!$C$7="Snowball",COUNTIF('Snowball Schedule'!$AG$7:$AG$366,">0.005")+1,COUNTIF('Avalanche Schedule'!$AG$7:$AG$366,">0.005")+1)>360,"30+ years",DATE(YEAR('Start Here'!$C$6),MONTH('Start Here'!$C$6)+IF('Start Here'!$C$7="Snowball",COUNTIF('Snowball Schedule'!$AG$7:$AG$366,">0.005")+1,COUNTIF('Avalanche Schedule'!$AG$7:$AG$366,">0.005")+1)-1,1)) -> 46692 | D6: =IF(IF('Start Here'!$C$7="Snowball",COUNTIF('Snowball Schedule'!$AG$7:$AG$366,">0.005")+1,COUNTIF('Avalanche Schedule'!$AG$7:$AG$366,">0.005")+1)>360,"30+",IF('Start Here'!$C$7="Snowball",COUNTIF('Snowball Schedule'!$AG$7:$AG$366,">0.005")+1,COUNTIF('Avalanche Schedule'!$AG$7:$AG$366,">0.005")+1)) -> 14 | G6: =IF('Start Here'!$C$7="Snowball",SUM('Snowball Schedule'!$AH$7:$AH$366),SUM('Avalanche Schedule'!$AH$7:$AH$366)) -> 847.68 | I6: ='My Debts'!$C$16+IF('Start Here'!$C$7="Snowball",SUM('Snowball Schedule'!$AH$7:$AH$366),SUM('Avalanche Schedule'!$AH$7:$AH$366)) -> 15697.68
B10: WHAT TO PAY THIS MONTH | D10: Month # | E10: 1 | G10: SNOWBALL vs AVALANCHE
B11: Debt | C11: Pay this month | D11: Balance after | E11: Order | H11: Snowball | I11: Avalanche | J11: Difference
B12: =IF('My Debts'!$B$6="","",'My Debts'!$B$6) -> Store card (example) | C12: =IF(B12="","",IF('Start Here'!$C$7="Snowball",INDEX('Snowball Schedule'!$B$7:$B$366,$E$10)-INDEX('Snowball Schedule'!$V$7:$V$366,$E$10),INDEX('Avalanche Schedule'!$B$7:$B$366,$E$10)-INDEX('Avalanche Schedule'!$V$7:$V$366,$E$10))) -> 805 | D12: =IF(B12="","",IF('Start Here'!$C$7="Snowball",INDEX('Snowball Schedule'!$V$7:$V$366,$E$10),INDEX('Avalanche Schedule'!$V$7:$V$366,$E$10))) -> 64.12 | E12: =IF(B12="","",IF('Start Here'!$C$7="Snowball",'My Debts'!$F$6,'My Debts'!$G$6)) -> 1 | G12: Debt-free in (months) | H12: =IF(COUNTIF('Snowball Schedule'!$AG$7:$AG$366,">0.005")+1>360,"30+ yrs",COUNTIF('Snowball Schedule'!$AG$7:$AG$366,">0.005")+1) -> 14 | I12: =IF(COUNTIF('Avalanche Schedule'!$AG$7:$AG$366,">0.005")+1>360,"30+ yrs",COUNTIF('Avalanche Schedule'!$AG$7:$AG$366,">0.005")+1) -> 14 | J12: =IFERROR(H12-I12,"-") -> 0
B13: =IF('My Debts'!$B$7="","",'My Debts'!$B$7) -> Visa (example) | C13: =IF(B13="","",IF('Start Here'!$C$7="Snowball",INDEX('Snowball Schedule'!$C$7:$C$366,$E$10)-INDEX('Snowball Schedule'!$W$7:$W$366,$E$10),INDEX('Avalanche Schedule'!$C$7:$C$366,$E$10)-INDEX('Avalanche Schedule'!$W$7:$W$366,$E$10))) -> 110 | D13: =IF(B13="","",IF('Start Here'!$C$7="Snowball",INDEX('Snowball Schedule'!$W$7:$W$366,$E$10),INDEX('Avalanche Schedule'!$W$7:$W$366,$E$10))) -> 4168.72 | E13: =IF(B13="","",IF('Start Here'!$C$7="Snowball",'My Debts'!$F$7,'My Debts'!$G$7)) -> 2 | G13: Total interest | H13: =SUM('Snowball Schedule'!$AH$7:$AH$366) -> 847.68 | I13: =SUM('Avalanche Schedule'!$AH$7:$AH$366) -> 847.68 | J13: =IFERROR(H13-I13,"-") -> 0
B14: =IF('My Debts'!$B$8="","",'My Debts'!$B$8) -> Car loan (example) | C14: =IF(B14="","",IF('Start Here'!$C$7="Snowball",INDEX('Snowball Schedule'!$D$7:$D$366,$E$10)-INDEX('Snowball Schedule'!$X$7:$X$366,$E$10),INDEX('Avalanche Schedule'!$D$7:$D$366,$E$10)-INDEX('Avalanche Schedule'!$X$7:$X$366,$E$10))) -> 285 | D14: =IF(B14="","",IF('Start Here'!$C$7="Snowball",INDEX('Snowball Schedule'!$X$7:$X$366,$E$10),INDEX('Avalanche Schedule'!$X$7:$X$366,$E$10))) -> 9571.35 | E14: =IF(B14="","",IF('Start Here'!$C$7="Snowball",'My Debts'!$F$8,'My Debts'!$G$8)) -> 3
B15: =IF('My Debts'!$B$9="","",'My Debts'!$B$9) | C15: =IF(B15="","",IF('Start Here'!$C$7="Snowball",INDEX('Snowball Schedule'!$E$7:$E$366,$E$10)-INDEX('Snowball Schedule'!$Y$7:$Y$366,$E$10),INDEX('Avalanche Schedule'!$E$7:$E$366,$E$10)-INDEX('Avalanche Schedule'!$Y$7:$Y$366,$E$10))) | D15: =IF(B15="","",IF('Start Here'!$C$7="Snowball",INDEX('Snowball Schedule'!$Y$7:$Y$366,$E$10),INDEX('Avalanche Schedule'!$Y$7:$Y$366,$E$10))) | E15: =IF(B15="","",IF('Start Here'!$C$7="Snowball",'My Debts'!$F$9,'My Debts'!$G$9)) | G15: =IF('My Debts'!$C$16=0,"",IF(J13>0.5,"Avalanche saves you "&TEXT(J13,"$#,##0")&" in interest.","Both methods cost about the same here, so Snowball's quick wins are a free bonus.")) -> Both methods cost about the same here, so Snowball's quick wins are a free bonus.
B16: =IF('My Debts'!$B$10="","",'My Debts'!$B$10) | C16: =IF(B16="","",IF('Start Here'!$C$7="Snowball",INDEX('Snowball Schedule'!$F$7:$F$366,$E$10)-INDEX('Snowball Schedule'!$Z$7:$Z$366,$E$10),INDEX('Avalanche Schedule'!$F$7:$F$366,$E$10)-INDEX('Avalanche Schedule'!$Z$7:$Z$366,$E$10))) | D16: =IF(B16="","",IF('Start Here'!$C$7="Snowball",INDEX('Snowball Schedule'!$Z$7:$Z$366,$E$10),INDEX('Avalanche Schedule'!$Z$7:$Z$366,$E$10))) | E16: =IF(B16="","",IF('Start Here'!$C$7="Snowball",'My Debts'!$F$10,'My Debts'!$G$10)) | G16: Snowball pays off small debts first for quick wins and motivation.
B17: =IF('My Debts'!$B$11="","",'My Debts'!$B$11) | C17: =IF(B17="","",IF('Start Here'!$C$7="Snowball",INDEX('Snowball Schedule'!$G$7:$G$366,$E$10)-INDEX('Snowball Schedule'!$AA$7:$AA$366,$E$10),INDEX('Avalanche Schedule'!$G$7:$G$366,$E$10)-INDEX('Avalanche Schedule'!$AA$7:$AA$366,$E$10))) | D17: =IF(B17="","",IF('Start Here'!$C$7="Snowball",INDEX('Snowball Schedule'!$AA$7:$AA$366,$E$10),INDEX('Avalanche Schedule'!$AA$7:$AA$366,$E$10))) | E17: =IF(B17="","",IF('Start Here'!$C$7="Snowball",'My Debts'!$F$11,'My Debts'!$G$11)) | G17: Avalanche targets the highest interest first and usually costs less.
B18: =IF('My Debts'!$B$12="","",'My Debts'!$B$12) | C18: =IF(B18="","",IF('Start Here'!$C$7="Snowball",INDEX('Snowball Schedule'!$H$7:$H$366,$E$10)-INDEX('Snowball Schedule'!$AB$7:$AB$366,$E$10),INDEX('Avalanche Schedule'!$H$7:$H$366,$E$10)-INDEX('Avalanche Schedule'!$AB$7:$AB$366,$E$10))) | D18: =IF(B18="","",IF('Start Here'!$C$7="Snowball",INDEX('Snowball Schedule'!$AB$7:$AB$366,$E$10),INDEX('Avalanche Schedule'!$AB$7:$AB$366,$E$10))) | E18: =IF(B18="","",IF('Start Here'!$C$7="Snowball",'My Debts'!$F$12,'My Debts'!$G$12))
B19: =IF('My Debts'!$B$13="","",'My Debts'!$B$13) | C19: =IF(B19="","",IF('Start Here'!$C$7="Snowball",INDEX('Snowball Schedule'!$I$7:$I$366,$E$10)-INDEX('Snowball Schedule'!$AC$7:$AC$366,$E$10),INDEX('Avalanche Schedule'!$I$7:$I$366,$E$10)-INDEX('Avalanche Schedule'!$AC$7:$AC$366,$E$10))) | D19: =IF(B19="","",IF('Start Here'!$C$7="Snowball",INDEX('Snowball Schedule'!$AC$7:$AC$366,$E$10),INDEX('Avalanche Schedule'!$AC$7:$AC$366,$E$10))) | E19: =IF(B19="","",IF('Start Here'!$C$7="Snowball",'My Debts'!$F$13,'My Debts'!$G$13)) | G19: PAYOFF ORDER (YOUR PLAN)
B20: =IF('My Debts'!$B$14="","",'My Debts'!$B$14) | C20: =IF(B20="","",IF('Start Here'!$C$7="Snowball",INDEX('Snowball Schedule'!$J$7:$J$366,$E$10)-INDEX('Snowball Schedule'!$AD$7:$AD$366,$E$10),INDEX('Avalanche Schedule'!$J$7:$J$366,$E$10)-INDEX('Avalanche Schedule'!$AD$7:$AD$366,$E$10))) | D20: =IF(B20="","",IF('Start Here'!$C$7="Snowball",INDEX('Snowball Schedule'!$AD$7:$AD$366,$E$10),INDEX('Avalanche Schedule'!$AD$7:$AD$366,$E$10))) | E20: =IF(B20="","",IF('Start Here'!$C$7="Snowball",'My Debts'!$F$14,'My Debts'!$G$14)) | G20: # | H20: Debt | I20: Paid off | J20: Interest paid
B21: =IF('My Debts'!$B$15="","",'My Debts'!$B$15) | C21: =IF(B21="","",IF('Start Here'!$C$7="Snowball",INDEX('Snowball Schedule'!$K$7:$K$366,$E$10)-INDEX('Snowball Schedule'!$AE$7:$AE$366,$E$10),INDEX('Avalanche Schedule'!$K$7:$K$366,$E$10)-INDEX('Avalanche Schedule'!$AE$7:$AE$366,$E$10))) | D21: =IF(B21="","",IF('Start Here'!$C$7="Snowball",INDEX('Snowball Schedule'!$AE$7:$AE$366,$E$10),INDEX('Avalanche Schedule'!$AE$7:$AE$366,$E$10))) | E21: =IF(B21="","",IF('Start Here'!$C$7="Snowball",'My Debts'!$F$15,'My Debts'!$G$15)) | G21: =IF(ISNA(MATCH(1,IF('Start Here'!$C$7="Snowball",'My Debts'!$F$6:$F$15,'My Debts'!$G$6:$G$15),0)),"",1) -> 1 | H21: =IF(G21="","",INDEX('My Debts'!$B$6:$B$15,MATCH(1,IF('Start Here'!$C$7="Snowball",'My Debts'!$F$6:$F$15,'My Debts'!$G$6:$G$15),0))) -> Store card (example) | I21: =IF(G21="","",INDEX('My Debts'!$H$6:$H$15,MATCH(1,IF('Start Here'!$C$7="Snowball",'My Debts'!$F$6:$F$15,'My Debts'!$G$6:$G$15),0))) -> 46327 | J21: =IF(G21="","",INDEX('My Debts'!$I$6:$I$15,MATCH(1,IF('Start Here'!$C$7="Snowball",'My Debts'!$F$6:$F$15,'My Debts'!$G$6:$G$15),0))) -> 20.56
B22: Total | C22: =SUM(C12:C21) -> 1200 | D22: =SUM(D12:D21) -> 13804.19 | G22: =IF(ISNA(MATCH(2,IF('Start Here'!$C$7="Snowball",'My Debts'!$F$6:$F$15,'My Debts'!$G$6:$G$15),0)),"",2) -> 2 | H22: =IF(G22="","",INDEX('My Debts'!$B$6:$B$15,MATCH(2,IF('Start Here'!$C$7="Snowball",'My Debts'!$F$6:$F$15,'My Debts'!$G$6:$G$15),0))) -> Visa (example) | I22: =IF(G22="","",INDEX('My Debts'!$H$6:$H$15,MATCH(2,IF('Start Here'!$C$7="Snowball",'My Debts'!$F$6:$F$15,'My Debts'!$G$6:$G$15),0))) -> 46447 | J22: =IF(G22="","",INDEX('My Debts'!$I$6:$I$15,MATCH(2,IF('Start Here'!$C$7="Snowball",'My Debts'!$F$6:$F$15,'My Debts'!$G$6:$G$15),0))) -> 314.6
G23: =IF(ISNA(MATCH(3,IF('Start Here'!$C$7="Snowball",'My Debts'!$F$6:$F$15,'My Debts'!$G$6:$G$15),0)),"",3) -> 3 | H23: =IF(G23="","",INDEX('My Debts'!$B$6:$B$15,MATCH(3,IF('Start Here'!$C$7="Snowball",'My Debts'!$F$6:$F$15,'My Debts'!$G$6:$G$15),0))) -> Car loan (example) | I23: =IF(G23="","",INDEX('My Debts'!$H$6:$H$15,MATCH(3,IF('Start Here'!$C$7="Snowball",'My Debts'!$F$6:$F$15,'My Debts'!$G$6:$G$15),0))) -> 46692 | J23: =IF(G23="","",INDEX('My Debts'!$I$6:$I$15,MATCH(3,IF('Start Here'!$C$7="Snowball",'My Debts'!$F$6:$F$15,'My Debts'!$G$6:$G$15),0))) -> 512.52
G24: =IF(ISNA(MATCH(4,IF('Start Here'!$C$7="Snowball",'My Debts'!$F$6:$F$15,'My Debts'!$G$6:$G$15),0)),"",4) | H24: =IF(G24="","",INDEX('My Debts'!$B$6:$B$15,MATCH(4,IF('Start Here'!$C$7="Snowball",'My Debts'!$F$6:$F$15,'My Debts'!$G$6:$G$15),0))) | I24: =IF(G24="","",INDEX('My Debts'!$H$6:$H$15,MATCH(4,IF('Start Here'!$C$7="Snowball",'My Debts'!$F$6:$F$15,'My Debts'!$G$6:$G$15),0))) | J24: =IF(G24="","",INDEX('My Debts'!$I$6:$I$15,MATCH(4,IF('Start Here'!$C$7="Snowball",'My Debts'!$F$6:$F$15,'My Debts'!$G$6:$G$15),0)))
G25: =IF(ISNA(MATCH(5,IF('Start Here'!$C$7="Snowball",'My Debts'!$F$6:$F$15,'My Debts'!$G$6:$G$15),0)),"",5) | H25: =IF(G25="","",INDEX('My Debts'!$B$6:$B$15,MATCH(5,IF('Start Here'!$C$7="Snowball",'My Debts'!$F$6:$F$15,'My Debts'!$G$6:$G$15),0))) | I25: =IF(G25="","",INDEX('My Debts'!$H$6:$H$15,MATCH(5,IF('Start Here'!$C$7="Snowball",'My Debts'!$F$6:$F$15,'My Debts'!$G$6:$G$15),0))) | J25: =IF(G25="","",INDEX('My Debts'!$I$6:$I$15,MATCH(5,IF('Start Here'!$C$7="Snowball",'My Debts'!$F$6:$F$15,'My Debts'!$G$6:$G$15),0)))
G26: =IF(ISNA(MATCH(6,IF('Start Here'!$C$7="Snowball",'My Debts'!$F$6:$F$15,'My Debts'!$G$6:$G$15),0)),"",6) | H26: =IF(G26="","",INDEX('My Debts'!$B$6:$B$15,MATCH(6,IF('Start Here'!$C$7="Snowball",'My Debts'!$F$6:$F$15,'My Debts'!$G$6:$G$15),0))) | I26: =IF(G26="","",INDEX('My Debts'!$H$6:$H$15,MATCH(6,IF('Start Here'!$C$7="Snowball",'My Debts'!$F$6:$F$15,'My Debts'!$G$6:$G$15),0))) | J26: =IF(G26="","",INDEX('My Debts'!$I$6:$I$15,MATCH(6,IF('Start Here'!$C$7="Snowball",'My Debts'!$F$6:$F$15,'My Debts'!$G$6:$G$15),0)))
G27: =IF(ISNA(MATCH(7,IF('Start Here'!$C$7="Snowball",'My Debts'!$F$6:$F$15,'My Debts'!$G$6:$G$15),0)),"",7) | H27: =IF(G27="","",INDEX('My Debts'!$B$6:$B$15,MATCH(7,IF('Start Here'!$C$7="Snowball",'My Debts'!$F$6:$F$15,'My Debts'!$G$6:$G$15),0))) | I27: =IF(G27="","",INDEX('My Debts'!$H$6:$H$15,MATCH(7,IF('Start Here'!$C$7="Snowball",'My Debts'!$F$6:$F$15,'My Debts'!$G$6:$G$15),0))) | J27: =IF(G27="","",INDEX('My Debts'!$I$6:$I$15,MATCH(7,IF('Start Here'!$C$7="Snowball",'My Debts'!$F$6:$F$15,'My Debts'!$G$6:$G$15),0)))
G28: =IF(ISNA(MATCH(8,IF('Start Here'!$C$7="Snowball",'My Debts'!$F$6:$F$15,'My Debts'!$G$6:$G$15),0)),"",8) | H28: =IF(G28="","",INDEX('My Debts'!$B$6:$B$15,MATCH(8,IF('Start Here'!$C$7="Snowball",'My Debts'!$F$6:$F$15,'My Debts'!$G$6:$G$15),0))) | I28: =IF(G28="","",INDEX('My Debts'!$H$6:$H$15,MATCH(8,IF('Start Here'!$C$7="Snowball",'My Debts'!$F$6:$F$15,'My Debts'!$G$6:$G$15),0))) | J28: =IF(G28="","",INDEX('My Debts'!$I$6:$I$15,MATCH(8,IF('Start Here'!$C$7="Snowball",'My Debts'!$F$6:$F$15,'My Debts'!$G$6:$G$15),0)))
G29: =IF(ISNA(MATCH(9,IF('Start Here'!$C$7="Snowball",'My Debts'!$F$6:$F$15,'My Debts'!$G$6:$G$15),0)),"",9) | H29: =IF(G29="","",INDEX('My Debts'!$B$6:$B$15,MATCH(9,IF('Start Here'!$C$7="Snowball",'My Debts'!$F$6:$F$15,'My Debts'!$G$6:$G$15),0))) | I29: =IF(G29="","",INDEX('My Debts'!$H$6:$H$15,MATCH(9,IF('Start Here'!$C$7="Snowball",'My Debts'!$F$6:$F$15,'My Debts'!$G$6:$G$15),0))) | J29: =IF(G29="","",INDEX('My Debts'!$I$6:$I$15,MATCH(9,IF('Start Here'!$C$7="Snowball",'My Debts'!$F$6:$F$15,'My Debts'!$G$6:$G$15),0)))
G30: =IF(ISNA(MATCH(10,IF('Start Here'!$C$7="Snowball",'My Debts'!$F$6:$F$15,'My Debts'!$G$6:$G$15),0)),"",10) | H30: =IF(G30="","",INDEX('My Debts'!$B$6:$B$15,MATCH(10,IF('Start Here'!$C$7="Snowball",'My Debts'!$F$6:$F$15,'My Debts'!$G$6:$G$15),0))) | I30: =IF(G30="","",INDEX('My Debts'!$H$6:$H$15,MATCH(10,IF('Start Here'!$C$7="Snowball",'My Debts'!$F$6:$F$15,'My Debts'!$G$6:$G$15),0))) | J30: =IF(G30="","",INDEX('My Debts'!$I$6:$I$15,MATCH(10,IF('Start Here'!$C$7="Snowball",'My Debts'!$F$6:$F$15,'My Debts'!$G$6:$G$15),0)))
B33: BALANCE OVER TIME

Sheet My Debts
A1: My Debts
A2: Enter up to 10 debts. Yellow cells are yours; grey cells calculate automatically.
B5: Debt name | C5: Balance ($) | D5: APR | E5: Minimum payment ($) | F5: Snowball order | G5: Avalanche order | H5: Paid off (your plan) | I5: Interest paid (your plan)
B6: Store card (example) | C6: 850 | D6: 0.2699 | E6: 35 | F6: =IF(C6="",99,SUMPRODUCT(--($C$6:$C$15<>""),--($C$6:$C$15<C6))+COUNTIF($C$6:C6,C6)) -> 1 | G6: =IF(C6="",99,SUMPRODUCT(--($C$6:$C$15<>""),--($D$6:$D$15>D6))+COUNTIF($D$6:D6,D6)) -> 1 | H6: =IF(C6="","",IF(IF('Start Here'!$C$7="Snowball",COUNTIF('Snowball Schedule'!$V$7:$V$366,">0.005")+1,COUNTIF('Avalanche Schedule'!$V$7:$V$366,">0.005")+1)>360,"30+ years",DATE(YEAR('Start Here'!$C$6),MONTH('Start Here'!$C$6)+IF('Start Here'!$C$7="Snowball",COUNTIF('Snowball Schedule'!$V$7:$V$366,">0.005")+1,COUNTIF('Avalanche Schedule'!$V$7:$V$366,">0.005")+1)-1,1))) -> 46327 | I6: =IF(C6="","",IF('Start Here'!$C$7="Snowball",SUM('Snowball Schedule'!$B$7:$B$366)-SUM('Snowball Schedule'!$V$6:$V$365),SUM('Avalanche Schedule'!$B$7:$B$366)-SUM('Avalanche Schedule'!$V$6:$V$365))) -> 20.56
B7: Visa (example) | C7: 4200 | D7: 0.2249 | E7: 110 | F7: =IF(C7="",99,SUMPRODUCT(--($C$6:$C$15<>""),--($C$6:$C$15<C7))+COUNTIF($C$6:C7,C7)) -> 2 | G7: =IF(C7="",99,SUMPRODUCT(--($C$6:$C$15<>""),--($D$6:$D$15>D7))+COUNTIF($D$6:D7,D7)) -> 2 | H7: =IF(C7="","",IF(IF('Start Here'!$C$7="Snowball",COUNTIF('Snowball Schedule'!$W$7:$W$366,">0.005")+1,COUNTIF('Avalanche Schedule'!$W$7:$W$366,">0.005")+1)>360,"30+ years",DATE(YEAR('Start Here'!$C$6),MONTH('Start Here'!$C$6)+IF('Start Here'!$C$7="Snowball",COUNTIF('Snowball Schedule'!$W$7:$W$366,">0.005")+1,COUNTIF('Avalanche Schedule'!$W$7:$W$366,">0.005")+1)-1,1))) -> 46447 | I7: =IF(C7="","",IF('Start Here'!$C$7="Snowball",SUM('Snowball Schedule'!$C$7:$C$366)-SUM('Snowball Schedule'!$W$6:$W$365),SUM('Avalanche Schedule'!$C$7:$C$366)-SUM('Avalanche Schedule'!$W$6:$W$365))) -> 314.6
B8: Car loan (example) | C8: 9800 | D8: 0.069 | E8: 285 | F8: =IF(C8="",99,SUMPRODUCT(--($C$6:$C$15<>""),--($C$6:$C$15<C8))+COUNTIF($C$6:C8,C8)) -> 3 | G8: =IF(C8="",99,SUMPRODUCT(--($C$6:$C$15<>""),--($D$6:$D$15>D8))+COUNTIF($D$6:D8,D8)) -> 3 | H8: =IF(C8="","",IF(IF('Start Here'!$C$7="Snowball",COUNTIF('Snowball Schedule'!$X$7:$X$366,">0.005")+1,COUNTIF('Avalanche Schedule'!$X$7:$X$366,">0.005")+1)>360,"30+ years",DATE(YEAR('Start Here'!$C$6),MONTH('Start Here'!$C$6)+IF('Start Here'!$C$7="Snowball",COUNTIF('Snowball Schedule'!$X$7:$X$366,">0.005")+1,COUNTIF('Avalanche Schedule'!$X$7:$X$366,">0.005")+1)-1,1))) -> 46692 | I8: =IF(C8="","",IF('Start Here'!$C$7="Snowball",SUM('Snowball Schedule'!$D$7:$D$366)-SUM('Snowball Schedule'!$X$6:$X$365),SUM('Avalanche Schedule'!$D$7:$D$366)-SUM('Avalanche Schedule'!$X$6:$X$365))) -> 512.52
F9: =IF(C9="",99,SUMPRODUCT(--($C$6:$C$15<>""),--($C$6:$C$15<C9))+COUNTIF($C$6:C9,C9)) -> 99 | G9: =IF(C9="",99,SUMPRODUCT(--($C$6:$C$15<>""),--($D$6:$D$15>D9))+COUNTIF($D$6:D9,D9)) -> 99 | H9: =IF(C9="","",IF(IF('Start Here'!$C$7="Snowball",COUNTIF('Snowball Schedule'!$Y$7:$Y$366,">0.005")+1,COUNTIF('Avalanche Schedule'!$Y$7:$Y$366,">0.005")+1)>360,"30+ years",DATE(YEAR('Start Here'!$C$6),MONTH('Start Here'!$C$6)+IF('Start Here'!$C$7="Snowball",COUNTIF('Snowball Schedule'!$Y$7:$Y$366,">0.005")+1,COUNTIF('Avalanche Schedule'!$Y$7:$Y$366,">0.005")+1)-1,1))) | I9: =IF(C9="","",IF('Start Here'!$C$7="Snowball",SUM('Snowball Schedule'!$E$7:$E$366)-SUM('Snowball Schedule'!$Y$6:$Y$365),SUM('Avalanche Schedule'!$E$7:$E$366)-SUM('Avalanche Schedule'!$Y$6:$Y$365)))
F10: =IF(C10="",99,SUMPRODUCT(--($C$6:$C$15<>""),--($C$6:$C$15<C10))+COUNTIF($C$6:C10,C10)) -> 99 | G10: =IF(C10="",99,SUMPRODUCT(--($C$6:$C$15<>""),--($D$6:$D$15>D10))+COUNTIF($D$6:D10,D10)) -> 99 | H10: =IF(C10="","",IF(IF('Start Here'!$C$7="Snowball",COUNTIF('Snowball Schedule'!$Z$7:$Z$366,">0.005")+1,COUNTIF('Avalanche Schedule'!$Z$7:$Z$366,">0.005")+1)>360,"30+ years",DATE(YEAR('Start Here'!$C$6),MONTH('Start Here'!$C$6)+IF('Start Here'!$C$7="Snowball",COUNTIF('Snowball Schedule'!$Z$7:$Z$366,">0.005")+1,COUNTIF('Avalanche Schedule'!$Z$7:$Z$366,">0.005")+1)-1,1))) | I10: =IF(C10="","",IF('Start Here'!$C$7="Snowball",SUM('Snowball Schedule'!$F$7:$F$366)-SUM('Snowball Schedule'!$Z$6:$Z$365),SUM('Avalanche Schedule'!$F$7:$F$366)-SUM('Avalanche Schedule'!$Z$6:$Z$365)))
F11: =IF(C11="",99,SUMPRODUCT(--($C$6:$C$15<>""),--($C$6:$C$15<C11))+COUNTIF($C$6:C11,C11)) -> 99 | G11: =IF(C11="",99,SUMPRODUCT(--($C$6:$C$15<>""),--($D$6:$D$15>D11))+COUNTIF($D$6:D11,D11)) -> 99 | H11: =IF(C11="","",IF(IF('Start Here'!$C$7="Snowball",COUNTIF('Snowball Schedule'!$AA$7:$AA$366,">0.005")+1,COUNTIF('Avalanche Schedule'!$AA$7:$AA$366,">0.005")+1)>360,"30+ years",DATE(YEAR('Start Here'!$C$6),MONTH('Start Here'!$C$6)+IF('Start Here'!$C$7="Snowball",COUNTIF('Snowball Schedule'!$AA$7:$AA$366,">0.005")+1,COUNTIF('Avalanche Schedule'!$AA$7:$AA$366,">0.005")+1)-1,1))) | I11: =IF(C11="","",IF('Start Here'!$C$7="Snowball",SUM('Snowball Schedule'!$G$7:$G$366)-SUM('Snowball Schedule'!$AA$6:$AA$365),SUM('Avalanche Schedule'!$G$7:$G$366)-SUM('Avalanche Schedule'!$AA$6:$AA$365)))
F12: =IF(C12="",99,SUMPRODUCT(--($C$6:$C$15<>""),--($C$6:$C$15<C12))+COUNTIF($C$6:C12,C12)) -> 99 | G12: =IF(C12="",99,SUMPRODUCT(--($C$6:$C$15<>""),--($D$6:$D$15>D12))+COUNTIF($D$6:D12,D12)) -> 99 | H12: =IF(C12="","",IF(IF('Start Here'!$C$7="Snowball",COUNTIF('Snowball Schedule'!$AB$7:$AB$366,">0.005")+1,COUNTIF('Avalanche Schedule'!$AB$7:$AB$366,">0.005")+1)>360,"30+ years",DATE(YEAR('Start Here'!$C$6),MONTH('Start Here'!$C$6)+IF('Start Here'!$C$7="Snowball",COUNTIF('Snowball Schedule'!$AB$7:$AB$366,">0.005")+1,COUNTIF('Avalanche Schedule'!$AB$7:$AB$366,">0.005")+1)-1,1))) | I12: =IF(C12="","",IF('Start Here'!$C$7="Snowball",SUM('Snowball Schedule'!$H$7:$H$366)-SUM('Snowball Schedule'!$AB$6:$AB$365),SUM('Avalanche Schedule'!$H$7:$H$366)-SUM('Avalanche Schedule'!$AB$6:$AB$365)))
F13: =IF(C13="",99,SUMPRODUCT(--($C$6:$C$15<>""),--($C$6:$C$15<C13))+COUNTIF($C$6:C13,C13)) -> 99 | G13: =IF(C13="",99,SUMPRODUCT(--($C$6:$C$15<>""),--($D$6:$D$15>D13))+COUNTIF($D$6:D13,D13)) -> 99 | H13: =IF(C13="","",IF(IF('Start Here'!$C$7="Snowball",COUNTIF('Snowball Schedule'!$AC$7:$AC$366,">0.005")+1,COUNTIF('Avalanche Schedule'!$AC$7:$AC$366,">0.005")+1)>360,"30+ years",DATE(YEAR('Start Here'!$C$6),MONTH('Start Here'!$C$6)+IF('Start Here'!$C$7="Snowball",COUNTIF('Snowball Schedule'!$AC$7:$AC$366,">0.005")+1,COUNTIF('Avalanche Schedule'!$AC$7:$AC$366,">0.005")+1)-1,1))) | I13: =IF(C13="","",IF('Start Here'!$C$7="Snowball",SUM('Snowball Schedule'!$I$7:$I$366)-SUM('Snowball Schedule'!$AC$6:$AC$365),SUM('Avalanche Schedule'!$I$7:$I$366)-SUM('Avalanche Schedule'!$AC$6:$AC$365)))
F14: =IF(C14="",99,SUMPRODUCT(--($C$6:$C$15<>""),--($C$6:$C$15<C14))+COUNTIF($C$6:C14,C14)) -> 99 | G14: =IF(C14="",99,SUMPRODUCT(--($C$6:$C$15<>""),--($D$6:$D$15>D14))+COUNTIF($D$6:D14,D14)) -> 99 | H14: =IF(C14="","",IF(IF('Start Here'!$C$7="Snowball",COUNTIF('Snowball Schedule'!$AD$7:$AD$366,">0.005")+1,COUNTIF('Avalanche Schedule'!$AD$7:$AD$366,">0.005")+1)>360,"30+ years",DATE(YEAR('Start Here'!$C$6),MONTH('Start Here'!$C$6)+IF('Start Here'!$C$7="Snowball",COUNTIF('Snowball Schedule'!$AD$7:$AD$366,">0.005")+1,COUNTIF('Avalanche Schedule'!$AD$7:$AD$366,">0.005")+1)-1,1))) | I14: =IF(C14="","",IF('Start Here'!$C$7="Snowball",SUM('Snowball Schedule'!$J$7:$J$366)-SUM('Snowball Schedule'!$AD$6:$AD$365),SUM('Avalanche Schedule'!$J$7:$J$366)-SUM('Avalanche Schedule'!$AD$6:$AD$365)))
F15: =IF(C15="",99,SUMPRODUCT(--($C$6:$C$15<>""),--($C$6:$C$15<C15))+COUNTIF($C$6:C15,C15)) -> 99 | G15: =IF(C15="",99,SUMPRODUCT(--($C$6:$C$15<>""),--($D$6:$D$15>D15))+COUNTIF($D$6:D15,D15)) -> 99 | H15: =IF(C15="","",IF(IF('Start Here'!$C$7="Snowball",COUNTIF('Snowball Schedule'!$AE$7:$AE$366,">0.005")+1,COUNTIF('Avalanche Schedule'!$AE$7:$AE$366,">0.005")+1)>360,"30+ years",DATE(YEAR('Start Here'!$C$6),MONTH('Start Here'!$C$6)+IF('Start Here'!$C$7="Snowball",COUNTIF('Snowball Schedule'!$AE$7:$AE$366,">0.005")+1,COUNTIF('Avalanche Schedule'!$AE$7:$AE$366,">0.005")+1)-1,1))) | I15: =IF(C15="","",IF('Start Here'!$C$7="Snowball",SUM('Snowball Schedule'!$K$7:$K$366)-SUM('Snowball Schedule'!$AE$6:$AE$365),SUM('Avalanche Schedule'!$K$7:$K$366)-SUM('Avalanche Schedule'!$AE$6:$AE$365)))
B16: Total | C16: =SUM(C6:C15) -> 14850 | D16: =IF(C16>0,SUMPRODUCT(C6:C15,D6:D15)/C16,0) -> 0.12459226 | E16: =SUM(E6:E15) -> 430
B18: Delete the example rows and enter your own debts. Rows left blank are ignored.

Sheet Snowball Schedule
A1: Snowball Schedule
A2: Month-by-month simulation. No need to edit this tab.
A4: Priority | B4: ='My Debts'!$F$6 -> 1 | C4: ='My Debts'!$F$7 -> 2 | D4: ='My Debts'!$F$8 -> 3 | E4: ='My Debts'!$F$9 -> 99 | F4: ='My Debts'!$F$10 -> 99 | G4: ='My Debts'!$F$11 -> 99 | H4: ='My Debts'!$F$12 -> 99 | I4: ='My Debts'!$F$13 -> 99 | J4: ='My Debts'!$F$14 -> 99 | K4: ='My Debts'!$F$15 -> 99
A5: Month | B5: =IF('My Debts'!$B$6="","Debt 1",'My Debts'!$B$6)&" · Owed" -> Store card (example) · Owed | C5: =IF('My Debts'!$B$7="","Debt 2",'My Debts'!$B$7)&" · Owed" -> Visa (example) · Owed | D5: =IF('My Debts'!$B$8="","Debt 3",'My Debts'!$B$8)&" · Owed" -> Car loan (example) · Owed | E5: =IF('My Debts'!$B$9="","Debt 4",'My Debts'!$B$9)&" · Owed" -> Debt 4 · Owed | F5: =IF('My Debts'!$B$10="","Debt 5",'My Debts'!$B$10)&" · Owed" -> Debt 5 · Owed | G5: =IF('My Debts'!$B$11="","Debt 6",'My Debts'!$B$11)&" · Owed" -> Debt 6 · Owed | H5: =IF('My Debts'!$B$12="","Debt 7",'My Debts'!$B$12)&" · Owed" -> Debt 7 · Owed | I5: =IF('My Debts'!$B$13="","Debt 8",'My Debts'!$B$13)&" · Owed" -> Debt 8 · Owed | J5: =IF('My Debts'!$B$14="","Debt 9",'My Debts'!$B$14)&" · Owed" -> Debt 9 · Owed | K5: =IF('My Debts'!$B$15="","Debt 10",'My Debts'!$B$15)&" · Owed" -> Debt 10 · Owed | L5: =IF('My Debts'!$B$6="","Debt 1",'My Debts'!$B$6)&" · Minimum" -> Store card (example) · Minimum | M5: =IF('My Debts'!$B$7="","Debt 2",'My Debts'!$B$7)&" · Minimum" -> Visa (example) · Minimum | N5: =IF('My Debts'!$B$8="","Debt 3",'My Debts'!$B$8)&" · Minimum" -> Car loan (example) · Minimum | O5: =IF('My Debts'!$B$9="","Debt 4",'My Debts'!$B$9)&" · Minimum" -> Debt 4 · Minimum | P5: =IF('My Debts'!$B$10="","Debt 5",'My Debts'!$B$10)&" · Minimum" -> Debt 5 · Minimum | Q5: =IF('My Debts'!$B$11="","Debt 6",'My Debts'!$B$11)&" · Minimum" -> Debt 6 · Minimum | R5: =IF('My Debts'!$B$12="","Debt 7",'My Debts'!$B$12)&" · Minimum" -> Debt 7 · Minimum | S5: =IF('My Debts'!$B$13="","Debt 8",'My Debts'!$B$13)&" · Minimum" -> Debt 8 · Minimum | T5: =IF('My Debts'!$B$14="","Debt 9",'My Debts'!$B$14)&" · Minimum" -> Debt 9 · Minimum | U5: =IF('My Debts'!$B$15="","Debt 10",'My Debts'!$B$15)&" · Minimum" -> Debt 10 · Minimum | V5: =IF('My Debts'!$B$6="","Debt 1",'My Debts'!$B$6)&" · End balance" -> Store card (example) · End balance | W5: =IF('My Debts'!$B$7="","Debt 2",'My Debts'!$B$7)&" · End balance" -> Visa (example) · End balance | X5: =IF('My Debts'!$B$8="","Debt 3",'My Debts'!$B$8)&" · End balance" -> Car loan (example) · End balance | Y5: =IF('My Debts'!$B$9="","Debt 4",'My Debts'!$B$9)&" · End balance" -> Debt 4 · End balance | Z5: =IF('My Debts'!$B$10="","Debt 5",'My Debts'!$B$10)&" · End balance" -> Debt 5 · End balance | AA5: =IF('My Debts'!$B$11="","Debt 6",'My Debts'!$B$11)&" · End balance" -> Debt 6 · End balance | AB5: =IF('My Debts'!$B$12="","Debt 7",'My Debts'!$B$12)&" · End balance" -> Debt 7 · End balance | AC5: =IF('My Debts'!$B$13="","Debt 8",'My Debts'!$B$13)&" · End balance" -> Debt 8 · End balance | AD5: =IF('My Debts'!$B$14="","Debt 9",'My Debts'!$B$14)&" · End balance" -> Debt 9 · End balance | AE5: =IF('My Debts'!$B$15="","Debt 10",'My Debts'!$B$15)&" · End balance" -> Debt 10 · End balance | AF5: Extra available | AG5: Total balance | AH5: Interest this month
A6: Start | V6: =N('My Debts'!$C$6) -> 850 | W6: =N('My Debts'!$C$7) -> 4200 | X6: =N('My Debts'!$C$8) -> 9800 | Y6: =N('My Debts'!$C$9) -> 0 | Z6: =N('My Debts'!$C$10) -> 0 | AA6: =N('My Debts'!$C$11) -> 0 | AB6: =N('My Debts'!$C$12) -> 0 | AC6: =N('My Debts'!$C$13) -> 0 | AD6: =N('My Debts'!$C$14) -> 0 | AE6: =N('My Debts'!$C$15) -> 0 | AG6: =SUM(V6:AE6) -> 14850
A7: =DATE(YEAR('Start Here'!$C$6),MONTH('Start Here'!$C$6)+0,1) -> 46296 | B7: =ROUND(V6*(1+N('My Debts'!$D$6)/12),2) -> 869.12 | C7: =ROUND(W6*(1+N('My Debts'!$D$7)/12),2) -> 4278.72 | D7: =ROUND(X6*(1+N('My Debts'!$D$8)/12),2) -> 9856.35 | E7: =ROUND(Y6*(1+N('My Debts'!$D$9)/12),2) -> 0 | F7: =ROUND(Z6*(1+N('My Debts'!$D$10)/12),2) -> 0 | G7: =ROUND(AA6*(1+N('My Debts'!$D$11)/12),2) -> 0 | H7: =ROUND(AB6*(1+N('My Debts'!$D$12)/12),2) -> 0 | I7: =ROUND(AC6*(1+N('My Debts'!$D$13)/12),2) -> 0 | J7: =ROUND(AD6*(1+N('My Debts'!$D$14)/12),2) -> 0 | K7: =ROUND(AE6*(1+N('My Debts'!$D$15)/12),2) -> 0 | L7: =MIN(N('My Debts'!$E$6),B7) -> 35 | M7: =MIN(N('My Debts'!$E$7),C7) -> 110 | N7: =MIN(N('My Debts'!$E$8),D7) -> 285 | O7: =MIN(N('My Debts'!$E$9),E7) -> 0 | P7: =MIN(N('My Debts'!$E$10),F7) -> 0 | Q7: =MIN(N('My Debts'!$E$11),G7) -> 0 | R7: =MIN(N('My Debts'!$E$12),H7) -> 0 | S7: =MIN(N('My Debts'!$E$13),I7) -> 0 | T7: =MIN(N('My Debts'!$E$14),J7) -> 0 | U7: =MIN(N('My Debts'!$E$15),K7) -> 0 | V7: =ROUND(B7-L7-MIN(B7-L7,MAX(0,$AF7-SUMPRODUCT(--($B$4:$K$4<B$4),$B7:$K7-$L7:$U7))),2) -> 64.12 | W7: =ROUND(C7-M7-MIN(C7-M7,MAX(0,$AF7-SUMPRODUCT(--($B$4:$K$4<C$4),$B7:$K7-$L7:$U7))),2) -> 4168.72 | X7: =ROUND(D7-N7-MIN(D7-N7,MAX(0,$AF7-SUMPRODUCT(--($B$4:$K$4<D$4),$B7:$K7-$L7:$U7))),2) -> 9571.35 | Y7: =ROUND(E7-O7-MIN(E7-O7,MAX(0,$AF7-SUMPRODUCT(--($B$4:$K$4<E$4),$B7:$K7-$L7:$U7))),2) -> 0 | Z7: =ROUND(F7-P7-MIN(F7-P7,MAX(0,$AF7-SUMPRODUCT(--($B$4:$K$4<F$4),$B7:$K7-$L7:$U7))),2) -> 0 | AA7: =ROUND(G7-Q7-MIN(G7-Q7,MAX(0,$AF7-SUMPRODUCT(--($B$4:$K$4<G$4),$B7:$K7-$L7:$U7))),2) -> 0 | AB7: =ROUND(H7-R7-MIN(H7-R7,MAX(0,$AF7-SUMPRODUCT(--($B$4:$K$4<H$4),$B7:$K7-$L7:$U7))),2) -> 0 | AC7: =ROUND(I7-S7-MIN(I7-S7,MAX(0,$AF7-SUMPRODUCT(--($B$4:$K$4<I$4),$B7:$K7-$L7:$U7))),2) -> 0 | ... AE7: =ROUND(K7-U7-MIN(K7-U7,MAX(0,$AF7-SUMPRODUCT(--($B$4:$K$4<K$4),$B7:$K7-$L7:$U7))),2) -> 0 | AF7: =MAX(0,'Start Here'!$C$5-SUM($L7:$U7)) -> 770 | AG7: =SUM(V7:AE7) -> 13804.19 | AH7: =SUM(B7:K7)-AG6 -> 154.19
A8: =DATE(YEAR('Start Here'!$C$6),MONTH('Start Here'!$C$6)+1,1) -> 46327 | B8: =ROUND(V7*(1+N('My Debts'!$D$6)/12),2) -> 65.56 | C8: =ROUND(W7*(1+N('My Debts'!$D$7)/12),2) -> 4246.85 | D8: =ROUND(X7*(1+N('My Debts'!$D$8)/12),2) -> 9626.39 | E8: =ROUND(Y7*(1+N('My Debts'!$D$9)/12),2) -> 0 | F8: =ROUND(Z7*(1+N('My Debts'!$D$10)/12),2) -> 0 | G8: =ROUND(AA7*(1+N('My Debts'!$D$11)/12),2) -> 0 | H8: =ROUND(AB7*(1+N('My Debts'!$D$12)/12),2) -> 0 | I8: =ROUND(AC7*(1+N('My Debts'!$D$13)/12),2) -> 0 | J8: =ROUND(AD7*(1+N('My Debts'!$D$14)/12),2) -> 0 | K8: =ROUND(AE7*(1+N('My Debts'!$D$15)/12),2) -> 0 | L8: =MIN(N('My Debts'!$E$6),B8) -> 35 | M8: =MIN(N('My Debts'!$E$7),C8) -> 110 | N8: =MIN(N('My Debts'!$E$8),D8) -> 285 | O8: =MIN(N('My Debts'!$E$9),E8) -> 0 | P8: =MIN(N('My Debts'!$E$10),F8) -> 0 | Q8: =MIN(N('My Debts'!$E$11),G8) -> 0 | R8: =MIN(N('My Debts'!$E$12),H8) -> 0 | S8: =MIN(N('My Debts'!$E$13),I8) -> 0 | T8: =MIN(N('My Debts'!$E$14),J8) -> 0 | U8: =MIN(N('My Debts'!$E$15),K8) -> 0 | V8: =ROUND(B8-L8-MIN(B8-L8,MAX(0,$AF8-SUMPRODUCT(--($B$4:$K$4<B$4),$B8:$K8-$L8:$U8))),2) -> 0 | W8: =ROUND(C8-M8-MIN(C8-M8,MAX(0,$AF8-SUMPRODUCT(--($B$4:$K$4<C$4),$B8:$K8-$L8:$U8))),2) -> 3397.41 | X8: =ROUND(D8-N8-MIN(D8-N8,MAX(0,$AF8-SUMPRODUCT(--($B$4:$K$4<D$4),$B8:$K8-$L8:$U8))),2) -> 9341.39 | Y8: =ROUND(E8-O8-MIN(E8-O8,MAX(0,$AF8-SUMPRODUCT(--($B$4:$K$4<E$4),$B8:$K8-$L8:$U8))),2) -> 0 | Z8: =ROUND(F8-P8-MIN(F8-P8,MAX(0,$AF8-SUMPRODUCT(--($B$4:$K$4<F$4),$B8:$K8-$L8:$U8))),2) -> 0 | AA8: =ROUND(G8-Q8-MIN(G8-Q8,MAX(0,$AF8-SUMPRODUCT(--($B$4:$K$4<G$4),$B8:$K8-$L8:$U8))),2) -> 0 | AB8: =ROUND(H8-R8-MIN(H8-R8,MAX(0,$AF8-SUMPRODUCT(--($B$4:$K$4<H$4),$B8:$K8-$L8:$U8))),2) -> 0 | AC8: =ROUND(I8-S8-MIN(I8-S8,MAX(0,$AF8-SUMPRODUCT(--($B$4:$K$4<I$4),$B8:$K8-$L8:$U8))),2) -> 0 | ... AE8: =ROUND(K8-U8-MIN(K8-U8,MAX(0,$AF8-SUMPRODUCT(--($B$4:$K$4<K$4),$B8:$K8-$L8:$U8))),2) -> 0 | AF8: =MAX(0,'Start Here'!$C$5-SUM($L8:$U8)) -> 770 | AG8: =SUM(V8:AE8) -> 12738.8 | AH8: =SUM(B8:K8)-AG7 -> 134.61
A9: =DATE(YEAR('Start Here'!$C$6),MONTH('Start Here'!$C$6)+2,1) -> 46357 | B9: =ROUND(V8*(1+N('My Debts'!$D$6)/12),2) -> 0 | C9: =ROUND(W8*(1+N('My Debts'!$D$7)/12),2) -> 3461.08 | D9: =ROUND(X8*(1+N('My Debts'!$D$8)/12),2) -> 9395.1 | E9: =ROUND(Y8*(1+N('My Debts'!$D$9)/12),2) -> 0 | F9: =ROUND(Z8*(1+N('My Debts'!$D$10)/12),2) -> 0 | G9: =ROUND(AA8*(1+N('My Debts'!$D$11)/12),2) -> 0 | H9: =ROUND(AB8*(1+N('My Debts'!$D$12)/12),2) -> 0 | I9: =ROUND(AC8*(1+N('My Debts'!$D$13)/12),2) -> 0 | J9: =ROUND(AD8*(1+N('My Debts'!$D$14)/12),2) -> 0 | K9: =ROUND(AE8*(1+N('My Debts'!$D$15)/12),2) -> 0 | L9: =MIN(N('My Debts'!$E$6),B9) -> 0 | M9: =MIN(N('My Debts'!$E$7),C9) -> 110 | N9: =MIN(N('My Debts'!$E$8),D9) -> 285 | O9: =MIN(N('My Debts'!$E$9),E9) -> 0 | P9: =MIN(N('My Debts'!$E$10),F9) -> 0 | Q9: =MIN(N('My Debts'!$E$11),G9) -> 0 | R9: =MIN(N('My Debts'!$E$12),H9) -> 0 | S9: =MIN(N('My Debts'!$E$13),I9) -> 0 | T9: =MIN(N('My Debts'!$E$14),J9) -> 0 | U9: =MIN(N('My Debts'!$E$15),K9) -> 0 | V9: =ROUND(B9-L9-MIN(B9-L9,MAX(0,$AF9-SUMPRODUCT(--($B$4:$K$4<B$4),$B9:$K9-$L9:$U9))),2) -> 0 | W9: =ROUND(C9-M9-MIN(C9-M9,MAX(0,$AF9-SUMPRODUCT(--($B$4:$K$4<C$4),$B9:$K9-$L9:$U9))),2) -> 2546.08 | X9: =ROUND(D9-N9-MIN(D9-N9,MAX(0,$AF9-SUMPRODUCT(--($B$4:$K$4<D$4),$B9:$K9-$L9:$U9))),2) -> 9110.1 | Y9: =ROUND(E9-O9-MIN(E9-O9,MAX(0,$AF9-SUMPRODUCT(--($B$4:$K$4<E$4),$B9:$K9-$L9:$U9))),2) -> 0 | Z9: =ROUND(F9-P9-MIN(F9-P9,MAX(0,$AF9-SUMPRODUCT(--($B$4:$K$4<F$4),$B9:$K9-$L9:$U9))),2) -> 0 | AA9: =ROUND(G9-Q9-MIN(G9-Q9,MAX(0,$AF9-SUMPRODUCT(--($B$4:$K$4<G$4),$B9:$K9-$L9:$U9))),2) -> 0 | AB9: =ROUND(H9-R9-MIN(H9-R9,MAX(0,$AF9-SUMPRODUCT(--($B$4:$K$4<H$4),$B9:$K9-$L9:$U9))),2) -> 0 | AC9: =ROUND(I9-S9-MIN(I9-S9,MAX(0,$AF9-SUMPRODUCT(--($B$4:$K$4<I$4),$B9:$K9-$L9:$U9))),2) -> 0 | ... AE9: =ROUND(K9-U9-MIN(K9-U9,MAX(0,$AF9-SUMPRODUCT(--($B$4:$K$4<K$4),$B9:$K9-$L9:$U9))),2) -> 0 | AF9: =MAX(0,'Start Here'!$C$5-SUM($L9:$U9)) -> 805 | AG9: =SUM(V9:AE9) -> 11656.18 | AH9: =SUM(B9:K9)-AG8 -> 117.38
A10: =DATE(YEAR('Start Here'!$C$6),MONTH('Start Here'!$C$6)+3,1) -> 46388 | B10: =ROUND(V9*(1+N('My Debts'!$D$6)/12),2) -> 0 | C10: =ROUND(W9*(1+N('My Debts'!$D$7)/12),2) -> 2593.8 | D10: =ROUND(X9*(1+N('My Debts'!$D$8)/12),2) -> 9162.48 | E10: =ROUND(Y9*(1+N('My Debts'!$D$9)/12),2) -> 0 | F10: =ROUND(Z9*(1+N('My Debts'!$D$10)/12),2) -> 0 | G10: =ROUND(AA9*(1+N('My Debts'!$D$11)/12),2) -> 0 | H10: =ROUND(AB9*(1+N('My Debts'!$D$12)/12),2) -> 0 | I10: =ROUND(AC9*(1+N('My Debts'!$D$13)/12),2) -> 0 | J10: =ROUND(AD9*(1+N('My Debts'!$D$14)/12),2) -> 0 | K10: =ROUND(AE9*(1+N('My Debts'!$D$15)/12),2) -> 0 | L10: =MIN(N('My Debts'!$E$6),B10) -> 0 | M10: =MIN(N('My Debts'!$E$7),C10) -> 110 | N10: =MIN(N('My Debts'!$E$8),D10) -> 285 | O10: =MIN(N('My Debts'!$E$9),E10) -> 0 | P10: =MIN(N('My Debts'!$E$10),F10) -> 0 | Q10: =MIN(N('My Debts'!$E$11),G10) -> 0 | R10: =MIN(N('My Debts'!$E$12),H10) -> 0 | S10: =MIN(N('My Debts'!$E$13),I10) -> 0 | T10: =MIN(N('My Debts'!$E$14),J10) -> 0 | U10: =MIN(N('My Debts'!$E$15),K10) -> 0 | V10: =ROUND(B10-L10-MIN(B10-L10,MAX(0,$AF10-SUMPRODUCT(--($B$4:$K$4<B$4),$B10:$K10-$L10:$U10))),2) -> 0 | W10: =ROUND(C10-M10-MIN(C10-M10,MAX(0,$AF10-SUMPRODUCT(--($B$4:$K$4<C$4),$B10:$K10-$L10:$U10))),2) -> 1678.8 | X10: =ROUND(D10-N10-MIN(D10-N10,MAX(0,$AF10-SUMPRODUCT(--($B$4:$K$4<D$4),$B10:$K10-$L10:$U10))),2) -> 8877.48 | Y10: =ROUND(E10-O10-MIN(E10-O10,MAX(0,$AF10-SUMPRODUCT(--($B$4:$K$4<E$4),$B10:$K10-$L10:$U10))),2) -> 0 | Z10: =ROUND(F10-P10-MIN(F10-P10,MAX(0,$AF10-SUMPRODUCT(--($B$4:$K$4<F$4),$B10:$K10-$L10:$U10))),2) -> 0 | AA10: =ROUND(G10-Q10-MIN(G10-Q10,MAX(0,$AF10-SUMPRODUCT(--($B$4:$K$4<G$4),$B10:$K10-$L10:$U10))),2) -> 0 | AB10: =ROUND(H10-R10-MIN(H10-R10,MAX(0,$AF10-SUMPRODUCT(--($B$4:$K$4<H$4),$B10:$K10-$L10:$U10))),2) -> 0 | AC10: =ROUND(I10-S10-MIN(I10-S10,MAX(0,$AF10-SUMPRODUCT(--($B$4:$K$4<I$4),$B10:$K10-$L10:$U10))),2) -> 0 | ... AE10: =ROUND(K10-U10-MIN(K10-U10,MAX(0,$AF10-SUMPRODUCT(--($B$4:$K$4<K$4),$B10:$K10-$L10:$U10))),2) -> 0 | AF10: =MAX(0,'Start Here'!$C$5-SUM($L10:$U10)) -> 805 | AG10: =SUM(V10:AE10) -> 10556.28 | AH10: =SUM(B10:K10)-AG9 -> 100.1
A11: =DATE(YEAR('Start Here'!$C$6),MONTH('Start Here'!$C$6)+4,1) -> 46419 | B11: =ROUND(V10*(1+N('My Debts'!$D$6)/12),2) -> 0 | C11: =ROUND(W10*(1+N('My Debts'!$D$7)/12),2) -> 1710.26 | D11: =ROUND(X10*(1+N('My Debts'!$D$8)/12),2) -> 8928.53 | E11: =ROUND(Y10*(1+N('My Debts'!$D$9)/12),2) -> 0 | F11: =ROUND(Z10*(1+N('My Debts'!$D$10)/12),2) -> 0 | G11: =ROUND(AA10*(1+N('My Debts'!$D$11)/12),2) -> 0 | H11: =ROUND(AB10*(1+N('My Debts'!$D$12)/12),2) -> 0 | I11: =ROUND(AC10*(1+N('My Debts'!$D$13)/12),2) -> 0 | J11: =ROUND(AD10*(1+N('My Debts'!$D$14)/12),2) -> 0 | K11: =ROUND(AE10*(1+N('My Debts'!$D$15)/12),2) -> 0 | L11: =MIN(N('My Debts'!$E$6),B11) -> 0 | M11: =MIN(N('My Debts'!$E$7),C11) -> 110 | N11: =MIN(N('My Debts'!$E$8),D11) -> 285 | O11: =MIN(N('My Debts'!$E$9),E11) -> 0 | P11: =MIN(N('My Debts'!$E$10),F11) -> 0 | Q11: =MIN(N('My Debts'!$E$11),G11) -> 0 | R11: =MIN(N('My Debts'!$E$12),H11) -> 0 | S11: =MIN(N('My Debts'!$E$13),I11) -> 0 | T11: =MIN(N('My Debts'!$E$14),J11) -> 0 | U11: =MIN(N('My Debts'!$E$15),K11) -> 0 | V11: =ROUND(B11-L11-MIN(B11-L11,MAX(0,$AF11-SUMPRODUCT(--($B$4:$K$4<B$4),$B11:$K11-$L11:$U11))),2) -> 0 | W11: =ROUND(C11-M11-MIN(C11-M11,MAX(0,$AF11-SUMPRODUCT(--($B$4:$K$4<C$4),$B11:$K11-$L11:$U11))),2) -> 795.26 | X11: =ROUND(D11-N11-MIN(D11-N11,MAX(0,$AF11-SUMPRODUCT(--($B$4:$K$4<D$4),$B11:$K11-$L11:$U11))),2) -> 8643.53 | Y11: =ROUND(E11-O11-MIN(E11-O11,MAX(0,$AF11-SUMPRODUCT(--($B$4:$K$4<E$4),$B11:$K11-$L11:$U11))),2) -> 0 | Z11: =ROUND(F11-P11-MIN(F11-P11,MAX(0,$AF11-SUMPRODUCT(--($B$4:$K$4<F$4),$B11:$K11-$L11:$U11))),2) -> 0 | AA11: =ROUND(G11-Q11-MIN(G11-Q11,MAX(0,$AF11-SUMPRODUCT(--($B$4:$K$4<G$4),$B11:$K11-$L11:$U11))),2) -> 0 | AB11: =ROUND(H11-R11-MIN(H11-R11,MAX(0,$AF11-SUMPRODUCT(--($B$4:$K$4<H$4),$B11:$K11-$L11:$U11))),2) -> 0 | AC11: =ROUND(I11-S11-MIN(I11-S11,MAX(0,$AF11-SUMPRODUCT(--($B$4:$K$4<I$4),$B11:$K11-$L11:$U11))),2) -> 0 | ... AE11: =ROUND(K11-U11-MIN(K11-U11,MAX(0,$AF11-SUMPRODUCT(--($B$4:$K$4<K$4),$B11:$K11-$L11:$U11))),2) -> 0 | AF11: =MAX(0,'Start Here'!$C$5-SUM($L11:$U11)) -> 805 | AG11: =SUM(V11:AE11) -> 9438.79 | AH11: =SUM(B11:K11)-AG10 -> 82.51
A12: =DATE(YEAR('Start Here'!$C$6),MONTH('Start Here'!$C$6)+5,1) -> 46447 | B12: =ROUND(V11*(1+N('My Debts'!$D$6)/12),2) -> 0 | C12: =ROUND(W11*(1+N('My Debts'!$D$7)/12),2) -> 810.16 | D12: =ROUND(X11*(1+N('My Debts'!$D$8)/12),2) -> 8693.23 | E12: =ROUND(Y11*(1+N('My Debts'!$D$9)/12),2) -> 0 | F12: =ROUND(Z11*(1+N('My Debts'!$D$10)/12),2) -> 0 | G12: =ROUND(AA11*(1+N('My Debts'!$D$11)/12),2) -> 0 | H12: =ROUND(AB11*(1+N('My Debts'!$D$12)/12),2) -> 0 | I12: =ROUND(AC11*(1+N('My Debts'!$D$13)/12),2) -> 0 | J12: =ROUND(AD11*(1+N('My Debts'!$D$14)/12),2) -> 0 | K12: =ROUND(AE11*(1+N('My Debts'!$D$15)/12),2) -> 0 | L12: =MIN(N('My Debts'!$E$6),B12) -> 0 | M12: =MIN(N('My Debts'!$E$7),C12) -> 110 | N12: =MIN(N('My Debts'!$E$8),D12) -> 285 | O12: =MIN(N('My Debts'!$E$9),E12) -> 0 | P12: =MIN(N('My Debts'!$E$10),F12) -> 0 | Q12: =MIN(N('My Debts'!$E$11),G12) -> 0 | R12: =MIN(N('My Debts'!$E$12),H12) -> 0 | S12: =MIN(N('My Debts'!$E$13),I12) -> 0 | T12: =MIN(N('My Debts'!$E$14),J12) -> 0 | U12: =MIN(N('My Debts'!$E$15),K12) -> 0 | V12: =ROUND(B12-L12-MIN(B12-L12,MAX(0,$AF12-SUMPRODUCT(--($B$4:$K$4<B$4),$B12:$K12-$L12:$U12))),2) -> 0 | W12: =ROUND(C12-M12-MIN(C12-M12,MAX(0,$AF12-SUMPRODUCT(--($B$4:$K$4<C$4),$B12:$K12-$L12:$U12))),2) -> 0 | X12: =ROUND(D12-N12-MIN(D12-N12,MAX(0,$AF12-SUMPRODUCT(--($B$4:$K$4<D$4),$B12:$K12-$L12:$U12))),2) -> 8303.39 | Y12: =ROUND(E12-O12-MIN(E12-O12,MAX(0,$AF12-SUMPRODUCT(--($B$4:$K$4<E$4),$B12:$K12-$L12:$U12))),2) -> 0 | Z12: =ROUND(F12-P12-MIN(F12-P12,MAX(0,$AF12-SUMPRODUCT(--($B$4:$K$4<F$4),$B12:$K12-$L12:$U12))),2) -> 0 | AA12: =ROUND(G12-Q12-MIN(G12-Q12,MAX(0,$AF12-SUMPRODUCT(--($B$4:$K$4<G$4),$B12:$K12-$L12:$U12))),2) -> 0 | AB12: =ROUND(H12-R12-MIN(H12-R12,MAX(0,$AF12-SUMPRODUCT(--($B$4:$K$4<H$4),$B12:$K12-$L12:$U12))),2) -> 0 | AC12: =ROUND(I12-S12-MIN(I12-S12,MAX(0,$AF12-SUMPRODUCT(--($B$4:$K$4<I$4),$B12:$K12-$L12:$U12))),2) -> 0 | ... AE12: =ROUND(K12-U12-MIN(K12-U12,MAX(0,$AF12-SUMPRODUCT(--($B$4:$K$4<K$4),$B12:$K12-$L12:$U12))),2) -> 0 | AF12: =MAX(0,'Start Here'!$C$5-SUM($L12:$U12)) -> 805 | AG12: =SUM(V12:AE12) -> 8303.39 | AH12: =SUM(B12:K12)-AG11 -> 64.6
A13: =DATE(YEAR('Start Here'!$C$6),MONTH('Start Here'!$C$6)+6,1) -> 46478 | B13: =ROUND(V12*(1+N('My Debts'!$D$6)/12),2) -> 0 | C13: =ROUND(W12*(1+N('My Debts'!$D$7)/12),2) -> 0 | D13: =ROUND(X12*(1+N('My Debts'!$D$8)/12),2) -> 8351.13 | E13: =ROUND(Y12*(1+N('My Debts'!$D$9)/12),2) -> 0 | F13: =ROUND(Z12*(1+N('My Debts'!$D$10)/12),2) -> 0 | G13: =ROUND(AA12*(1+N('My Debts'!$D$11)/12),2) -> 0 | H13: =ROUND(AB12*(1+N('My Debts'!$D$12)/12),2) -> 0 | I13: =ROUND(AC12*(1+N('My Debts'!$D$13)/12),2) -> 0 | J13: =ROUND(AD12*(1+N('My Debts'!$D$14)/12),2) -> 0 | K13: =ROUND(AE12*(1+N('My Debts'!$D$15)/12),2) -> 0 | L13: =MIN(N('My Debts'!$E$6),B13) -> 0 | M13: =MIN(N('My Debts'!$E$7),C13) -> 0 | N13: =MIN(N('My Debts'!$E$8),D13) -> 285 | O13: =MIN(N('My Debts'!$E$9),E13) -> 0 | P13: =MIN(N('My Debts'!$E$10),F13) -> 0 | Q13: =MIN(N('My Debts'!$E$11),G13) -> 0 | R13: =MIN(N('My Debts'!$E$12),H13) -> 0 | S13: =MIN(N('My Debts'!$E$13),I13) -> 0 | T13: =MIN(N('My Debts'!$E$14),J13) -> 0 | U13: =MIN(N('My Debts'!$E$15),K13) -> 0 | V13: =ROUND(B13-L13-MIN(B13-L13,MAX(0,$AF13-SUMPRODUCT(--($B$4:$K$4<B$4),$B13:$K13-$L13:$U13))),2) -> 0 | W13: =ROUND(C13-M13-MIN(C13-M13,MAX(0,$AF13-SUMPRODUCT(--($B$4:$K$4<C$4),$B13:$K13-$L13:$U13))),2) -> 0 | X13: =ROUND(D13-N13-MIN(D13-N13,MAX(0,$AF13-SUMPRODUCT(--($B$4:$K$4<D$4),$B13:$K13-$L13:$U13))),2) -> 7151.13 | Y13: =ROUND(E13-O13-MIN(E13-O13,MAX(0,$AF13-SUMPRODUCT(--($B$4:$K$4<E$4),$B13:$K13-$L13:$U13))),2) -> 0 | Z13: =ROUND(F13-P13-MIN(F13-P13,MAX(0,$AF13-SUMPRODUCT(--($B$4:$K$4<F$4),$B13:$K13-$L13:$U13))),2) -> 0 | AA13: =ROUND(G13-Q13-MIN(G13-Q13,MAX(0,$AF13-SUMPRODUCT(--($B$4:$K$4<G$4),$B13:$K13-$L13:$U13))),2) -> 0 | AB13: =ROUND(H13-R13-MIN(H13-R13,MAX(0,$AF13-SUMPRODUCT(--($B$4:$K$4<H$4),$B13:$K13-$L13:$U13))),2) -> 0 | AC13: =ROUND(I13-S13-MIN(I13-S13,MAX(0,$AF13-SUMPRODUCT(--($B$4:$K$4<I$4),$B13:$K13-$L13:$U13))),2) -> 0 | ... AE13: =ROUND(K13-U13-MIN(K13-U13,MAX(0,$AF13-SUMPRODUCT(--($B$4:$K$4<K$4),$B13:$K13-$L13:$U13))),2) -> 0 | AF13: =MAX(0,'Start Here'!$C$5-SUM($L13:$U13)) -> 915 | AG13: =SUM(V13:AE13) -> 7151.13 | AH13: =SUM(B13:K13)-AG12 -> 47.74
A14: =DATE(YEAR('Start Here'!$C$6),MONTH('Start Here'!$C$6)+7,1) -> 46508 | B14: =ROUND(V13*(1+N('My Debts'!$D$6)/12),2) -> 0 | C14: =ROUND(W13*(1+N('My Debts'!$D$7)/12),2) -> 0 | D14: =ROUND(X13*(1+N('My Debts'!$D$8)/12),2) -> 7192.25 | E14: =ROUND(Y13*(1+N('My Debts'!$D$9)/12),2) -> 0 | F14: =ROUND(Z13*(1+N('My Debts'!$D$10)/12),2) -> 0 | G14: =ROUND(AA13*(1+N('My Debts'!$D$11)/12),2) -> 0 | H14: =ROUND(AB13*(1+N('My Debts'!$D$12)/12),2) -> 0 | I14: =ROUND(AC13*(1+N('My Debts'!$D$13)/12),2) -> 0 | J14: =ROUND(AD13*(1+N('My Debts'!$D$14)/12),2) -> 0 | K14: =ROUND(AE13*(1+N('My Debts'!$D$15)/12),2) -> 0 | L14: =MIN(N('My Debts'!$E$6),B14) -> 0 | M14: =MIN(N('My Debts'!$E$7),C14) -> 0 | N14: =MIN(N('My Debts'!$E$8),D14) -> 285 | O14: =MIN(N('My Debts'!$E$9),E14) -> 0 | P14: =MIN(N('My Debts'!$E$10),F14) -> 0 | Q14: =MIN(N('My Debts'!$E$11),G14) -> 0 | R14: =MIN(N('My Debts'!$E$12),H14) -> 0 | S14: =MIN(N('My Debts'!$E$13),I14) -> 0 | T14: =MIN(N('My Debts'!$E$14),J14) -> 0 | U14: =MIN(N('My Debts'!$E$15),K14) -> 0 | V14: =ROUND(B14-L14-MIN(B14-L14,MAX(0,$AF14-SUMPRODUCT(--($B$4:$K$4<B$4),$B14:$K14-$L14:$U14))),2) -> 0 | W14: =ROUND(C14-M14-MIN(C14-M14,MAX(0,$AF14-SUMPRODUCT(--($B$4:$K$4<C$4),$B14:$K14-$L14:$U14))),2) -> 0 | X14: =ROUND(D14-N14-MIN(D14-N14,MAX(0,$AF14-SUMPRODUCT(--($B$4:$K$4<D$4),$B14:$K14-$L14:$U14))),2) -> 5992.25 | Y14: =ROUND(E14-O14-MIN(E14-O14,MAX(0,$AF14-SUMPRODUCT(--($B$4:$K$4<E$4),$B14:$K14-$L14:$U14))),2) -> 0 | Z14: =ROUND(F14-P14-MIN(F14-P14,MAX(0,$AF14-SUMPRODUCT(--($B$4:$K$4<F$4),$B14:$K14-$L14:$U14))),2) -> 0 | AA14: =ROUND(G14-Q14-MIN(G14-Q14,MAX(0,$AF14-SUMPRODUCT(--($B$4:$K$4<G$4),$B14:$K14-$L14:$U14))),2) -> 0 | AB14: =ROUND(H14-R14-MIN(H14-R14,MAX(0,$AF14-SUMPRODUCT(--($B$4:$K$4<H$4),$B14:$K14-$L14:$U14))),2) -> 0 | AC14: =ROUND(I14-S14-MIN(I14-S14,MAX(0,$AF14-SUMPRODUCT(--($B$4:$K$4<I$4),$B14:$K14-$L14:$U14))),2) -> 0 | ... AE14: =ROUND(K14-U14-MIN(K14-U14,MAX(0,$AF14-SUMPRODUCT(--($B$4:$K$4<K$4),$B14:$K14-$L14:$U14))),2) -> 0 | AF14: =MAX(0,'Start Here'!$C$5-SUM($L14:$U14)) -> 915 | AG14: =SUM(V14:AE14) -> 5992.25 | AH14: =SUM(B14:K14)-AG13 -> 41.12
A15: =DATE(YEAR('Start Here'!$C$6),MONTH('Start Here'!$C$6)+8,1) -> 46539 | B15: =ROUND(V14*(1+N('My Debts'!$D$6)/12),2) -> 0 | C15: =ROUND(W14*(1+N('My Debts'!$D$7)/12),2) -> 0 | D15: =ROUND(X14*(1+N('My Debts'!$D$8)/12),2) -> 6026.71 | E15: =ROUND(Y14*(1+N('My Debts'!$D$9)/12),2) -> 0 | F15: =ROUND(Z14*(1+N('My Debts'!$D$10)/12),2) -> 0 | G15: =ROUND(AA14*(1+N('My Debts'!$D$11)/12),2) -> 0 | H15: =ROUND(AB14*(1+N('My Debts'!$D$12)/12),2) -> 0 | I15: =ROUND(AC14*(1+N('My Debts'!$D$13)/12),2) -> 0 | J15: =ROUND(AD14*(1+N('My Debts'!$D$14)/12),2) -> 0 | K15: =ROUND(AE14*(1+N('My Debts'!$D$15)/12),2) -> 0 | L15: =MIN(N('My Debts'!$E$6),B15) -> 0 | M15: =MIN(N('My Debts'!$E$7),C15) -> 0 | N15: =MIN(N('My Debts'!$E$8),D15) -> 285 | O15: =MIN(N('My Debts'!$E$9),E15) -> 0 | P15: =MIN(N('My Debts'!$E$10),F15) -> 0 | Q15: =MIN(N('My Debts'!$E$11),G15) -> 0 | R15: =MIN(N('My Debts'!$E$12),H15) -> 0 | S15: =MIN(N('My Debts'!$E$13),I15) -> 0 | T15: =MIN(N('My Debts'!$E$14),J15) -> 0 | U15: =MIN(N('My Debts'!$E$15),K15) -> 0 | V15: =ROUND(B15-L15-MIN(B15-L15,MAX(0,$AF15-SUMPRODUCT(--($B$4:$K$4<B$4),$B15:$K15-$L15:$U15))),2) -> 0 | W15: =ROUND(C15-M15-MIN(C15-M15,MAX(0,$AF15-SUMPRODUCT(--($B$4:$K$4<C$4),$B15:$K15-$L15:$U15))),2) -> 0 | X15: =ROUND(D15-N15-MIN(D15-N15,MAX(0,$AF15-SUMPRODUCT(--($B$4:$K$4<D$4),$B15:$K15-$L15:$U15))),2) -> 4826.71 | Y15: =ROUND(E15-O15-MIN(E15-O15,MAX(0,$AF15-SUMPRODUCT(--($B$4:$K$4<E$4),$B15:$K15-$L15:$U15))),2) -> 0 | Z15: =ROUND(F15-P15-MIN(F15-P15,MAX(0,$AF15-SUMPRODUCT(--($B$4:$K$4<F$4),$B15:$K15-$L15:$U15))),2) -> 0 | AA15: =ROUND(G15-Q15-MIN(G15-Q15,MAX(0,$AF15-SUMPRODUCT(--($B$4:$K$4<G$4),$B15:$K15-$L15:$U15))),2) -> 0 | AB15: =ROUND(H15-R15-MIN(H15-R15,MAX(0,$AF15-SUMPRODUCT(--($B$4:$K$4<H$4),$B15:$K15-$L15:$U15))),2) -> 0 | AC15: =ROUND(I15-S15-MIN(I15-S15,MAX(0,$AF15-SUMPRODUCT(--($B$4:$K$4<I$4),$B15:$K15-$L15:$U15))),2) -> 0 | ... AE15: =ROUND(K15-U15-MIN(K15-U15,MAX(0,$AF15-SUMPRODUCT(--($B$4:$K$4<K$4),$B15:$K15-$L15:$U15))),2) -> 0 | AF15: =MAX(0,'Start Here'!$C$5-SUM($L15:$U15)) -> 915 | AG15: =SUM(V15:AE15) -> 4826.71 | AH15: =SUM(B15:K15)-AG14 -> 34.46
A16: =DATE(YEAR('Start Here'!$C$6),MONTH('Start Here'!$C$6)+9,1) -> 46569 | B16: =ROUND(V15*(1+N('My Debts'!$D$6)/12),2) -> 0 | C16: =ROUND(W15*(1+N('My Debts'!$D$7)/12),2) -> 0 | D16: =ROUND(X15*(1+N('My Debts'!$D$8)/12),2) -> 4854.46 | E16: =ROUND(Y15*(1+N('My Debts'!$D$9)/12),2) -> 0 | F16: =ROUND(Z15*(1+N('My Debts'!$D$10)/12),2) -> 0 | G16: =ROUND(AA15*(1+N('My Debts'!$D$11)/12),2) -> 0 | H16: =ROUND(AB15*(1+N('My Debts'!$D$12)/12),2) -> 0 | I16: =ROUND(AC15*(1+N('My Debts'!$D$13)/12),2) -> 0 | J16: =ROUND(AD15*(1+N('My Debts'!$D$14)/12),2) -> 0 | K16: =ROUND(AE15*(1+N('My Debts'!$D$15)/12),2) -> 0 | L16: =MIN(N('My Debts'!$E$6),B16) -> 0 | M16: =MIN(N('My Debts'!$E$7),C16) -> 0 | N16: =MIN(N('My Debts'!$E$8),D16) -> 285 | O16: =MIN(N('My Debts'!$E$9),E16) -> 0 | P16: =MIN(N('My Debts'!$E$10),F16) -> 0 | Q16: =MIN(N('My Debts'!$E$11),G16) -> 0 | R16: =MIN(N('My Debts'!$E$12),H16) -> 0 | S16: =MIN(N('My Debts'!$E$13),I16) -> 0 | T16: =MIN(N('My Debts'!$E$14),J16) -> 0 | U16: =MIN(N('My Debts'!$E$15),K16) -> 0 | V16: =ROUND(B16-L16-MIN(B16-L16,MAX(0,$AF16-SUMPRODUCT(--($B$4:$K$4<B$4),$B16:$K16-$L16:$U16))),2) -> 0 | W16: =ROUND(C16-M16-MIN(C16-M16,MAX(0,$AF16-SUMPRODUCT(--($B$4:$K$4<C$4),$B16:$K16-$L16:$U16))),2) -> 0 | X16: =ROUND(D16-N16-MIN(D16-N16,MAX(0,$AF16-SUMPRODUCT(--($B$4:$K$4<D$4),$B16:$K16-$L16:$U16))),2) -> 3654.46 | Y16: =ROUND(E16-O16-MIN(E16-O16,MAX(0,$AF16-SUMPRODUCT(--($B$4:$K$4<E$4),$B16:$K16-$L16:$U16))),2) -> 0 | Z16: =ROUND(F16-P16-MIN(F16-P16,MAX(0,$AF16-SUMPRODUCT(--($B$4:$K$4<F$4),$B16:$K16-$L16:$U16))),2) -> 0 | AA16: =ROUND(G16-Q16-MIN(G16-Q16,MAX(0,$AF16-SUMPRODUCT(--($B$4:$K$4<G$4),$B16:$K16-$L16:$U16))),2) -> 0 | AB16: =ROUND(H16-R16-MIN(H16-R16,MAX(0,$AF16-SUMPRODUCT(--($B$4:$K$4<H$4),$B16:$K16-$L16:$U16))),2) -> 0 | AC16: =ROUND(I16-S16-MIN(I16-S16,MAX(0,$AF16-SUMPRODUCT(--($B$4:$K$4<I$4),$B16:$K16-$L16:$U16))),2) -> 0 | ... AE16: =ROUND(K16-U16-MIN(K16-U16,MAX(0,$AF16-SUMPRODUCT(--($B$4:$K$4<K$4),$B16:$K16-$L16:$U16))),2) -> 0 | AF16: =MAX(0,'Start Here'!$C$5-SUM($L16:$U16)) -> 915 | AG16: =SUM(V16:AE16) -> 3654.46 | AH16: =SUM(B16:K16)-AG15 -> 27.75
A17: =DATE(YEAR('Start Here'!$C$6),MONTH('Start Here'!$C$6)+10,1) -> 46600 | B17: =ROUND(V16*(1+N('My Debts'!$D$6)/12),2) -> 0 | C17: =ROUND(W16*(1+N('My Debts'!$D$7)/12),2) -> 0 | D17: =ROUND(X16*(1+N('My Debts'!$D$8)/12),2) -> 3675.47 | E17: =ROUND(Y16*(1+N('My Debts'!$D$9)/12),2) -> 0 | F17: =ROUND(Z16*(1+N('My Debts'!$D$10)/12),2) -> 0 | G17: =ROUND(AA16*(1+N('My Debts'!$D$11)/12),2) -> 0 | H17: =ROUND(AB16*(1+N('My Debts'!$D$12)/12),2) -> 0 | I17: =ROUND(AC16*(1+N('My Debts'!$D$13)/12),2) -> 0 | J17: =ROUND(AD16*(1+N('My Debts'!$D$14)/12),2) -> 0 | K17: =ROUND(AE16*(1+N('My Debts'!$D$15)/12),2) -> 0 | L17: =MIN(N('My Debts'!$E$6),B17) -> 0 | M17: =MIN(N('My Debts'!$E$7),C17) -> 0 | N17: =MIN(N('My Debts'!$E$8),D17) -> 285 | O17: =MIN(N('My Debts'!$E$9),E17) -> 0 | P17: =MIN(N('My Debts'!$E$10),F17) -> 0 | Q17: =MIN(N('My Debts'!$E$11),G17) -> 0 | R17: =MIN(N('My Debts'!$E$12),H17) -> 0 | S17: =MIN(N('My Debts'!$E$13),I17) -> 0 | T17: =MIN(N('My Debts'!$E$14),J17) -> 0 | U17: =MIN(N('My Debts'!$E$15),K17) -> 0 | V17: =ROUND(B17-L17-MIN(B17-L17,MAX(0,$AF17-SUMPRODUCT(--($B$4:$K$4<B$4),$B17:$K17-$L17:$U17))),2) -> 0 | W17: =ROUND(C17-M17-MIN(C17-M17,MAX(0,$AF17-SUMPRODUCT(--($B$4:$K$4<C$4),$B17:$K17-$L17:$U17))),2) -> 0 | X17: =ROUND(D17-N17-MIN(D17-N17,MAX(0,$AF17-SUMPRODUCT(--($B$4:$K$4<D$4),$B17:$K17-$L17:$U17))),2) -> 2475.47 | Y17: =ROUND(E17-O17-MIN(E17-O17,MAX(0,$AF17-SUMPRODUCT(--($B$4:$K$4<E$4),$B17:$K17-$L17:$U17))),2) -> 0 | Z17: =ROUND(F17-P17-MIN(F17-P17,MAX(0,$AF17-SUMPRODUCT(--($B$4:$K$4<F$4),$B17:$K17-$L17:$U17))),2) -> 0 | AA17: =ROUND(G17-Q17-MIN(G17-Q17,MAX(0,$AF17-SUMPRODUCT(--($B$4:$K$4<G$4),$B17:$K17-$L17:$U17))),2) -> 0 | AB17: =ROUND(H17-R17-MIN(H17-R17,MAX(0,$AF17-SUMPRODUCT(--($B$4:$K$4<H$4),$B17:$K17-$L17:$U17))),2) -> 0 | AC17: =ROUND(I17-S17-MIN(I17-S17,MAX(0,$AF17-SUMPRODUCT(--($B$4:$K$4<I$4),$B17:$K17-$L17:$U17))),2) -> 0 | ... AE17: =ROUND(K17-U17-MIN(K17-U17,MAX(0,$AF17-SUMPRODUCT(--($B$4:$K$4<K$4),$B17:$K17-$L17:$U17))),2) -> 0 | AF17: =MAX(0,'Start Here'!$C$5-SUM($L17:$U17)) -> 915 | AG17: =SUM(V17:AE17) -> 2475.47 | AH17: =SUM(B17:K17)-AG16 -> 21.01
A18: =DATE(YEAR('Start Here'!$C$6),MONTH('Start Here'!$C$6)+11,1) -> 46631 | B18: =ROUND(V17*(1+N('My Debts'!$D$6)/12),2) -> 0 | C18: =ROUND(W17*(1+N('My Debts'!$D$7)/12),2) -> 0 | D18: =ROUND(X17*(1+N('My Debts'!$D$8)/12),2) -> 2489.7 | E18: =ROUND(Y17*(1+N('My Debts'!$D$9)/12),2) -> 0 | F18: =ROUND(Z17*(1+N('My Debts'!$D$10)/12),2) -> 0 | G18: =ROUND(AA17*(1+N('My Debts'!$D$11)/12),2) -> 0 | H18: =ROUND(AB17*(1+N('My Debts'!$D$12)/12),2) -> 0 | I18: =ROUND(AC17*(1+N('My Debts'!$D$13)/12),2) -> 0 | J18: =ROUND(AD17*(1+N('My Debts'!$D$14)/12),2) -> 0 | K18: =ROUND(AE17*(1+N('My Debts'!$D$15)/12),2) -> 0 | L18: =MIN(N('My Debts'!$E$6),B18) -> 0 | M18: =MIN(N('My Debts'!$E$7),C18) -> 0 | N18: =MIN(N('My Debts'!$E$8),D18) -> 285 | O18: =MIN(N('My Debts'!$E$9),E18) -> 0 | P18: =MIN(N('My Debts'!$E$10),F18) -> 0 | Q18: =MIN(N('My Debts'!$E$11),G18) -> 0 | R18: =MIN(N('My Debts'!$E$12),H18) -> 0 | S18: =MIN(N('My Debts'!$E$13),I18) -> 0 | T18: =MIN(N('My Debts'!$E$14),J18) -> 0 | U18: =MIN(N('My Debts'!$E$15),K18) -> 0 | V18: =ROUND(B18-L18-MIN(B18-L18,MAX(0,$AF18-SUMPRODUCT(--($B$4:$K$4<B$4),$B18:$K18-$L18:$U18))),2) -> 0 | W18: =ROUND(C18-M18-MIN(C18-M18,MAX(0,$AF18-SUMPRODUCT(--($B$4:$K$4<C$4),$B18:$K18-$L18:$U18))),2) -> 0 | X18: =ROUND(D18-N18-MIN(D18-N18,MAX(0,$AF18-SUMPRODUCT(--($B$4:$K$4<D$4),$B18:$K18-$L18:$U18))),2) -> 1289.7 | Y18: =ROUND(E18-O18-MIN(E18-O18,MAX(0,$AF18-SUMPRODUCT(--($B$4:$K$4<E$4),$B18:$K18-$L18:$U18))),2) -> 0 | Z18: =ROUND(F18-P18-MIN(F18-P18,MAX(0,$AF18-SUMPRODUCT(--($B$4:$K$4<F$4),$B18:$K18-$L18:$U18))),2) -> 0 | AA18: =ROUND(G18-Q18-MIN(G18-Q18,MAX(0,$AF18-SUMPRODUCT(--($B$4:$K$4<G$4),$B18:$K18-$L18:$U18))),2) -> 0 | AB18: =ROUND(H18-R18-MIN(H18-R18,MAX(0,$AF18-SUMPRODUCT(--($B$4:$K$4<H$4),$B18:$K18-$L18:$U18))),2) -> 0 | AC18: =ROUND(I18-S18-MIN(I18-S18,MAX(0,$AF18-SUMPRODUCT(--($B$4:$K$4<I$4),$B18:$K18-$L18:$U18))),2) -> 0 | ... AE18: =ROUND(K18-U18-MIN(K18-U18,MAX(0,$AF18-SUMPRODUCT(--($B$4:$K$4<K$4),$B18:$K18-$L18:$U18))),2) -> 0 | AF18: =MAX(0,'Start Here'!$C$5-SUM($L18:$U18)) -> 915 | AG18: =SUM(V18:AE18) -> 1289.7 | AH18: =SUM(B18:K18)-AG17 -> 14.23
A19: =DATE(YEAR('Start Here'!$C$6),MONTH('Start Here'!$C$6)+12,1) -> 46661 | B19: =ROUND(V18*(1+N('My Debts'!$D$6)/12),2) -> 0 | C19: =ROUND(W18*(1+N('My Debts'!$D$7)/12),2) -> 0 | D19: =ROUND(X18*(1+N('My Debts'!$D$8)/12),2) -> 1297.12 | E19: =ROUND(Y18*(1+N('My Debts'!$D$9)/12),2) -> 0 | F19: =ROUND(Z18*(1+N('My Debts'!$D$10)/12),2) -> 0 | G19: =ROUND(AA18*(1+N('My Debts'!$D$11)/12),2) -> 0 | H19: =ROUND(AB18*(1+N('My Debts'!$D$12)/12),2) -> 0 | I19: =ROUND(AC18*(1+N('My Debts'!$D$13)/12),2) -> 0 | J19: =ROUND(AD18*(1+N('My Debts'!$D$14)/12),2) -> 0 | K19: =ROUND(AE18*(1+N('My Debts'!$D$15)/12),2) -> 0 | L19: =MIN(N('My Debts'!$E$6),B19) -> 0 | M19: =MIN(N('My Debts'!$E$7),C19) -> 0 | N19: =MIN(N('My Debts'!$E$8),D19) -> 285 | O19: =MIN(N('My Debts'!$E$9),E19) -> 0 | P19: =MIN(N('My Debts'!$E$10),F19) -> 0 | Q19: =MIN(N('My Debts'!$E$11),G19) -> 0 | R19: =MIN(N('My Debts'!$E$12),H19) -> 0 | S19: =MIN(N('My Debts'!$E$13),I19) -> 0 | T19: =MIN(N('My Debts'!$E$14),J19) -> 0 | U19: =MIN(N('My Debts'!$E$15),K19) -> 0 | V19: =ROUND(B19-L19-MIN(B19-L19,MAX(0,$AF19-SUMPRODUCT(--($B$4:$K$4<B$4),$B19:$K19-$L19:$U19))),2) -> 0 | W19: =ROUND(C19-M19-MIN(C19-M19,MAX(0,$AF19-SUMPRODUCT(--($B$4:$K$4<C$4),$B19:$K19-$L19:$U19))),2) -> 0 | X19: =ROUND(D19-N19-MIN(D19-N19,MAX(0,$AF19-SUMPRODUCT(--($B$4:$K$4<D$4),$B19:$K19-$L19:$U19))),2) -> 97.12 | Y19: =ROUND(E19-O19-MIN(E19-O19,MAX(0,$AF19-SUMPRODUCT(--($B$4:$K$4<E$4),$B19:$K19-$L19:$U19))),2) -> 0 | Z19: =ROUND(F19-P19-MIN(F19-P19,MAX(0,$AF19-SUMPRODUCT(--($B$4:$K$4<F$4),$B19:$K19-$L19:$U19))),2) -> 0 | AA19: =ROUND(G19-Q19-MIN(G19-Q19,MAX(0,$AF19-SUMPRODUCT(--($B$4:$K$4<G$4),$B19:$K19-$L19:$U19))),2) -> 0 | AB19: =ROUND(H19-R19-MIN(H19-R19,MAX(0,$AF19-SUMPRODUCT(--($B$4:$K$4<H$4),$B19:$K19-$L19:$U19))),2) -> 0 | AC19: =ROUND(I19-S19-MIN(I19-S19,MAX(0,$AF19-SUMPRODUCT(--($B$4:$K$4<I$4),$B19:$K19-$L19:$U19))),2) -> 0 | ... AE19: =ROUND(K19-U19-MIN(K19-U19,MAX(0,$AF19-SUMPRODUCT(--($B$4:$K$4<K$4),$B19:$K19-$L19:$U19))),2) -> 0 | AF19: =MAX(0,'Start Here'!$C$5-SUM($L19:$U19)) -> 915 | AG19: =SUM(V19:AE19) -> 97.12 | AH19: =SUM(B19:K19)-AG18 -> 7.42
A20: =DATE(YEAR('Start Here'!$C$6),MONTH('Start Here'!$C$6)+13,1) -> 46692 | B20: =ROUND(V19*(1+N('My Debts'!$D$6)/12),2) -> 0 | C20: =ROUND(W19*(1+N('My Debts'!$D$7)/12),2) -> 0 | D20: =ROUND(X19*(1+N('My Debts'!$D$8)/12),2) -> 97.68 | E20: =ROUND(Y19*(1+N('My Debts'!$D$9)/12),2) -> 0 | F20: =ROUND(Z19*(1+N('My Debts'!$D$10)/12),2) -> 0 | G20: =ROUND(AA19*(1+N('My Debts'!$D$11)/12),2) -> 0 | H20: =ROUND(AB19*(1+N('My Debts'!$D$12)/12),2) -> 0 | I20: =ROUND(AC19*(1+N('My Debts'!$D$13)/12),2) -> 0 | J20: =ROUND(AD19*(1+N('My Debts'!$D$14)/12),2) -> 0 | K20: =ROUND(AE19*(1+N('My Debts'!$D$15)/12),2) -> 0 | L20: =MIN(N('My Debts'!$E$6),B20) -> 0 | M20: =MIN(N('My Debts'!$E$7),C20) -> 0 | N20: =MIN(N('My Debts'!$E$8),D20) -> 97.68 | O20: =MIN(N('My Debts'!$E$9),E20) -> 0 | P20: =MIN(N('My Debts'!$E$10),F20) -> 0 | Q20: =MIN(N('My Debts'!$E$11),G20) -> 0 | R20: =MIN(N('My Debts'!$E$12),H20) -> 0 | S20: =MIN(N('My Debts'!$E$13),I20) -> 0 | T20: =MIN(N('My Debts'!$E$14),J20) -> 0 | U20: =MIN(N('My Debts'!$E$15),K20) -> 0 | V20: =ROUND(B20-L20-MIN(B20-L20,MAX(0,$AF20-SUMPRODUCT(--($B$4:$K$4<B$4),$B20:$K20-$L20:$U20))),2) -> 0 | W20: =ROUND(C20-M20-MIN(C20-M20,MAX(0,$AF20-SUMPRODUCT(--($B$4:$K$4<C$4),$B20:$K20-$L20:$U20))),2) -> 0 | X20: =ROUND(D20-N20-MIN(D20-N20,MAX(0,$AF20-SUMPRODUCT(--($B$4:$K$4<D$4),$B20:$K20-$L20:$U20))),2) -> 0 | Y20: =ROUND(E20-O20-MIN(E20-O20,MAX(0,$AF20-SUMPRODUCT(--($B$4:$K$4<E$4),$B20:$K20-$L20:$U20))),2) -> 0 | Z20: =ROUND(F20-P20-MIN(F20-P20,MAX(0,$AF20-SUMPRODUCT(--($B$4:$K$4<F$4),$B20:$K20-$L20:$U20))),2) -> 0 | AA20: =ROUND(G20-Q20-MIN(G20-Q20,MAX(0,$AF20-SUMPRODUCT(--($B$4:$K$4<G$4),$B20:$K20-$L20:$U20))),2) -> 0 | AB20: =ROUND(H20-R20-MIN(H20-R20,MAX(0,$AF20-SUMPRODUCT(--($B$4:$K$4<H$4),$B20:$K20-$L20:$U20))),2) -> 0 | AC20: =ROUND(I20-S20-MIN(I20-S20,MAX(0,$AF20-SUMPRODUCT(--($B$4:$K$4<I$4),$B20:$K20-$L20:$U20))),2) -> 0 | ... AE20: =ROUND(K20-U20-MIN(K20-U20,MAX(0,$AF20-SUMPRODUCT(--($B$4:$K$4<K$4),$B20:$K20-$L20:$U20))),2) -> 0 | AF20: =MAX(0,'Start Here'!$C$5-SUM($L20:$U20)) -> 1102.32 | AG20: =SUM(V20:AE20) -> 0 | AH20: =SUM(B20:K20)-AG19 -> 0.56
A21: =DATE(YEAR('Start Here'!$C$6),MONTH('Start Here'!$C$6)+14,1) -> 46722 | B21: =ROUND(V20*(1+N('My Debts'!$D$6)/12),2) -> 0 | C21: =ROUND(W20*(1+N('My Debts'!$D$7)/12),2) -> 0 | D21: =ROUND(X20*(1+N('My Debts'!$D$8)/12),2) -> 0 | E21: =ROUND(Y20*(1+N('My Debts'!$D$9)/12),2) -> 0 | F21: =ROUND(Z20*(1+N('My Debts'!$D$10)/12),2) -> 0 | G21: =ROUND(AA20*(1+N('My Debts'!$D$11)/12),2) -> 0 | H21: =ROUND(AB20*(1+N('My Debts'!$D$12)/12),2) -> 0 | I21: =ROUND(AC20*(1+N('My Debts'!$D$13)/12),2) -> 0 | J21: =ROUND(AD20*(1+N('My Debts'!$D$14)/12),2) -> 0 | K21: =ROUND(AE20*(1+N('My Debts'!$D$15)/12),2) -> 0 | L21: =MIN(N('My Debts'!$E$6),B21) -> 0 | M21: =MIN(N('My Debts'!$E$7),C21) -> 0 | N21: =MIN(N('My Debts'!$E$8),D21) -> 0 | O21: =MIN(N('My Debts'!$E$9),E21) -> 0 | P21: =MIN(N('My Debts'!$E$10),F21) -> 0 | Q21: =MIN(N('My Debts'!$E$11),G21) -> 0 | R21: =MIN(N('My Debts'!$E$12),H21) -> 0 | S21: =MIN(N('My Debts'!$E$13),I21) -> 0 | T21: =MIN(N('My Debts'!$E$14),J21) -> 0 | U21: =MIN(N('My Debts'!$E$15),K21) -> 0 | V21: =ROUND(B21-L21-MIN(B21-L21,MAX(0,$AF21-SUMPRODUCT(--($B$4:$K$4<B$4),$B21:$K21-$L21:$U21))),2) -> 0 | W21: =ROUND(C21-M21-MIN(C21-M21,MAX(0,$AF21-SUMPRODUCT(--($B$4:$K$4<C$4),$B21:$K21-$L21:$U21))),2) -> 0 | X21: =ROUND(D21-N21-MIN(D21-N21,MAX(0,$AF21-SUMPRODUCT(--($B$4:$K$4<D$4),$B21:$K21-$L21:$U21))),2) -> 0 | Y21: =ROUND(E21-O21-MIN(E21-O21,MAX(0,$AF21-SUMPRODUCT(--($B$4:$K$4<E$4),$B21:$K21-$L21:$U21))),2) -> 0 | Z21: =ROUND(F21-P21-MIN(F21-P21,MAX(0,$AF21-SUMPRODUCT(--($B$4:$K$4<F$4),$B21:$K21-$L21:$U21))),2) -> 0 | AA21: =ROUND(G21-Q21-MIN(G21-Q21,MAX(0,$AF21-SUMPRODUCT(--($B$4:$K$4<G$4),$B21:$K21-$L21:$U21))),2) -> 0 | AB21: =ROUND(H21-R21-MIN(H21-R21,MAX(0,$AF21-SUMPRODUCT(--($B$4:$K$4<H$4),$B21:$K21-$L21:$U21))),2) -> 0 | AC21: =ROUND(I21-S21-MIN(I21-S21,MAX(0,$AF21-SUMPRODUCT(--($B$4:$K$4<I$4),$B21:$K21-$L21:$U21))),2) -> 0 | ... AE21: =ROUND(K21-U21-MIN(K21-U21,MAX(0,$AF21-SUMPRODUCT(--($B$4:$K$4<K$4),$B21:$K21-$L21:$U21))),2) -> 0 | AF21: =MAX(0,'Start Here'!$C$5-SUM($L21:$U21)) -> 1200 | AG21: =SUM(V21:AE21) -> 0 | AH21: =SUM(B21:K21)-AG20 -> 0
A22: =DATE(YEAR('Start Here'!$C$6),MONTH('Start Here'!$C$6)+15,1) -> 46753 | B22: =ROUND(V21*(1+N('My Debts'!$D$6)/12),2) -> 0 | C22: =ROUND(W21*(1+N('My Debts'!$D$7)/12),2) -> 0 | D22: =ROUND(X21*(1+N('My Debts'!$D$8)/12),2) -> 0 | E22: =ROUND(Y21*(1+N('My Debts'!$D$9)/12),2) -> 0 | F22: =ROUND(Z21*(1+N('My Debts'!$D$10)/12),2) -> 0 | G22: =ROUND(AA21*(1+N('My Debts'!$D$11)/12),2) -> 0 | H22: =ROUND(AB21*(1+N('My Debts'!$D$12)/12),2) -> 0 | I22: =ROUND(AC21*(1+N('My Debts'!$D$13)/12),2) -> 0 | J22: =ROUND(AD21*(1+N('My Debts'!$D$14)/12),2) -> 0 | K22: =ROUND(AE21*(1+N('My Debts'!$D$15)/12),2) -> 0 | L22: =MIN(N('My Debts'!$E$6),B22) -> 0 | M22: =MIN(N('My Debts'!$E$7),C22) -> 0 | N22: =MIN(N('My Debts'!$E$8),D22) -> 0 | O22: =MIN(N('My Debts'!$E$9),E22) -> 0 | P22: =MIN(N('My Debts'!$E$10),F22) -> 0 | Q22: =MIN(N('My Debts'!$E$11),G22) -> 0 | R22: =MIN(N('My Debts'!$E$12),H22) -> 0 | S22: =MIN(N('My Debts'!$E$13),I22) -> 0 | T22: =MIN(N('My Debts'!$E$14),J22) -> 0 | U22: =MIN(N('My Debts'!$E$15),K22) -> 0 | V22: =ROUND(B22-L22-MIN(B22-L22,MAX(0,$AF22-SUMPRODUCT(--($B$4:$K$4<B$4),$B22:$K22-$L22:$U22))),2) -> 0 | W22: =ROUND(C22-M22-MIN(C22-M22,MAX(0,$AF22-SUMPRODUCT(--($B$4:$K$4<C$4),$B22:$K22-$L22:$U22))),2) -> 0 | X22: =ROUND(D22-N22-MIN(D22-N22,MAX(0,$AF22-SUMPRODUCT(--($B$4:$K$4<D$4),$B22:$K22-$L22:$U22))),2) -> 0 | Y22: =ROUND(E22-O22-MIN(E22-O22,MAX(0,$AF22-SUMPRODUCT(--($B$4:$K$4<E$4),$B22:$K22-$L22:$U22))),2) -> 0 | Z22: =ROUND(F22-P22-MIN(F22-P22,MAX(0,$AF22-SUMPRODUCT(--($B$4:$K$4<F$4),$B22:$K22-$L22:$U22))),2) -> 0 | AA22: =ROUND(G22-Q22-MIN(G22-Q22,MAX(0,$AF22-SUMPRODUCT(--($B$4:$K$4<G$4),$B22:$K22-$L22:$U22))),2) -> 0 | AB22: =ROUND(H22-R22-MIN(H22-R22,MAX(0,$AF22-SUMPRODUCT(--($B$4:$K$4<H$4),$B22:$K22-$L22:$U22))),2) -> 0 | AC22: =ROUND(I22-S22-MIN(I22-S22,MAX(0,$AF22-SUMPRODUCT(--($B$4:$K$4<I$4),$B22:$K22-$L22:$U22))),2) -> 0 | ... AE22: =ROUND(K22-U22-MIN(K22-U22,MAX(0,$AF22-SUMPRODUCT(--($B$4:$K$4<K$4),$B22:$K22-$L22:$U22))),2) -> 0 | AF22: =MAX(0,'Start Here'!$C$5-SUM($L22:$U22)) -> 1200 | AG22: =SUM(V22:AE22) -> 0 | AH22: =SUM(B22:K22)-AG21 -> 0
A23: =DATE(YEAR('Start Here'!$C$6),MONTH('Start Here'!$C$6)+16,1) -> 46784 | B23: =ROUND(V22*(1+N('My Debts'!$D$6)/12),2) -> 0 | C23: =ROUND(W22*(1+N('My Debts'!$D$7)/12),2) -> 0 | D23: =ROUND(X22*(1+N('My Debts'!$D$8)/12),2) -> 0 | E23: =ROUND(Y22*(1+N('My Debts'!$D$9)/12),2) -> 0 | F23: =ROUND(Z22*(1+N('My Debts'!$D$10)/12),2) -> 0 | G23: =ROUND(AA22*(1+N('My Debts'!$D$11)/12),2) -> 0 | H23: =ROUND(AB22*(1+N('My Debts'!$D$12)/12),2) -> 0 | I23: =ROUND(AC22*(1+N('My Debts'!$D$13)/12),2) -> 0 | J23: =ROUND(AD22*(1+N('My Debts'!$D$14)/12),2) -> 0 | K23: =ROUND(AE22*(1+N('My Debts'!$D$15)/12),2) -> 0 | L23: =MIN(N('My Debts'!$E$6),B23) -> 0 | M23: =MIN(N('My Debts'!$E$7),C23) -> 0 | N23: =MIN(N('My Debts'!$E$8),D23) -> 0 | O23: =MIN(N('My Debts'!$E$9),E23) -> 0 | P23: =MIN(N('My Debts'!$E$10),F23) -> 0 | Q23: =MIN(N('My Debts'!$E$11),G23) -> 0 | R23: =MIN(N('My Debts'!$E$12),H23) -> 0 | S23: =MIN(N('My Debts'!$E$13),I23) -> 0 | T23: =MIN(N('My Debts'!$E$14),J23) -> 0 | U23: =MIN(N('My Debts'!$E$15),K23) -> 0 | V23: =ROUND(B23-L23-MIN(B23-L23,MAX(0,$AF23-SUMPRODUCT(--($B$4:$K$4<B$4),$B23:$K23-$L23:$U23))),2) -> 0 | W23: =ROUND(C23-M23-MIN(C23-M23,MAX(0,$AF23-SUMPRODUCT(--($B$4:$K$4<C$4),$B23:$K23-$L23:$U23))),2) -> 0 | X23: =ROUND(D23-N23-MIN(D23-N23,MAX(0,$AF23-SUMPRODUCT(--($B$4:$K$4<D$4),$B23:$K23-$L23:$U23))),2) -> 0 | Y23: =ROUND(E23-O23-MIN(E23-O23,MAX(0,$AF23-SUMPRODUCT(--($B$4:$K$4<E$4),$B23:$K23-$L23:$U23))),2) -> 0 | Z23: =ROUND(F23-P23-MIN(F23-P23,MAX(0,$AF23-SUMPRODUCT(--($B$4:$K$4<F$4),$B23:$K23-$L23:$U23))),2) -> 0 | AA23: =ROUND(G23-Q23-MIN(G23-Q23,MAX(0,$AF23-SUMPRODUCT(--($B$4:$K$4<G$4),$B23:$K23-$L23:$U23))),2) -> 0 | AB23: =ROUND(H23-R23-MIN(H23-R23,MAX(0,$AF23-SUMPRODUCT(--($B$4:$K$4<H$4),$B23:$K23-$L23:$U23))),2) -> 0 | AC23: =ROUND(I23-S23-MIN(I23-S23,MAX(0,$AF23-SUMPRODUCT(--($B$4:$K$4<I$4),$B23:$K23-$L23:$U23))),2) -> 0 | ... AE23: =ROUND(K23-U23-MIN(K23-U23,MAX(0,$AF23-SUMPRODUCT(--($B$4:$K$4<K$4),$B23:$K23-$L23:$U23))),2) -> 0 | AF23: =MAX(0,'Start Here'!$C$5-SUM($L23:$U23)) -> 1200 | AG23: =SUM(V23:AE23) -> 0 | AH23: =SUM(B23:K23)-AG22 -> 0
A24: =DATE(YEAR('Start Here'!$C$6),MONTH('Start Here'!$C$6)+17,1) -> 46813 | B24: =ROUND(V23*(1+N('My Debts'!$D$6)/12),2) -> 0 | C24: =ROUND(W23*(1+N('My Debts'!$D$7)/12),2) -> 0 | D24: =ROUND(X23*(1+N('My Debts'!$D$8)/12),2) -> 0 | E24: =ROUND(Y23*(1+N('My Debts'!$D$9)/12),2) -> 0 | F24: =ROUND(Z23*(1+N('My Debts'!$D$10)/12),2) -> 0 | G24: =ROUND(AA23*(1+N('My Debts'!$D$11)/12),2) -> 0 | H24: =ROUND(AB23*(1+N('My Debts'!$D$12)/12),2) -> 0 | I24: =ROUND(AC23*(1+N('My Debts'!$D$13)/12),2) -> 0 | J24: =ROUND(AD23*(1+N('My Debts'!$D$14)/12),2) -> 0 | K24: =ROUND(AE23*(1+N('My Debts'!$D$15)/12),2) -> 0 | L24: =MIN(N('My Debts'!$E$6),B24) -> 0 | M24: =MIN(N('My Debts'!$E$7),C24) -> 0 | N24: =MIN(N('My Debts'!$E$8),D24) -> 0 | O24: =MIN(N('My Debts'!$E$9),E24) -> 0 | P24: =MIN(N('My Debts'!$E$10),F24) -> 0 | Q24: =MIN(N('My Debts'!$E$11),G24) -> 0 | R24: =MIN(N('My Debts'!$E$12),H24) -> 0 | S24: =MIN(N('My Debts'!$E$13),I24) -> 0 | T24: =MIN(N('My Debts'!$E$14),J24) -> 0 | U24: =MIN(N('My Debts'!$E$15),K24) -> 0 | V24: =ROUND(B24-L24-MIN(B24-L24,MAX(0,$AF24-SUMPRODUCT(--($B$4:$K$4<B$4),$B24:$K24-$L24:$U24))),2) -> 0 | W24: =ROUND(C24-M24-MIN(C24-M24,MAX(0,$AF24-SUMPRODUCT(--($B$4:$K$4<C$4),$B24:$K24-$L24:$U24))),2) -> 0 | X24: =ROUND(D24-N24-MIN(D24-N24,MAX(0,$AF24-SUMPRODUCT(--($B$4:$K$4<D$4),$B24:$K24-$L24:$U24))),2) -> 0 | Y24: =ROUND(E24-O24-MIN(E24-O24,MAX(0,$AF24-SUMPRODUCT(--($B$4:$K$4<E$4),$B24:$K24-$L24:$U24))),2) -> 0 | Z24: =ROUND(F24-P24-MIN(F24-P24,MAX(0,$AF24-SUMPRODUCT(--($B$4:$K$4<F$4),$B24:$K24-$L24:$U24))),2) -> 0 | AA24: =ROUND(G24-Q24-MIN(G24-Q24,MAX(0,$AF24-SUMPRODUCT(--($B$4:$K$4<G$4),$B24:$K24-$L24:$U24))),2) -> 0 | AB24: =ROUND(H24-R24-MIN(H24-R24,MAX(0,$AF24-SUMPRODUCT(--($B$4:$K$4<H$4),$B24:$K24-$L24:$U24))),2) -> 0 | AC24: =ROUND(I24-S24-MIN(I24-S24,MAX(0,$AF24-SUMPRODUCT(--($B$4:$K$4<I$4),$B24:$K24-$L24:$U24))),2) -> 0 | ... AE24: =ROUND(K24-U24-MIN(K24-U24,MAX(0,$AF24-SUMPRODUCT(--($B$4:$K$4<K$4),$B24:$K24-$L24:$U24))),2) -> 0 | AF24: =MAX(0,'Start Here'!$C$5-SUM($L24:$U24)) -> 1200 | AG24: =SUM(V24:AE24) -> 0 | AH24: =SUM(B24:K24)-AG23 -> 0
A25: =DATE(YEAR('Start Here'!$C$6),MONTH('Start Here'!$C$6)+18,1) -> 46844 | B25: =ROUND(V24*(1+N('My Debts'!$D$6)/12),2) -> 0 | C25: =ROUND(W24*(1+N('My Debts'!$D$7)/12),2) -> 0 | D25: =ROUND(X24*(1+N('My Debts'!$D$8)/12),2) -> 0 | E25: =ROUND(Y24*(1+N('My Debts'!$D$9)/12),2) -> 0 | F25: =ROUND(Z24*(1+N('My Debts'!$D$10)/12),2) -> 0 | G25: =ROUND(AA24*(1+N('My Debts'!$D$11)/12),2) -> 0 | H25: =ROUND(AB24*(1+N('My Debts'!$D$12)/12),2) -> 0 | I25: =ROUND(AC24*(1+N('My Debts'!$D$13)/12),2) -> 0 | J25: =ROUND(AD24*(1+N('My Debts'!$D$14)/12),2) -> 0 | K25: =ROUND(AE24*(1+N('My Debts'!$D$15)/12),2) -> 0 | L25: =MIN(N('My Debts'!$E$6),B25) -> 0 | M25: =MIN(N('My Debts'!$E$7),C25) -> 0 | N25: =MIN(N('My Debts'!$E$8),D25) -> 0 | O25: =MIN(N('My Debts'!$E$9),E25) -> 0 | P25: =MIN(N('My Debts'!$E$10),F25) -> 0 | Q25: =MIN(N('My Debts'!$E$11),G25) -> 0 | R25: =MIN(N('My Debts'!$E$12),H25) -> 0 | S25: =MIN(N('My Debts'!$E$13),I25) -> 0 | T25: =MIN(N('My Debts'!$E$14),J25) -> 0 | U25: =MIN(N('My Debts'!$E$15),K25) -> 0 | V25: =ROUND(B25-L25-MIN(B25-L25,MAX(0,$AF25-SUMPRODUCT(--($B$4:$K$4<B$4),$B25:$K25-$L25:$U25))),2) -> 0 | W25: =ROUND(C25-M25-MIN(C25-M25,MAX(0,$AF25-SUMPRODUCT(--($B$4:$K$4<C$4),$B25:$K25-$L25:$U25))),2) -> 0 | X25: =ROUND(D25-N25-MIN(D25-N25,MAX(0,$AF25-SUMPRODUCT(--($B$4:$K$4<D$4),$B25:$K25-$L25:$U25))),2) -> 0 | Y25: =ROUND(E25-O25-MIN(E25-O25,MAX(0,$AF25-SUMPRODUCT(--($B$4:$K$4<E$4),$B25:$K25-$L25:$U25))),2) -> 0 | Z25: =ROUND(F25-P25-MIN(F25-P25,MAX(0,$AF25-SUMPRODUCT(--($B$4:$K$4<F$4),$B25:$K25-$L25:$U25))),2) -> 0 | AA25: =ROUND(G25-Q25-MIN(G25-Q25,MAX(0,$AF25-SUMPRODUCT(--($B$4:$K$4<G$4),$B25:$K25-$L25:$U25))),2) -> 0 | AB25: =ROUND(H25-R25-MIN(H25-R25,MAX(0,$AF25-SUMPRODUCT(--($B$4:$K$4<H$4),$B25:$K25-$L25:$U25))),2) -> 0 | AC25: =ROUND(I25-S25-MIN(I25-S25,MAX(0,$AF25-SUMPRODUCT(--($B$4:$K$4<I$4),$B25:$K25-$L25:$U25))),2) -> 0 | ... AE25: =ROUND(K25-U25-MIN(K25-U25,MAX(0,$AF25-SUMPRODUCT(--($B$4:$K$4<K$4),$B25:$K25-$L25:$U25))),2) -> 0 | AF25: =MAX(0,'Start Here'!$C$5-SUM($L25:$U25)) -> 1200 | AG25: =SUM(V25:AE25) -> 0 | AH25: =SUM(B25:K25)-AG24 -> 0
A26: =DATE(YEAR('Start Here'!$C$6),MONTH('Start Here'!$C$6)+19,1) -> 46874 | B26: =ROUND(V25*(1+N('My Debts'!$D$6)/12),2) -> 0 | C26: =ROUND(W25*(1+N('My Debts'!$D$7)/12),2) -> 0 | D26: =ROUND(X25*(1+N('My Debts'!$D$8)/12),2) -> 0 | E26: =ROUND(Y25*(1+N('My Debts'!$D$9)/12),2) -> 0 | F26: =ROUND(Z25*(1+N('My Debts'!$D$10)/12),2) -> 0 | G26: =ROUND(AA25*(1+N('My Debts'!$D$11)/12),2) -> 0 | H26: =ROUND(AB25*(1+N('My Debts'!$D$12)/12),2) -> 0 | I26: =ROUND(AC25*(1+N('My Debts'!$D$13)/12),2) -> 0 | J26: =ROUND(AD25*(1+N('My Debts'!$D$14)/12),2) -> 0 | K26: =ROUND(AE25*(1+N('My Debts'!$D$15)/12),2) -> 0 | L26: =MIN(N('My Debts'!$E$6),B26) -> 0 | M26: =MIN(N('My Debts'!$E$7),C26) -> 0 | N26: =MIN(N('My Debts'!$E$8),D26) -> 0 | O26: =MIN(N('My Debts'!$E$9),E26) -> 0 | P26: =MIN(N('My Debts'!$E$10),F26) -> 0 | Q26: =MIN(N('My Debts'!$E$11),G26) -> 0 | R26: =MIN(N('My Debts'!$E$12),H26) -> 0 | S26: =MIN(N('My Debts'!$E$13),I26) -> 0 | T26: =MIN(N('My Debts'!$E$14),J26) -> 0 | U26: =MIN(N('My Debts'!$E$15),K26) -> 0 | V26: =ROUND(B26-L26-MIN(B26-L26,MAX(0,$AF26-SUMPRODUCT(--($B$4:$K$4<B$4),$B26:$K26-$L26:$U26))),2) -> 0 | W26: =ROUND(C26-M26-MIN(C26-M26,MAX(0,$AF26-SUMPRODUCT(--($B$4:$K$4<C$4),$B26:$K26-$L26:$U26))),2) -> 0 | X26: =ROUND(D26-N26-MIN(D26-N26,MAX(0,$AF26-SUMPRODUCT(--($B$4:$K$4<D$4),$B26:$K26-$L26:$U26))),2) -> 0 | Y26: =ROUND(E26-O26-MIN(E26-O26,MAX(0,$AF26-SUMPRODUCT(--($B$4:$K$4<E$4),$B26:$K26-$L26:$U26))),2) -> 0 | Z26: =ROUND(F26-P26-MIN(F26-P26,MAX(0,$AF26-SUMPRODUCT(--($B$4:$K$4<F$4),$B26:$K26-$L26:$U26))),2) -> 0 | AA26: =ROUND(G26-Q26-MIN(G26-Q26,MAX(0,$AF26-SUMPRODUCT(--($B$4:$K$4<G$4),$B26:$K26-$L26:$U26))),2) -> 0 | AB26: =ROUND(H26-R26-MIN(H26-R26,MAX(0,$AF26-SUMPRODUCT(--($B$4:$K$4<H$4),$B26:$K26-$L26:$U26))),2) -> 0 | AC26: =ROUND(I26-S26-MIN(I26-S26,MAX(0,$AF26-SUMPRODUCT(--($B$4:$K$4<I$4),$B26:$K26-$L26:$U26))),2) -> 0 | ... AE26: =ROUND(K26-U26-MIN(K26-U26,MAX(0,$AF26-SUMPRODUCT(--($B$4:$K$4<K$4),$B26:$K26-$L26:$U26))),2) -> 0 | AF26: =MAX(0,'Start Here'!$C$5-SUM($L26:$U26)) -> 1200 | AG26: =SUM(V26:AE26) -> 0 | AH26: =SUM(B26:K26)-AG25 -> 0
A27: =DATE(YEAR('Start Here'!$C$6),MONTH('Start Here'!$C$6)+20,1) -> 46905 | B27: =ROUND(V26*(1+N('My Debts'!$D$6)/12),2) -> 0 | C27: =ROUND(W26*(1+N('My Debts'!$D$7)/12),2) -> 0 | D27: =ROUND(X26*(1+N('My Debts'!$D$8)/12),2) -> 0 | E27: =ROUND(Y26*(1+N('My Debts'!$D$9)/12),2) -> 0 | F27: =ROUND(Z26*(1+N('My Debts'!$D$10)/12),2) -> 0 | G27: =ROUND(AA26*(1+N('My Debts'!$D$11)/12),2) -> 0 | H27: =ROUND(AB26*(1+N('My Debts'!$D$12)/12),2) -> 0 | I27: =ROUND(AC26*(1+N('My Debts'!$D$13)/12),2) -> 0 | J27: =ROUND(AD26*(1+N('My Debts'!$D$14)/12),2) -> 0 | K27: =ROUND(AE26*(1+N('My Debts'!$D$15)/12),2) -> 0 | L27: =MIN(N('My Debts'!$E$6),B27) -> 0 | M27: =MIN(N('My Debts'!$E$7),C27) -> 0 | N27: =MIN(N('My Debts'!$E$8),D27) -> 0 | O27: =MIN(N('My Debts'!$E$9),E27) -> 0 | P27: =MIN(N('My Debts'!$E$10),F27) -> 0 | Q27: =MIN(N('My Debts'!$E$11),G27) -> 0 | R27: =MIN(N('My Debts'!$E$12),H27) -> 0 | S27: =MIN(N('My Debts'!$E$13),I27) -> 0 | T27: =MIN(N('My Debts'!$E$14),J27) -> 0 | U27: =MIN(N('My Debts'!$E$15),K27) -> 0 | V27: =ROUND(B27-L27-MIN(B27-L27,MAX(0,$AF27-SUMPRODUCT(--($B$4:$K$4<B$4),$B27:$K27-$L27:$U27))),2) -> 0 | W27: =ROUND(C27-M27-MIN(C27-M27,MAX(0,$AF27-SUMPRODUCT(--($B$4:$K$4<C$4),$B27:$K27-$L27:$U27))),2) -> 0 | X27: =ROUND(D27-N27-MIN(D27-N27,MAX(0,$AF27-SUMPRODUCT(--($B$4:$K$4<D$4),$B27:$K27-$L27:$U27))),2) -> 0 | Y27: =ROUND(E27-O27-MIN(E27-O27,MAX(0,$AF27-SUMPRODUCT(--($B$4:$K$4<E$4),$B27:$K27-$L27:$U27))),2) -> 0 | Z27: =ROUND(F27-P27-MIN(F27-P27,MAX(0,$AF27-SUMPRODUCT(--($B$4:$K$4<F$4),$B27:$K27-$L27:$U27))),2) -> 0 | AA27: =ROUND(G27-Q27-MIN(G27-Q27,MAX(0,$AF27-SUMPRODUCT(--($B$4:$K$4<G$4),$B27:$K27-$L27:$U27))),2) -> 0 | AB27: =ROUND(H27-R27-MIN(H27-R27,MAX(0,$AF27-SUMPRODUCT(--($B$4:$K$4<H$4),$B27:$K27-$L27:$U27))),2) -> 0 | AC27: =ROUND(I27-S27-MIN(I27-S27,MAX(0,$AF27-SUMPRODUCT(--($B$4:$K$4<I$4),$B27:$K27-$L27:$U27))),2) -> 0 | ... AE27: =ROUND(K27-U27-MIN(K27-U27,MAX(0,$AF27-SUMPRODUCT(--($B$4:$K$4<K$4),$B27:$K27-$L27:$U27))),2) -> 0 | AF27: =MAX(0,'Start Here'!$C$5-SUM($L27:$U27)) -> 1200 | AG27: =SUM(V27:AE27) -> 0 | AH27: =SUM(B27:K27)-AG26 -> 0
A28: =DATE(YEAR('Start Here'!$C$6),MONTH('Start Here'!$C$6)+21,1) -> 46935 | B28: =ROUND(V27*(1+N('My Debts'!$D$6)/12),2) -> 0 | C28: =ROUND(W27*(1+N('My Debts'!$D$7)/12),2) -> 0 | D28: =ROUND(X27*(1+N('My Debts'!$D$8)/12),2) -> 0 | E28: =ROUND(Y27*(1+N('My Debts'!$D$9)/12),2) -> 0 | F28: =ROUND(Z27*(1+N('My Debts'!$D$10)/12),2) -> 0 | G28: =ROUND(AA27*(1+N('My Debts'!$D$11)/12),2) -> 0 | H28: =ROUND(AB27*(1+N('My Debts'!$D$12)/12),2) -> 0 | I28: =ROUND(AC27*(1+N('My Debts'!$D$13)/12),2) -> 0 | J28: =ROUND(AD27*(1+N('My Debts'!$D$14)/12),2) -> 0 | K28: =ROUND(AE27*(1+N('My Debts'!$D$15)/12),2) -> 0 | L28: =MIN(N('My Debts'!$E$6),B28) -> 0 | M28: =MIN(N('My Debts'!$E$7),C28) -> 0 | N28: =MIN(N('My Debts'!$E$8),D28) -> 0 | O28: =MIN(N('My Debts'!$E$9),E28) -> 0 | P28: =MIN(N('My Debts'!$E$10),F28) -> 0 | Q28: =MIN(N('My Debts'!$E$11),G28) -> 0 | R28: =MIN(N('My Debts'!$E$12),H28) -> 0 | S28: =MIN(N('My Debts'!$E$13),I28) -> 0 | T28: =MIN(N('My Debts'!$E$14),J28) -> 0 | U28: =MIN(N('My Debts'!$E$15),K28) -> 0 | V28: =ROUND(B28-L28-MIN(B28-L28,MAX(0,$AF28-SUMPRODUCT(--($B$4:$K$4<B$4),$B28:$K28-$L28:$U28))),2) -> 0 | W28: =ROUND(C28-M28-MIN(C28-M28,MAX(0,$AF28-SUMPRODUCT(--($B$4:$K$4<C$4),$B28:$K28-$L28:$U28))),2) -> 0 | X28: =ROUND(D28-N28-MIN(D28-N28,MAX(0,$AF28-SUMPRODUCT(--($B$4:$K$4<D$4),$B28:$K28-$L28:$U28))),2) -> 0 | Y28: =ROUND(E28-O28-MIN(E28-O28,MAX(0,$AF28-SUMPRODUCT(--($B$4:$K$4<E$4),$B28:$K28-$L28:$U28))),2) -> 0 | Z28: =ROUND(F28-P28-MIN(F28-P28,MAX(0,$AF28-SUMPRODUCT(--($B$4:$K$4<F$4),$B28:$K28-$L28:$U28))),2) -> 0 | AA28: =ROUND(G28-Q28-MIN(G28-Q28,MAX(0,$AF28-SUMPRODUCT(--($B$4:$K$4<G$4),$B28:$K28-$L28:$U28))),2) -> 0 | AB28: =ROUND(H28-R28-MIN(H28-R28,MAX(0,$AF28-SUMPRODUCT(--($B$4:$K$4<H$4),$B28:$K28-$L28:$U28))),2) -> 0 | AC28: =ROUND(I28-S28-MIN(I28-S28,MAX(0,$AF28-SUMPRODUCT(--($B$4:$K$4<I$4),$B28:$K28-$L28:$U28))),2) -> 0 | ... AE28: =ROUND(K28-U28-MIN(K28-U28,MAX(0,$AF28-SUMPRODUCT(--($B$4:$K$4<K$4),$B28:$K28-$L28:$U28))),2) -> 0 | AF28: =MAX(0,'Start Here'!$C$5-SUM($L28:$U28)) -> 1200 | AG28: =SUM(V28:AE28) -> 0 | AH28: =SUM(B28:K28)-AG27 -> 0
A29: =DATE(YEAR('Start Here'!$C$6),MONTH('Start Here'!$C$6)+22,1) -> 46966 | B29: =ROUND(V28*(1+N('My Debts'!$D$6)/12),2) -> 0 | C29: =ROUND(W28*(1+N('My Debts'!$D$7)/12),2) -> 0 | D29: =ROUND(X28*(1+N('My Debts'!$D$8)/12),2) -> 0 | E29: =ROUND(Y28*(1+N('My Debts'!$D$9)/12),2) -> 0 | F29: =ROUND(Z28*(1+N('My Debts'!$D$10)/12),2) -> 0 | G29: =ROUND(AA28*(1+N('My Debts'!$D$11)/12),2) -> 0 | H29: =ROUND(AB28*(1+N('My Debts'!$D$12)/12),2) -> 0 | I29: =ROUND(AC28*(1+N('My Debts'!$D$13)/12),2) -> 0 | J29: =ROUND(AD28*(1+N('My Debts'!$D$14)/12),2) -> 0 | K29: =ROUND(AE28*(1+N('My Debts'!$D$15)/12),2) -> 0 | L29: =MIN(N('My Debts'!$E$6),B29) -> 0 | M29: =MIN(N('My Debts'!$E$7),C29) -> 0 | N29: =MIN(N('My Debts'!$E$8),D29) -> 0 | O29: =MIN(N('My Debts'!$E$9),E29) -> 0 | P29: =MIN(N('My Debts'!$E$10),F29) -> 0 | Q29: =MIN(N('My Debts'!$E$11),G29) -> 0 | R29: =MIN(N('My Debts'!$E$12),H29) -> 0 | S29: =MIN(N('My Debts'!$E$13),I29) -> 0 | T29: =MIN(N('My Debts'!$E$14),J29) -> 0 | U29: =MIN(N('My Debts'!$E$15),K29) -> 0 | V29: =ROUND(B29-L29-MIN(B29-L29,MAX(0,$AF29-SUMPRODUCT(--($B$4:$K$4<B$4),$B29:$K29-$L29:$U29))),2) -> 0 | W29: =ROUND(C29-M29-MIN(C29-M29,MAX(0,$AF29-SUMPRODUCT(--($B$4:$K$4<C$4),$B29:$K29-$L29:$U29))),2) -> 0 | X29: =ROUND(D29-N29-MIN(D29-N29,MAX(0,$AF29-SUMPRODUCT(--($B$4:$K$4<D$4),$B29:$K29-$L29:$U29))),2) -> 0 | Y29: =ROUND(E29-O29-MIN(E29-O29,MAX(0,$AF29-SUMPRODUCT(--($B$4:$K$4<E$4),$B29:$K29-$L29:$U29))),2) -> 0 | Z29: =ROUND(F29-P29-MIN(F29-P29,MAX(0,$AF29-SUMPRODUCT(--($B$4:$K$4<F$4),$B29:$K29-$L29:$U29))),2) -> 0 | AA29: =ROUND(G29-Q29-MIN(G29-Q29,MAX(0,$AF29-SUMPRODUCT(--($B$4:$K$4<G$4),$B29:$K29-$L29:$U29))),2) -> 0 | AB29: =ROUND(H29-R29-MIN(H29-R29,MAX(0,$AF29-SUMPRODUCT(--($B$4:$K$4<H$4),$B29:$K29-$L29:$U29))),2) -> 0 | AC29: =ROUND(I29-S29-MIN(I29-S29,MAX(0,$AF29-SUMPRODUCT(--($B$4:$K$4<I$4),$B29:$K29-$L29:$U29))),2) -> 0 | ... AE29: =ROUND(K29-U29-MIN(K29-U29,MAX(0,$AF29-SUMPRODUCT(--($B$4:$K$4<K$4),$B29:$K29-$L29:$U29))),2) -> 0 | AF29: =MAX(0,'Start Here'!$C$5-SUM($L29:$U29)) -> 1200 | AG29: =SUM(V29:AE29) -> 0 | AH29: =SUM(B29:K29)-AG28 -> 0
A30: =DATE(YEAR('Start Here'!$C$6),MONTH('Start Here'!$C$6)+23,1) -> 46997 | B30: =ROUND(V29*(1+N('My Debts'!$D$6)/12),2) -> 0 | C30: =ROUND(W29*(1+N('My Debts'!$D$7)/12),2) -> 0 | D30: =ROUND(X29*(1+N('My Debts'!$D$8)/12),2) -> 0 | E30: =ROUND(Y29*(1+N('My Debts'!$D$9)/12),2) -> 0 | F30: =ROUND(Z29*(1+N('My Debts'!$D$10)/12),2) -> 0 | G30: =ROUND(AA29*(1+N('My Debts'!$D$11)/12),2) -> 0 | H30: =ROUND(AB29*(1+N('My Debts'!$D$12)/12),2) -> 0 | I30: =ROUND(AC29*(1+N('My Debts'!$D$13)/12),2) -> 0 | J30: =ROUND(AD29*(1+N('My Debts'!$D$14)/12),2) -> 0 | K30: =ROUND(AE29*(1+N('My Debts'!$D$15)/12),2) -> 0 | L30: =MIN(N('My Debts'!$E$6),B30) -> 0 | M30: =MIN(N('My Debts'!$E$7),C30) -> 0 | N30: =MIN(N('My Debts'!$E$8),D30) -> 0 | O30: =MIN(N('My Debts'!$E$9),E30) -> 0 | P30: =MIN(N('My Debts'!$E$10),F30) -> 0 | Q30: =MIN(N('My Debts'!$E$11),G30) -> 0 | R30: =MIN(N('My Debts'!$E$12),H30) -> 0 | S30: =MIN(N('My Debts'!$E$13),I30) -> 0 | T30: =MIN(N('My Debts'!$E$14),J30) -> 0 | U30: =MIN(N('My Debts'!$E$15),K30) -> 0 | V30: =ROUND(B30-L30-MIN(B30-L30,MAX(0,$AF30-SUMPRODUCT(--($B$4:$K$4<B$4),$B30:$K30-$L30:$U30))),2) -> 0 | W30: =ROUND(C30-M30-MIN(C30-M30,MAX(0,$AF30-SUMPRODUCT(--($B$4:$K$4<C$4),$B30:$K30-$L30:$U30))),2) -> 0 | X30: =ROUND(D30-N30-MIN(D30-N30,MAX(0,$AF30-SUMPRODUCT(--($B$4:$K$4<D$4),$B30:$K30-$L30:$U30))),2) -> 0 | Y30: =ROUND(E30-O30-MIN(E30-O30,MAX(0,$AF30-SUMPRODUCT(--($B$4:$K$4<E$4),$B30:$K30-$L30:$U30))),2) -> 0 | Z30: =ROUND(F30-P30-MIN(F30-P30,MAX(0,$AF30-SUMPRODUCT(--($B$4:$K$4<F$4),$B30:$K30-$L30:$U30))),2) -> 0 | AA30: =ROUND(G30-Q30-MIN(G30-Q30,MAX(0,$AF30-SUMPRODUCT(--($B$4:$K$4<G$4),$B30:$K30-$L30:$U30))),2) -> 0 | AB30: =ROUND(H30-R30-MIN(H30-R30,MAX(0,$AF30-SUMPRODUCT(--($B$4:$K$4<H$4),$B30:$K30-$L30:$U30))),2) -> 0 | AC30: =ROUND(I30-S30-MIN(I30-S30,MAX(0,$AF30-SUMPRODUCT(--($B$4:$K$4<I$4),$B30:$K30-$L30:$U30))),2) -> 0 | ... AE30: =ROUND(K30-U30-MIN(K30-U30,MAX(0,$AF30-SUMPRODUCT(--($B$4:$K$4<K$4),$B30:$K30-$L30:$U30))),2) -> 0 | AF30: =MAX(0,'Start Here'!$C$5-SUM($L30:$U30)) -> 1200 | AG30: =SUM(V30:AE30) -> 0 | AH30: =SUM(B30:K30)-AG29 -> 0
A31: =DATE(YEAR('Start Here'!$C$6),MONTH('Start Here'!$C$6)+24,1) -> 47027 | B31: =ROUND(V30*(1+N('My Debts'!$D$6)/12),2) -> 0 | C31: =ROUND(W30*(1+N('My Debts'!$D$7)/12),2) -> 0 | D31: =ROUND(X30*(1+N('My Debts'!$D$8)/12),2) -> 0 | E31: =ROUND(Y30*(1+N('My Debts'!$D$9)/12),2) -> 0 | F31: =ROUND(Z30*(1+N('My Debts'!$D$10)/12),2) -> 0 | G31: =ROUND(AA30*(1+N('My Debts'!$D$11)/12),2) -> 0 | H31: =ROUND(AB30*(1+N('My Debts'!$D$12)/12),2) -> 0 | I31: =ROUND(AC30*(1+N('My Debts'!$D$13)/12),2) -> 0 | J31: =ROUND(AD30*(1+N('My Debts'!$D$14)/12),2) -> 0 | K31: =ROUND(AE30*(1+N('My Debts'!$D$15)/12),2) -> 0 | L31: =MIN(N('My Debts'!$E$6),B31) -> 0 | M31: =MIN(N('My Debts'!$E$7),C31) -> 0 | N31: =MIN(N('My Debts'!$E$8),D31) -> 0 | O31: =MIN(N('My Debts'!$E$9),E31) -> 0 | P31: =MIN(N('My Debts'!$E$10),F31) -> 0 | Q31: =MIN(N('My Debts'!$E$11),G31) -> 0 | R31: =MIN(N('My Debts'!$E$12),H31) -> 0 | S31: =MIN(N('My Debts'!$E$13),I31) -> 0 | T31: =MIN(N('My Debts'!$E$14),J31) -> 0 | U31: =MIN(N('My Debts'!$E$15),K31) -> 0 | V31: =ROUND(B31-L31-MIN(B31-L31,MAX(0,$AF31-SUMPRODUCT(--($B$4:$K$4<B$4),$B31:$K31-$L31:$U31))),2) -> 0 | W31: =ROUND(C31-M31-MIN(C31-M31,MAX(0,$AF31-SUMPRODUCT(--($B$4:$K$4<C$4),$B31:$K31-$L31:$U31))),2) -> 0 | X31: =ROUND(D31-N31-MIN(D31-N31,MAX(0,$AF31-SUMPRODUCT(--($B$4:$K$4<D$4),$B31:$K31-$L31:$U31))),2) -> 0 | Y31: =ROUND(E31-O31-MIN(E31-O31,MAX(0,$AF31-SUMPRODUCT(--($B$4:$K$4<E$4),$B31:$K31-$L31:$U31))),2) -> 0 | Z31: =ROUND(F31-P31-MIN(F31-P31,MAX(0,$AF31-SUMPRODUCT(--($B$4:$K$4<F$4),$B31:$K31-$L31:$U31))),2) -> 0 | AA31: =ROUND(G31-Q31-MIN(G31-Q31,MAX(0,$AF31-SUMPRODUCT(--($B$4:$K$4<G$4),$B31:$K31-$L31:$U31))),2) -> 0 | AB31: =ROUND(H31-R31-MIN(H31-R31,MAX(0,$AF31-SUMPRODUCT(--($B$4:$K$4<H$4),$B31:$K31-$L31:$U31))),2) -> 0 | AC31: =ROUND(I31-S31-MIN(I31-S31,MAX(0,$AF31-SUMPRODUCT(--($B$4:$K$4<I$4),$B31:$K31-$L31:$U31))),2) -> 0 | ... AE31: =ROUND(K31-U31-MIN(K31-U31,MAX(0,$AF31-SUMPRODUCT(--($B$4:$K$4<K$4),$B31:$K31-$L31:$U31))),2) -> 0 | AF31: =MAX(0,'Start Here'!$C$5-SUM($L31:$U31)) -> 1200 | AG31: =SUM(V31:AE31) -> 0 | AH31: =SUM(B31:K31)-AG30 -> 0
A32: =DATE(YEAR('Start Here'!$C$6),MONTH('Start Here'!$C$6)+25,1) -> 47058 | B32: =ROUND(V31*(1+N('My Debts'!$D$6)/12),2) -> 0 | C32: =ROUND(W31*(1+N('My Debts'!$D$7)/12),2) -> 0 | D32: =ROUND(X31*(1+N('My Debts'!$D$8)/12),2) -> 0 | E32: =ROUND(Y31*(1+N('My Debts'!$D$9)/12),2) -> 0 | F32: =ROUND(Z31*(1+N('My Debts'!$D$10)/12),2) -> 0 | G32: =ROUND(AA31*(1+N('My Debts'!$D$11)/12),2) -> 0 | H32: =ROUND(AB31*(1+N('My Debts'!$D$12)/12),2) -> 0 | I32: =ROUND(AC31*(1+N('My Debts'!$D$13)/12),2) -> 0 | J32: =ROUND(AD31*(1+N('My Debts'!$D$14)/12),2) -> 0 | K32: =ROUND(AE31*(1+N('My Debts'!$D$15)/12),2) -> 0 | L32: =MIN(N('My Debts'!$E$6),B32) -> 0 | M32: =MIN(N('My Debts'!$E$7),C32) -> 0 | N32: =MIN(N('My Debts'!$E$8),D32) -> 0 | O32: =MIN(N('My Debts'!$E$9),E32) -> 0 | P32: =MIN(N('My Debts'!$E$10),F32) -> 0 | Q32: =MIN(N('My Debts'!$E$11),G32) -> 0 | R32: =MIN(N('My Debts'!$E$12),H32) -> 0 | S32: =MIN(N('My Debts'!$E$13),I32) -> 0 | T32: =MIN(N('My Debts'!$E$14),J32) -> 0 | U32: =MIN(N('My Debts'!$E$15),K32) -> 0 | V32: =ROUND(B32-L32-MIN(B32-L32,MAX(0,$AF32-SUMPRODUCT(--($B$4:$K$4<B$4),$B32:$K32-$L32:$U32))),2) -> 0 | W32: =ROUND(C32-M32-MIN(C32-M32,MAX(0,$AF32-SUMPRODUCT(--($B$4:$K$4<C$4),$B32:$K32-$L32:$U32))),2) -> 0 | X32: =ROUND(D32-N32-MIN(D32-N32,MAX(0,$AF32-SUMPRODUCT(--($B$4:$K$4<D$4),$B32:$K32-$L32:$U32))),2) -> 0 | Y32: =ROUND(E32-O32-MIN(E32-O32,MAX(0,$AF32-SUMPRODUCT(--($B$4:$K$4<E$4),$B32:$K32-$L32:$U32))),2) -> 0 | Z32: =ROUND(F32-P32-MIN(F32-P32,MAX(0,$AF32-SUMPRODUCT(--($B$4:$K$4<F$4),$B32:$K32-$L32:$U32))),2) -> 0 | AA32: =ROUND(G32-Q32-MIN(G32-Q32,MAX(0,$AF32-SUMPRODUCT(--($B$4:$K$4<G$4),$B32:$K32-$L32:$U32))),2) -> 0 | AB32: =ROUND(H32-R32-MIN(H32-R32,MAX(0,$AF32-SUMPRODUCT(--($B$4:$K$4<H$4),$B32:$K32-$L32:$U32))),2) -> 0 | AC32: =ROUND(I32-S32-MIN(I32-S32,MAX(0,$AF32-SUMPRODUCT(--($B$4:$K$4<I$4),$B32:$K32-$L32:$U32))),2) -> 0 | ... AE32: =ROUND(K32-U32-MIN(K32-U32,MAX(0,$AF32-SUMPRODUCT(--($B$4:$K$4<K$4),$B32:$K32-$L32:$U32))),2) -> 0 | AF32: =MAX(0,'Start Here'!$C$5-SUM($L32:$U32)) -> 1200 | AG32: =SUM(V32:AE32) -> 0 | AH32: =SUM(B32:K32)-AG31 -> 0
A33: =DATE(YEAR('Start Here'!$C$6),MONTH('Start Here'!$C$6)+26,1) -> 47088 | B33: =ROUND(V32*(1+N('My Debts'!$D$6)/12),2) -> 0 | C33: =ROUND(W32*(1+N('My Debts'!$D$7)/12),2) -> 0 | D33: =ROUND(X32*(1+N('My Debts'!$D$8)/12),2) -> 0 | E33: =ROUND(Y32*(1+N('My Debts'!$D$9)/12),2) -> 0 | F33: =ROUND(Z32*(1+N('My Debts'!$D$10)/12),2) -> 0 | G33: =ROUND(AA32*(1+N('My Debts'!$D$11)/12),2) -> 0 | H33: =ROUND(AB32*(1+N('My Debts'!$D$12)/12),2) -> 0 | I33: =ROUND(AC32*(1+N('My Debts'!$D$13)/12),2) -> 0 | J33: =ROUND(AD32*(1+N('My Debts'!$D$14)/12),2) -> 0 | K33: =ROUND(AE32*(1+N('My Debts'!$D$15)/12),2) -> 0 | L33: =MIN(N('My Debts'!$E$6),B33) -> 0 | M33: =MIN(N('My Debts'!$E$7),C33) -> 0 | N33: =MIN(N('My Debts'!$E$8),D33) -> 0 | O33: =MIN(N('My Debts'!$E$9),E33) -> 0 | P33: =MIN(N('My Debts'!$E$10),F33) -> 0 | Q33: =MIN(N('My Debts'!$E$11),G33) -> 0 | R33: =MIN(N('My Debts'!$E$12),H33) -> 0 | S33: =MIN(N('My Debts'!$E$13),I33) -> 0 | T33: =MIN(N('My Debts'!$E$14),J33) -> 0 | U33: =MIN(N('My Debts'!$E$15),K33) -> 0 | V33: =ROUND(B33-L33-MIN(B33-L33,MAX(0,$AF33-SUMPRODUCT(--($B$4:$K$4<B$4),$B33:$K33-$L33:$U33))),2) -> 0 | W33: =ROUND(C33-M33-MIN(C33-M33,MAX(0,$AF33-SUMPRODUCT(--($B$4:$K$4<C$4),$B33:$K33-$L33:$U33))),2) -> 0 | X33: =ROUND(D33-N33-MIN(D33-N33,MAX(0,$AF33-SUMPRODUCT(--($B$4:$K$4<D$4),$B33:$K33-$L33:$U33))),2) -> 0 | Y33: =ROUND(E33-O33-MIN(E33-O33,MAX(0,$AF33-SUMPRODUCT(--($B$4:$K$4<E$4),$B33:$K33-$L33:$U33))),2) -> 0 | Z33: =ROUND(F33-P33-MIN(F33-P33,MAX(0,$AF33-SUMPRODUCT(--($B$4:$K$4<F$4),$B33:$K33-$L33:$U33))),2) -> 0 | AA33: =ROUND(G33-Q33-MIN(G33-Q33,MAX(0,$AF33-SUMPRODUCT(--($B$4:$K$4<G$4),$B33:$K33-$L33:$U33))),2) -> 0 | AB33: =ROUND(H33-R33-MIN(H33-R33,MAX(0,$AF33-SUMPRODUCT(--($B$4:$K$4<H$4),$B33:$K33-$L33:$U33))),2) -> 0 | AC33: =ROUND(I33-S33-MIN(I33-S33,MAX(0,$AF33-SUMPRODUCT(--($B$4:$K$4<I$4),$B33:$K33-$L33:$U33))),2) -> 0 | ... AE33: =ROUND(K33-U33-MIN(K33-U33,MAX(0,$AF33-SUMPRODUCT(--($B$4:$K$4<K$4),$B33:$K33-$L33:$U33))),2) -> 0 | AF33: =MAX(0,'Start Here'!$C$5-SUM($L33:$U33)) -> 1200 | AG33: =SUM(V33:AE33) -> 0 | AH33: =SUM(B33:K33)-AG32 -> 0
A34: =DATE(YEAR('Start Here'!$C$6),MONTH('Start Here'!$C$6)+27,1) -> 47119 | B34: =ROUND(V33*(1+N('My Debts'!$D$6)/12),2) -> 0 | C34: =ROUND(W33*(1+N('My Debts'!$D$7)/12),2) -> 0 | D34: =ROUND(X33*(1+N('My Debts'!$D$8)/12),2) -> 0 | E34: =ROUND(Y33*(1+N('My Debts'!$D$9)/12),2) -> 0 | F34: =ROUND(Z33*(1+N('My Debts'!$D$10)/12),2) -> 0 | G34: =ROUND(AA33*(1+N('My Debts'!$D$11)/12),2) -> 0 | H34: =ROUND(AB33*(1+N('My Debts'!$D$12)/12),2) -> 0 | I34: =ROUND(AC33*(1+N('My Debts'!$D$13)/12),2) -> 0 | J34: =ROUND(AD33*(1+N('My Debts'!$D$14)/12),2) -> 0 | K34: =ROUND(AE33*(1+N('My Debts'!$D$15)/12),2) -> 0 | L34: =MIN(N('My Debts'!$E$6),B34) -> 0 | M34: =MIN(N('My Debts'!$E$7),C34) -> 0 | N34: =MIN(N('My Debts'!$E$8),D34) -> 0 | O34: =MIN(N('My Debts'!$E$9),E34) -> 0 | P34: =MIN(N('My Debts'!$E$10),F34) -> 0 | Q34: =MIN(N('My Debts'!$E$11),G34) -> 0 | R34: =MIN(N('My Debts'!$E$12),H34) -> 0 | S34: =MIN(N('My Debts'!$E$13),I34) -> 0 | T34: =MIN(N('My Debts'!$E$14),J34) -> 0 | U34: =MIN(N('My Debts'!$E$15),K34) -> 0 | V34: =ROUND(B34-L34-MIN(B34-L34,MAX(0,$AF34-SUMPRODUCT(--($B$4:$K$4<B$4),$B34:$K34-$L34:$U34))),2) -> 0 | W34: =ROUND(C34-M34-MIN(C34-M34,MAX(0,$AF34-SUMPRODUCT(--($B$4:$K$4<C$4),$B34:$K34-$L34:$U34))),2) -> 0 | X34: =ROUND(D34-N34-MIN(D34-N34,MAX(0,$AF34-SUMPRODUCT(--($B$4:$K$4<D$4),$B34:$K34-$L34:$U34))),2) -> 0 | Y34: =ROUND(E34-O34-MIN(E34-O34,MAX(0,$AF34-SUMPRODUCT(--($B$4:$K$4<E$4),$B34:$K34-$L34:$U34))),2) -> 0 | Z34: =ROUND(F34-P34-MIN(F34-P34,MAX(0,$AF34-SUMPRODUCT(--($B$4:$K$4<F$4),$B34:$K34-$L34:$U34))),2) -> 0 | AA34: =ROUND(G34-Q34-MIN(G34-Q34,MAX(0,$AF34-SUMPRODUCT(--($B$4:$K$4<G$4),$B34:$K34-$L34:$U34))),2) -> 0 | AB34: =ROUND(H34-R34-MIN(H34-R34,MAX(0,$AF34-SUMPRODUCT(--($B$4:$K$4<H$4),$B34:$K34-$L34:$U34))),2) -> 0 | AC34: =ROUND(I34-S34-MIN(I34-S34,MAX(0,$AF34-SUMPRODUCT(--($B$4:$K$4<I$4),$B34:$K34-$L34:$U34))),2) -> 0 | ... AE34: =ROUND(K34-U34-MIN(K34-U34,MAX(0,$AF34-SUMPRODUCT(--($B$4:$K$4<K$4),$B34:$K34-$L34:$U34))),2) -> 0 | AF34: =MAX(0,'Start Here'!$C$5-SUM($L34:$U34)) -> 1200 | AG34: =SUM(V34:AE34) -> 0 | AH34: =SUM(B34:K34)-AG33 -> 0
A35: =DATE(YEAR('Start Here'!$C$6),MONTH('Start Here'!$C$6)+28,1) -> 47150 | B35: =ROUND(V34*(1+N('My Debts'!$D$6)/12),2) -> 0 | C35: =ROUND(W34*(1+N('My Debts'!$D$7)/12),2) -> 0 | D35: =ROUND(X34*(1+N('My Debts'!$D$8)/12),2) -> 0 | E35: =ROUND(Y34*(1+N('My Debts'!$D$9)/12),2) -> 0 | F35: =ROUND(Z34*(1+N('My Debts'!$D$10)/12),2) -> 0 | G35: =ROUND(AA34*(1+N('My Debts'!$D$11)/12),2) -> 0 | H35: =ROUND(AB34*(1+N('My Debts'!$D$12)/12),2) -> 0 | I35: =ROUND(AC34*(1+N('My Debts'!$D$13)/12),2) -> 0 | J35: =ROUND(AD34*(1+N('My Debts'!$D$14)/12),2) -> 0 | K35: =ROUND(AE34*(1+N('My Debts'!$D$15)/12),2) -> 0 | L35: =MIN(N('My Debts'!$E$6),B35) -> 0 | M35: =MIN(N('My Debts'!$E$7),C35) -> 0 | N35: =MIN(N('My Debts'!$E$8),D35) -> 0 | O35: =MIN(N('My Debts'!$E$9),E35) -> 0 | P35: =MIN(N('My Debts'!$E$10),F35) -> 0 | Q35: =MIN(N('My Debts'!$E$11),G35) -> 0 | R35: =MIN(N('My Debts'!$E$12),H35) -> 0 | S35: =MIN(N('My Debts'!$E$13),I35) -> 0 | T35: =MIN(N('My Debts'!$E$14),J35) -> 0 | U35: =MIN(N('My Debts'!$E$15),K35) -> 0 | V35: =ROUND(B35-L35-MIN(B35-L35,MAX(0,$AF35-SUMPRODUCT(--($B$4:$K$4<B$4),$B35:$K35-$L35:$U35))),2) -> 0 | W35: =ROUND(C35-M35-MIN(C35-M35,MAX(0,$AF35-SUMPRODUCT(--($B$4:$K$4<C$4),$B35:$K35-$L35:$U35))),2) -> 0 | X35: =ROUND(D35-N35-MIN(D35-N35,MAX(0,$AF35-SUMPRODUCT(--($B$4:$K$4<D$4),$B35:$K35-$L35:$U35))),2) -> 0 | Y35: =ROUND(E35-O35-MIN(E35-O35,MAX(0,$AF35-SUMPRODUCT(--($B$4:$K$4<E$4),$B35:$K35-$L35:$U35))),2) -> 0 | Z35: =ROUND(F35-P35-MIN(F35-P35,MAX(0,$AF35-SUMPRODUCT(--($B$4:$K$4<F$4),$B35:$K35-$L35:$U35))),2) -> 0 | AA35: =ROUND(G35-Q35-MIN(G35-Q35,MAX(0,$AF35-SUMPRODUCT(--($B$4:$K$4<G$4),$B35:$K35-$L35:$U35))),2) -> 0 | AB35: =ROUND(H35-R35-MIN(H35-R35,MAX(0,$AF35-SUMPRODUCT(--($B$4:$K$4<H$4),$B35:$K35-$L35:$U35))),2) -> 0 | AC35: =ROUND(I35-S35-MIN(I35-S35,MAX(0,$AF35-SUMPRODUCT(--($B$4:$K$4<I$4),$B35:$K35-$L35:$U35))),2) -> 0 | ... AE35: =ROUND(K35-U35-MIN(K35-U35,MAX(0,$AF35-SUMPRODUCT(--($B$4:$K$4<K$4),$B35:$K35-$L35:$U35))),2) -> 0 | AF35: =MAX(0,'Start Here'!$C$5-SUM($L35:$U35)) -> 1200 | AG35: =SUM(V35:AE35) -> 0 | AH35: =SUM(B35:K35)-AG34 -> 0
A36: =DATE(YEAR('Start Here'!$C$6),MONTH('Start Here'!$C$6)+29,1) -> 47178 | B36: =ROUND(V35*(1+N('My Debts'!$D$6)/12),2) -> 0 | C36: =ROUND(W35*(1+N('My Debts'!$D$7)/12),2) -> 0 | D36: =ROUND(X35*(1+N('My Debts'!$D$8)/12),2) -> 0 | E36: =ROUND(Y35*(1+N('My Debts'!$D$9)/12),2) -> 0 | F36: =ROUND(Z35*(1+N('My Debts'!$D$10)/12),2) -> 0 | G36: =ROUND(AA35*(1+N('My Debts'!$D$11)/12),2) -> 0 | H36: =ROUND(AB35*(1+N('My Debts'!$D$12)/12),2) -> 0 | I36: =ROUND(AC35*(1+N('My Debts'!$D$13)/12),2) -> 0 | J36: =ROUND(AD35*(1+N('My Debts'!$D$14)/12),2) -> 0 | K36: =ROUND(AE35*(1+N('My Debts'!$D$15)/12),2) -> 0 | L36: =MIN(N('My Debts'!$E$6),B36) -> 0 | M36: =MIN(N('My Debts'!$E$7),C36) -> 0 | N36: =MIN(N('My Debts'!$E$8),D36) -> 0 | O36: =MIN(N('My Debts'!$E$9),E36) -> 0 | P36: =MIN(N('My Debts'!$E$10),F36) -> 0 | Q36: =MIN(N('My Debts'!$E$11),G36) -> 0 | R36: =MIN(N('My Debts'!$E$12),H36) -> 0 | S36: =MIN(N('My Debts'!$E$13),I36) -> 0 | T36: =MIN(N('My Debts'!$E$14),J36) -> 0 | U36: =MIN(N('My Debts'!$E$15),K36) -> 0 | V36: =ROUND(B36-L36-MIN(B36-L36,MAX(0,$AF36-SUMPRODUCT(--($B$4:$K$4<B$4),$B36:$K36-$L36:$U36))),2) -> 0 | W36: =ROUND(C36-M36-MIN(C36-M36,MAX(0,$AF36-SUMPRODUCT(--($B$4:$K$4<C$4),$B36:$K36-$L36:$U36))),2) -> 0 | X36: =ROUND(D36-N36-MIN(D36-N36,MAX(0,$AF36-SUMPRODUCT(--($B$4:$K$4<D$4),$B36:$K36-$L36:$U36))),2) -> 0 | Y36: =ROUND(E36-O36-MIN(E36-O36,MAX(0,$AF36-SUMPRODUCT(--($B$4:$K$4<E$4),$B36:$K36-$L36:$U36))),2) -> 0 | Z36: =ROUND(F36-P36-MIN(F36-P36,MAX(0,$AF36-SUMPRODUCT(--($B$4:$K$4<F$4),$B36:$K36-$L36:$U36))),2) -> 0 | AA36: =ROUND(G36-Q36-MIN(G36-Q36,MAX(0,$AF36-SUMPRODUCT(--($B$4:$K$4<G$4),$B36:$K36-$L36:$U36))),2) -> 0 | AB36: =ROUND(H36-R36-MIN(H36-R36,MAX(0,$AF36-SUMPRODUCT(--($B$4:$K$4<H$4),$B36:$K36-$L36:$U36))),2) -> 0 | AC36: =ROUND(I36-S36-MIN(I36-S36,MAX(0,$AF36-SUMPRODUCT(--($B$4:$K$4<I$4),$B36:$K36-$L36:$U36))),2) -> 0 | ... AE36: =ROUND(K36-U36-MIN(K36-U36,MAX(0,$AF36-SUMPRODUCT(--($B$4:$K$4<K$4),$B36:$K36-$L36:$U36))),2) -> 0 | AF36: =MAX(0,'Start Here'!$C$5-SUM($L36:$U36)) -> 1200 | AG36: =SUM(V36:AE36) -> 0 | AH36: =SUM(B36:K36)-AG35 -> 0
A37: =DATE(YEAR('Start Here'!$C$6),MONTH('Start Here'!$C$6)+30,1) -> 47209 | B37: =ROUND(V36*(1+N('My Debts'!$D$6)/12),2) -> 0 | C37: =ROUND(W36*(1+N('My Debts'!$D$7)/12),2) -> 0 | D37: =ROUND(X36*(1+N('My Debts'!$D$8)/12),2) -> 0 | E37: =ROUND(Y36*(1+N('My Debts'!$D$9)/12),2) -> 0 | F37: =ROUND(Z36*(1+N('My Debts'!$D$10)/12),2) -> 0 | G37: =ROUND(AA36*(1+N('My Debts'!$D$11)/12),2) -> 0 | H37: =ROUND(AB36*(1+N('My Debts'!$D$12)/12),2) -> 0 | I37: =ROUND(AC36*(1+N('My Debts'!$D$13)/12),2) -> 0 | J37: =ROUND(AD36*(1+N('My Debts'!$D$14)/12),2) -> 0 | K37: =ROUND(AE36*(1+N('My Debts'!$D$15)/12),2) -> 0 | L37: =MIN(N('My Debts'!$E$6),B37) -> 0 | M37: =MIN(N('My Debts'!$E$7),C37) -> 0 | N37: =MIN(N('My Debts'!$E$8),D37) -> 0 | O37: =MIN(N('My Debts'!$E$9),E37) -> 0 | P37: =MIN(N('My Debts'!$E$10),F37) -> 0 | Q37: =MIN(N('My Debts'!$E$11),G37) -> 0 | R37: =MIN(N('My Debts'!$E$12),H37) -> 0 | S37: =MIN(N('My Debts'!$E$13),I37) -> 0 | T37: =MIN(N('My Debts'!$E$14),J37) -> 0 | U37: =MIN(N('My Debts'!$E$15),K37) -> 0 | V37: =ROUND(B37-L37-MIN(B37-L37,MAX(0,$AF37-SUMPRODUCT(--($B$4:$K$4<B$4),$B37:$K37-$L37:$U37))),2) -> 0 | W37: =ROUND(C37-M37-MIN(C37-M37,MAX(0,$AF37-SUMPRODUCT(--($B$4:$K$4<C$4),$B37:$K37-$L37:$U37))),2) -> 0 | X37: =ROUND(D37-N37-MIN(D37-N37,MAX(0,$AF37-SUMPRODUCT(--($B$4:$K$4<D$4),$B37:$K37-$L37:$U37))),2) -> 0 | Y37: =ROUND(E37-O37-MIN(E37-O37,MAX(0,$AF37-SUMPRODUCT(--($B$4:$K$4<E$4),$B37:$K37-$L37:$U37))),2) -> 0 | Z37: =ROUND(F37-P37-MIN(F37-P37,MAX(0,$AF37-SUMPRODUCT(--($B$4:$K$4<F$4),$B37:$K37-$L37:$U37))),2) -> 0 | AA37: =ROUND(G37-Q37-MIN(G37-Q37,MAX(0,$AF37-SUMPRODUCT(--($B$4:$K$4<G$4),$B37:$K37-$L37:$U37))),2) -> 0 | AB37: =ROUND(H37-R37-MIN(H37-R37,MAX(0,$AF37-SUMPRODUCT(--($B$4:$K$4<H$4),$B37:$K37-$L37:$U37))),2) -> 0 | AC37: =ROUND(I37-S37-MIN(I37-S37,MAX(0,$AF37-SUMPRODUCT(--($B$4:$K$4<I$4),$B37:$K37-$L37:$U37))),2) -> 0 | ... AE37: =ROUND(K37-U37-MIN(K37-U37,MAX(0,$AF37-SUMPRODUCT(--($B$4:$K$4<K$4),$B37:$K37-$L37:$U37))),2) -> 0 | AF37: =MAX(0,'Start Here'!$C$5-SUM($L37:$U37)) -> 1200 | AG37: =SUM(V37:AE37) -> 0 | AH37: =SUM(B37:K37)-AG36 -> 0
A38: =DATE(YEAR('Start Here'!$C$6),MONTH('Start Here'!$C$6)+31,1) -> 47239 | B38: =ROUND(V37*(1+N('My Debts'!$D$6)/12),2) -> 0 | C38: =ROUND(W37*(1+N('My Debts'!$D$7)/12),2) -> 0 | D38: =ROUND(X37*(1+N('My Debts'!$D$8)/12),2) -> 0 | E38: =ROUND(Y37*(1+N('My Debts'!$D$9)/12),2) -> 0 | F38: =ROUND(Z37*(1+N('My Debts'!$D$10)/12),2) -> 0 | G38: =ROUND(AA37*(1+N('My Debts'!$D$11)/12),2) -> 0 | H38: =ROUND(AB37*(1+N('My Debts'!$D$12)/12),2) -> 0 | I38: =ROUND(AC37*(1+N('My Debts'!$D$13)/12),2) -> 0 | J38: =ROUND(AD37*(1+N('My Debts'!$D$14)/12),2) -> 0 | K38: =ROUND(AE37*(1+N('My Debts'!$D$15)/12),2) -> 0 | L38: =MIN(N('My Debts'!$E$6),B38) -> 0 | M38: =MIN(N('My Debts'!$E$7),C38) -> 0 | N38: =MIN(N('My Debts'!$E$8),D38) -> 0 | O38: =MIN(N('My Debts'!$E$9),E38) -> 0 | P38: =MIN(N('My Debts'!$E$10),F38) -> 0 | Q38: =MIN(N('My Debts'!$E$11),G38) -> 0 | R38: =MIN(N('My Debts'!$E$12),H38) -> 0 | S38: =MIN(N('My Debts'!$E$13),I38) -> 0 | T38: =MIN(N('My Debts'!$E$14),J38) -> 0 | U38: =MIN(N('My Debts'!$E$15),K38) -> 0 | V38: =ROUND(B38-L38-MIN(B38-L38,MAX(0,$AF38-SUMPRODUCT(--($B$4:$K$4<B$4),$B38:$K38-$L38:$U38))),2) -> 0 | W38: =ROUND(C38-M38-MIN(C38-M38,MAX(0,$AF38-SUMPRODUCT(--($B$4:$K$4<C$4),$B38:$K38-$L38:$U38))),2) -> 0 | X38: =ROUND(D38-N38-MIN(D38-N38,MAX(0,$AF38-SUMPRODUCT(--($B$4:$K$4<D$4),$B38:$K38-$L38:$U38))),2) -> 0 | Y38: =ROUND(E38-O38-MIN(E38-O38,MAX(0,$AF38-SUMPRODUCT(--($B$4:$K$4<E$4),$B38:$K38-$L38:$U38))),2) -> 0 | Z38: =ROUND(F38-P38-MIN(F38-P38,MAX(0,$AF38-SUMPRODUCT(--($B$4:$K$4<F$4),$B38:$K38-$L38:$U38))),2) -> 0 | AA38: =ROUND(G38-Q38-MIN(G38-Q38,MAX(0,$AF38-SUMPRODUCT(--($B$4:$K$4<G$4),$B38:$K38-$L38:$U38))),2) -> 0 | AB38: =ROUND(H38-R38-MIN(H38-R38,MAX(0,$AF38-SUMPRODUCT(--($B$4:$K$4<H$4),$B38:$K38-$L38:$U38))),2) -> 0 | AC38: =ROUND(I38-S38-MIN(I38-S38,MAX(0,$AF38-SUMPRODUCT(--($B$4:$K$4<I$4),$B38:$K38-$L38:$U38))),2) -> 0 | ... AE38: =ROUND(K38-U38-MIN(K38-U38,MAX(0,$AF38-SUMPRODUCT(--($B$4:$K$4<K$4),$B38:$K38-$L38:$U38))),2) -> 0 | AF38: =MAX(0,'Start Here'!$C$5-SUM($L38:$U38)) -> 1200 | AG38: =SUM(V38:AE38) -> 0 | AH38: =SUM(B38:K38)-AG37 -> 0
A39: =DATE(YEAR('Start Here'!$C$6),MONTH('Start Here'!$C$6)+32,1) -> 47270 | B39: =ROUND(V38*(1+N('My Debts'!$D$6)/12),2) -> 0 | C39: =ROUND(W38*(1+N('My Debts'!$D$7)/12),2) -> 0 | D39: =ROUND(X38*(1+N('My Debts'!$D$8)/12),2) -> 0 | E39: =ROUND(Y38*(1+N('My Debts'!$D$9)/12),2) -> 0 | F39: =ROUND(Z38*(1+N('My Debts'!$D$10)/12),2) -> 0 | G39: =ROUND(AA38*(1+N('My Debts'!$D$11)/12),2) -> 0 | H39: =ROUND(AB38*(1+N('My Debts'!$D$12)/12),2) -> 0 | I39: =ROUND(AC38*(1+N('My Debts'!$D$13)/12),2) -> 0 | J39: =ROUND(AD38*(1+N('My Debts'!$D$14)/12),2) -> 0 | K39: =ROUND(AE38*(1+N('My Debts'!$D$15)/12),2) -> 0 | L39: =MIN(N('My Debts'!$E$6),B39) -> 0 | M39: =MIN(N('My Debts'!$E$7),C39) -> 0 | N39: =MIN(N('My Debts'!$E$8),D39) -> 0 | O39: =MIN(N('My Debts'!$E$9),E39) -> 0 | P39: =MIN(N('My Debts'!$E$10),F39) -> 0 | Q39: =MIN(N('My Debts'!$E$11),G39) -> 0 | R39: =MIN(N('My Debts'!$E$12),H39) -> 0 | S39: =MIN(N('My Debts'!$E$13),I39) -> 0 | T39: =MIN(N('My Debts'!$E$14),J39) -> 0 | U39: =MIN(N('My Debts'!$E$15),K39) -> 0 | V39: =ROUND(B39-L39-MIN(B39-L39,MAX(0,$AF39-SUMPRODUCT(--($B$4:$K$4<B$4),$B39:$K39-$L39:$U39))),2) -> 0 | W39: =ROUND(C39-M39-MIN(C39-M39,MAX(0,$AF39-SUMPRODUCT(--($B$4:$K$4<C$4),$B39:$K39-$L39:$U39))),2) -> 0 | X39: =ROUND(D39-N39-MIN(D39-N39,MAX(0,$AF39-SUMPRODUCT(--($B$4:$K$4<D$4),$B39:$K39-$L39:$U39))),2) -> 0 | Y39: =ROUND(E39-O39-MIN(E39-O39,MAX(0,$AF39-SUMPRODUCT(--($B$4:$K$4<E$4),$B39:$K39-$L39:$U39))),2) -> 0 | Z39: =ROUND(F39-P39-MIN(F39-P39,MAX(0,$AF39-SUMPRODUCT(--($B$4:$K$4<F$4),$B39:$K39-$L39:$U39))),2) -> 0 | AA39: =ROUND(G39-Q39-MIN(G39-Q39,MAX(0,$AF39-SUMPRODUCT(--($B$4:$K$4<G$4),$B39:$K39-$L39:$U39))),2) -> 0 | AB39: =ROUND(H39-R39-MIN(H39-R39,MAX(0,$AF39-SUMPRODUCT(--($B$4:$K$4<H$4),$B39:$K39-$L39:$U39))),2) -> 0 | AC39: =ROUND(I39-S39-MIN(I39-S39,MAX(0,$AF39-SUMPRODUCT(--($B$4:$K$4<I$4),$B39:$K39-$L39:$U39))),2) -> 0 | ... AE39: =ROUND(K39-U39-MIN(K39-U39,MAX(0,$AF39-SUMPRODUCT(--($B$4:$K$4<K$4),$B39:$K39-$L39:$U39))),2) -> 0 | AF39: =MAX(0,'Start Here'!$C$5-SUM($L39:$U39)) -> 1200 | AG39: =SUM(V39:AE39) -> 0 | AH39: =SUM(B39:K39)-AG38 -> 0
A40: =DATE(YEAR('Start Here'!$C$6),MONTH('Start Here'!$C$6)+33,1) -> 47300 | B40: =ROUND(V39*(1+N('My Debts'!$D$6)/12),2) -> 0 | C40: =ROUND(W39*(1+N('My Debts'!$D$7)/12),2) -> 0 | D40: =ROUND(X39*(1+N('My Debts'!$D$8)/12),2) -> 0 | E40: =ROUND(Y39*(1+N('My Debts'!$D$9)/12),2) -> 0 | F40: =ROUND(Z39*(1+N('My Debts'!$D$10)/12),2) -> 0 | G40: =ROUND(AA39*(1+N('My Debts'!$D$11)/12),2) -> 0 | H40: =ROUND(AB39*(1+N('My Debts'!$D$12)/12),2) -> 0 | I40: =ROUND(AC39*(1+N('My Debts'!$D$13)/12),2) -> 0 | J40: =ROUND(AD39*(1+N('My Debts'!$D$14)/12),2) -> 0 | K40: =ROUND(AE39*(1+N('My Debts'!$D$15)/12),2) -> 0 | L40: =MIN(N('My Debts'!$E$6),B40) -> 0 | M40: =MIN(N('My Debts'!$E$7),C40) -> 0 | N40: =MIN(N('My Debts'!$E$8),D40) -> 0 | O40: =MIN(N('My Debts'!$E$9),E40) -> 0 | P40: =MIN(N('My Debts'!$E$10),F40) -> 0 | Q40: =MIN(N('My Debts'!$E$11),G40) -> 0 | R40: =MIN(N('My Debts'!$E$12),H40) -> 0 | S40: =MIN(N('My Debts'!$E$13),I40) -> 0 | T40: =MIN(N('My Debts'!$E$14),J40) -> 0 | U40: =MIN(N('My Debts'!$E$15),K40) -> 0 | V40: =ROUND(B40-L40-MIN(B40-L40,MAX(0,$AF40-SUMPRODUCT(--($B$4:$K$4<B$4),$B40:$K40-$L40:$U40))),2) -> 0 | W40: =ROUND(C40-M40-MIN(C40-M40,MAX(0,$AF40-SUMPRODUCT(--($B$4:$K$4<C$4),$B40:$K40-$L40:$U40))),2) -> 0 | X40: =ROUND(D40-N40-MIN(D40-N40,MAX(0,$AF40-SUMPRODUCT(--($B$4:$K$4<D$4),$B40:$K40-$L40:$U40))),2) -> 0 | Y40: =ROUND(E40-O40-MIN(E40-O40,MAX(0,$AF40-SUMPRODUCT(--($B$4:$K$4<E$4),$B40:$K40-$L40:$U40))),2) -> 0 | Z40: =ROUND(F40-P40-MIN(F40-P40,MAX(0,$AF40-SUMPRODUCT(--($B$4:$K$4<F$4),$B40:$K40-$L40:$U40))),2) -> 0 | AA40: =ROUND(G40-Q40-MIN(G40-Q40,MAX(0,$AF40-SUMPRODUCT(--($B$4:$K$4<G$4),$B40:$K40-$L40:$U40))),2) -> 0 | AB40: =ROUND(H40-R40-MIN(H40-R40,MAX(0,$AF40-SUMPRODUCT(--($B$4:$K$4<H$4),$B40:$K40-$L40:$U40))),2) -> 0 | AC40: =ROUND(I40-S40-MIN(I40-S40,MAX(0,$AF40-SUMPRODUCT(--($B$4:$K$4<I$4),$B40:$K40-$L40:$U40))),2) -> 0 | ... AE40: =ROUND(K40-U40-MIN(K40-U40,MAX(0,$AF40-SUMPRODUCT(--($B$4:$K$4<K$4),$B40:$K40-$L40:$U40))),2) -> 0 | AF40: =MAX(0,'Start Here'!$C$5-SUM($L40:$U40)) -> 1200 | AG40: =SUM(V40:AE40) -> 0 | AH40: =SUM(B40:K40)-AG39 -> 0
A41: =DATE(YEAR('Start Here'!$C$6),MONTH('Start Here'!$C$6)+34,1) -> 47331 | B41: =ROUND(V40*(1+N('My Debts'!$D$6)/12),2) -> 0 | C41: =ROUND(W40*(1+N('My Debts'!$D$7)/12),2) -> 0 | D41: =ROUND(X40*(1+N('My Debts'!$D$8)/12),2) -> 0 | E41: =ROUND(Y40*(1+N('My Debts'!$D$9)/12),2) -> 0 | F41: =ROUND(Z40*(1+N('My Debts'!$D$10)/12),2) -> 0 | G41: =ROUND(AA40*(1+N('My Debts'!$D$11)/12),2) -> 0 | H41: =ROUND(AB40*(1+N('My Debts'!$D$12)/12),2) -> 0 | I41: =ROUND(AC40*(1+N('My Debts'!$D$13)/12),2) -> 0 | J41: =ROUND(AD40*(1+N('My Debts'!$D$14)/12),2) -> 0 | K41: =ROUND(AE40*(1+N('My Debts'!$D$15)/12),2) -> 0 | L41: =MIN(N('My Debts'!$E$6),B41) -> 0 | M41: =MIN(N('My Debts'!$E$7),C41) -> 0 | N41: =MIN(N('My Debts'!$E$8),D41) -> 0 | O41: =MIN(N('My Debts'!$E$9),E41) -> 0 | P41: =MIN(N('My Debts'!$E$10),F41) -> 0 | Q41: =MIN(N('My Debts'!$E$11),G41) -> 0 | R41: =MIN(N('My Debts'!$E$12),H41) -> 0 | S41: =MIN(N('My Debts'!$E$13),I41) -> 0 | T41: =MIN(N('My Debts'!$E$14),J41) -> 0 | U41: =MIN(N('My Debts'!$E$15),K41) -> 0 | V41: =ROUND(B41-L41-MIN(B41-L41,MAX(0,$AF41-SUMPRODUCT(--($B$4:$K$4<B$4),$B41:$K41-$L41:$U41))),2) -> 0 | W41: =ROUND(C41-M41-MIN(C41-M41,MAX(0,$AF41-SUMPRODUCT(--($B$4:$K$4<C$4),$B41:$K41-$L41:$U41))),2) -> 0 | X41: =ROUND(D41-N41-MIN(D41-N41,MAX(0,$AF41-SUMPRODUCT(--($B$4:$K$4<D$4),$B41:$K41-$L41:$U41))),2) -> 0 | Y41: =ROUND(E41-O41-MIN(E41-O41,MAX(0,$AF41-SUMPRODUCT(--($B$4:$K$4<E$4),$B41:$K41-$L41:$U41))),2) -> 0 | Z41: =ROUND(F41-P41-MIN(F41-P41,MAX(0,$AF41-SUMPRODUCT(--($B$4:$K$4<F$4),$B41:$K41-$L41:$U41))),2) -> 0 | AA41: =ROUND(G41-Q41-MIN(G41-Q41,MAX(0,$AF41-SUMPRODUCT(--($B$4:$K$4<G$4),$B41:$K41-$L41:$U41))),2) -> 0 | AB41: =ROUND(H41-R41-MIN(H41-R41,MAX(0,$AF41-SUMPRODUCT(--($B$4:$K$4<H$4),$B41:$K41-$L41:$U41))),2) -> 0 | AC41: =ROUND(I41-S41-MIN(I41-S41,MAX(0,$AF41-SUMPRODUCT(--($B$4:$K$4<I$4),$B41:$K41-$L41:$U41))),2) -> 0 | ... AE41: =ROUND(K41-U41-MIN(K41-U41,MAX(0,$AF41-SUMPRODUCT(--($B$4:$K$4<K$4),$B41:$K41-$L41:$U41))),2) -> 0 | AF41: =MAX(0,'Start Here'!$C$5-SUM($L41:$U41)) -> 1200 | AG41: =SUM(V41:AE41) -> 0 | AH41: =SUM(B41:K41)-AG40 -> 0
A42: =DATE(YEAR('Start Here'!$C$6),MONTH('Start Here'!$C$6)+35,1) -> 47362 | B42: =ROUND(V41*(1+N('My Debts'!$D$6)/12),2) -> 0 | C42: =ROUND(W41*(1+N('My Debts'!$D$7)/12),2) -> 0 | D42: =ROUND(X41*(1+N('My Debts'!$D$8)/12),2) -> 0 | E42: =ROUND(Y41*(1+N('My Debts'!$D$9)/12),2) -> 0 | F42: =ROUND(Z41*(1+N('My Debts'!$D$10)/12),2) -> 0 | G42: =ROUND(AA41*(1+N('My Debts'!$D$11)/12),2) -> 0 | H42: =ROUND(AB41*(1+N('My Debts'!$D$12)/12),2) -> 0 | I42: =ROUND(AC41*(1+N('My Debts'!$D$13)/12),2) -> 0 | J42: =ROUND(AD41*(1+N('My Debts'!$D$14)/12),2) -> 0 | K42: =ROUND(AE41*(1+N('My Debts'!$D$15)/12),2) -> 0 | L42: =MIN(N('My Debts'!$E$6),B42) -> 0 | M42: =MIN(N('My Debts'!$E$7),C42) -> 0 | N42: =MIN(N('My Debts'!$E$8),D42) -> 0 | O42: =MIN(N('My Debts'!$E$9),E42) -> 0 | P42: =MIN(N('My Debts'!$E$10),F42) -> 0 | Q42: =MIN(N('My Debts'!$E$11),G42) -> 0 | R42: =MIN(N('My Debts'!$E$12),H42) -> 0 | S42: =MIN(N('My Debts'!$E$13),I42) -> 0 | T42: =MIN(N('My Debts'!$E$14),J42) -> 0 | U42: =MIN(N('My Debts'!$E$15),K42) -> 0 | V42: =ROUND(B42-L42-MIN(B42-L42,MAX(0,$AF42-SUMPRODUCT(--($B$4:$K$4<B$4),$B42:$K42-$L42:$U42))),2) -> 0 | W42: =ROUND(C42-M42-MIN(C42-M42,MAX(0,$AF42-SUMPRODUCT(--($B$4:$K$4<C$4),$B42:$K42-$L42:$U42))),2) -> 0 | X42: =ROUND(D42-N42-MIN(D42-N42,MAX(0,$AF42-SUMPRODUCT(--($B$4:$K$4<D$4),$B42:$K42-$L42:$U42))),2) -> 0 | Y42: =ROUND(E42-O42-MIN(E42-O42,MAX(0,$AF42-SUMPRODUCT(--($B$4:$K$4<E$4),$B42:$K42-$L42:$U42))),2) -> 0 | Z42: =ROUND(F42-P42-MIN(F42-P42,MAX(0,$AF42-SUMPRODUCT(--($B$4:$K$4<F$4),$B42:$K42-$L42:$U42))),2) -> 0 | AA42: =ROUND(G42-Q42-MIN(G42-Q42,MAX(0,$AF42-SUMPRODUCT(--($B$4:$K$4<G$4),$B42:$K42-$L42:$U42))),2) -> 0 | AB42: =ROUND(H42-R42-MIN(H42-R42,MAX(0,$AF42-SUMPRODUCT(--($B$4:$K$4<H$4),$B42:$K42-$L42:$U42))),2) -> 0 | AC42: =ROUND(I42-S42-MIN(I42-S42,MAX(0,$AF42-SUMPRODUCT(--($B$4:$K$4<I$4),$B42:$K42-$L42:$U42))),2) -> 0 | ... AE42: =ROUND(K42-U42-MIN(K42-U42,MAX(0,$AF42-SUMPRODUCT(--($B$4:$K$4<K$4),$B42:$K42-$L42:$U42))),2) -> 0 | AF42: =MAX(0,'Start Here'!$C$5-SUM($L42:$U42)) -> 1200 | AG42: =SUM(V42:AE42) -> 0 | AH42: =SUM(B42:K42)-AG41 -> 0
A43: =DATE(YEAR('Start Here'!$C$6),MONTH('Start Here'!$C$6)+36,1) -> 47392 | B43: =ROUND(V42*(1+N('My Debts'!$D$6)/12),2) -> 0 | C43: =ROUND(W42*(1+N('My Debts'!$D$7)/12),2) -> 0 | D43: =ROUND(X42*(1+N('My Debts'!$D$8)/12),2) -> 0 | E43: =ROUND(Y42*(1+N('My Debts'!$D$9)/12),2) -> 0 | F43: =ROUND(Z42*(1+N('My Debts'!$D$10)/12),2) -> 0 | G43: =ROUND(AA42*(1+N('My Debts'!$D$11)/12),2) -> 0 | H43: =ROUND(AB42*(1+N('My Debts'!$D$12)/12),2) -> 0 | I43: =ROUND(AC42*(1+N('My Debts'!$D$13)/12),2) -> 0 | J43: =ROUND(AD42*(1+N('My Debts'!$D$14)/12),2) -> 0 | K43: =ROUND(AE42*(1+N('My Debts'!$D$15)/12),2) -> 0 | L43: =MIN(N('My Debts'!$E$6),B43) -> 0 | M43: =MIN(N('My Debts'!$E$7),C43) -> 0 | N43: =MIN(N('My Debts'!$E$8),D43) -> 0 | O43: =MIN(N('My Debts'!$E$9),E43) -> 0 | P43: =MIN(N('My Debts'!$E$10),F43) -> 0 | Q43: =MIN(N('My Debts'!$E$11),G43) -> 0 | R43: =MIN(N('My Debts'!$E$12),H43) -> 0 | S43: =MIN(N('My Debts'!$E$13),I43) -> 0 | T43: =MIN(N('My Debts'!$E$14),J43) -> 0 | U43: =MIN(N('My Debts'!$E$15),K43) -> 0 | V43: =ROUND(B43-L43-MIN(B43-L43,MAX(0,$AF43-SUMPRODUCT(--($B$4:$K$4<B$4),$B43:$K43-$L43:$U43))),2) -> 0 | W43: =ROUND(C43-M43-MIN(C43-M43,MAX(0,$AF43-SUMPRODUCT(--($B$4:$K$4<C$4),$B43:$K43-$L43:$U43))),2) -> 0 | X43: =ROUND(D43-N43-MIN(D43-N43,MAX(0,$AF43-SUMPRODUCT(--($B$4:$K$4<D$4),$B43:$K43-$L43:$U43))),2) -> 0 | Y43: =ROUND(E43-O43-MIN(E43-O43,MAX(0,$AF43-SUMPRODUCT(--($B$4:$K$4<E$4),$B43:$K43-$L43:$U43))),2) -> 0 | Z43: =ROUND(F43-P43-MIN(F43-P43,MAX(0,$AF43-SUMPRODUCT(--($B$4:$K$4<F$4),$B43:$K43-$L43:$U43))),2) -> 0 | AA43: =ROUND(G43-Q43-MIN(G43-Q43,MAX(0,$AF43-SUMPRODUCT(--($B$4:$K$4<G$4),$B43:$K43-$L43:$U43))),2) -> 0 | AB43: =ROUND(H43-R43-MIN(H43-R43,MAX(0,$AF43-SUMPRODUCT(--($B$4:$K$4<H$4),$B43:$K43-$L43:$U43))),2) -> 0 | AC43: =ROUND(I43-S43-MIN(I43-S43,MAX(0,$AF43-SUMPRODUCT(--($B$4:$K$4<I$4),$B43:$K43-$L43:$U43))),2) -> 0 | ... AE43: =ROUND(K43-U43-MIN(K43-U43,MAX(0,$AF43-SUMPRODUCT(--($B$4:$K$4<K$4),$B43:$K43-$L43:$U43))),2) -> 0 | AF43: =MAX(0,'Start Here'!$C$5-SUM($L43:$U43)) -> 1200 | AG43: =SUM(V43:AE43) -> 0 | AH43: =SUM(B43:K43)-AG42 -> 0
A44: =DATE(YEAR('Start Here'!$C$6),MONTH('Start Here'!$C$6)+37,1) -> 47423 | B44: =ROUND(V43*(1+N('My Debts'!$D$6)/12),2) -> 0 | C44: =ROUND(W43*(1+N('My Debts'!$D$7)/12),2) -> 0 | D44: =ROUND(X43*(1+N('My Debts'!$D$8)/12),2) -> 0 | E44: =ROUND(Y43*(1+N('My Debts'!$D$9)/12),2) -> 0 | F44: =ROUND(Z43*(1+N('My Debts'!$D$10)/12),2) -> 0 | G44: =ROUND(AA43*(1+N('My Debts'!$D$11)/12),2) -> 0 | H44: =ROUND(AB43*(1+N('My Debts'!$D$12)/12),2) -> 0 | I44: =ROUND(AC43*(1+N('My Debts'!$D$13)/12),2) -> 0 | J44: =ROUND(AD43*(1+N('My Debts'!$D$14)/12),2) -> 0 | K44: =ROUND(AE43*(1+N('My Debts'!$D$15)/12),2) -> 0 | L44: =MIN(N('My Debts'!$E$6),B44) -> 0 | M44: =MIN(N('My Debts'!$E$7),C44) -> 0 | N44: =MIN(N('My Debts'!$E$8),D44) -> 0 | O44: =MIN(N('My Debts'!$E$9),E44) -> 0 | P44: =MIN(N('My Debts'!$E$10),F44) -> 0 | Q44: =MIN(N('My Debts'!$E$11),G44) -> 0 | R44: =MIN(N('My Debts'!$E$12),H44) -> 0 | S44: =MIN(N('My Debts'!$E$13),I44) -> 0 | T44: =MIN(N('My Debts'!$E$14),J44) -> 0 | U44: =MIN(N('My Debts'!$E$15),K44) -> 0 | V44: =ROUND(B44-L44-MIN(B44-L44,MAX(0,$AF44-SUMPRODUCT(--($B$4:$K$4<B$4),$B44:$K44-$L44:$U44))),2) -> 0 | W44: =ROUND(C44-M44-MIN(C44-M44,MAX(0,$AF44-SUMPRODUCT(--($B$4:$K$4<C$4),$B44:$K44-$L44:$U44))),2) -> 0 | X44: =ROUND(D44-N44-MIN(D44-N44,MAX(0,$AF44-SUMPRODUCT(--($B$4:$K$4<D$4),$B44:$K44-$L44:$U44))),2) -> 0 | Y44: =ROUND(E44-O44-MIN(E44-O44,MAX(0,$AF44-SUMPRODUCT(--($B$4:$K$4<E$4),$B44:$K44-$L44:$U44))),2) -> 0 | Z44: =ROUND(F44-P44-MIN(F44-P44,MAX(0,$AF44-SUMPRODUCT(--($B$4:$K$4<F$4),$B44:$K44-$L44:$U44))),2) -> 0 | AA44: =ROUND(G44-Q44-MIN(G44-Q44,MAX(0,$AF44-SUMPRODUCT(--($B$4:$K$4<G$4),$B44:$K44-$L44:$U44))),2) -> 0 | AB44: =ROUND(H44-R44-MIN(H44-R44,MAX(0,$AF44-SUMPRODUCT(--($B$4:$K$4<H$4),$B44:$K44-$L44:$U44))),2) -> 0 | AC44: =ROUND(I44-S44-MIN(I44-S44,MAX(0,$AF44-SUMPRODUCT(--($B$4:$K$4<I$4),$B44:$K44-$L44:$U44))),2) -> 0 | ... AE44: =ROUND(K44-U44-MIN(K44-U44,MAX(0,$AF44-SUMPRODUCT(--($B$4:$K$4<K$4),$B44:$K44-$L44:$U44))),2) -> 0 | AF44: =MAX(0,'Start Here'!$C$5-SUM($L44:$U44)) -> 1200 | AG44: =SUM(V44:AE44) -> 0 | AH44: =SUM(B44:K44)-AG43 -> 0
A45: =DATE(YEAR('Start Here'!$C$6),MONTH('Start Here'!$C$6)+38,1) -> 47453 | B45: =ROUND(V44*(1+N('My Debts'!$D$6)/12),2) -> 0 | C45: =ROUND(W44*(1+N('My Debts'!$D$7)/12),2) -> 0 | D45: =ROUND(X44*(1+N('My Debts'!$D$8)/12),2) -> 0 | E45: =ROUND(Y44*(1+N('My Debts'!$D$9)/12),2) -> 0 | F45: =ROUND(Z44*(1+N('My Debts'!$D$10)/12),2) -> 0 | G45: =ROUND(AA44*(1+N('My Debts'!$D$11)/12),2) -> 0 | H45: =ROUND(AB44*(1+N('My Debts'!$D$12)/12),2) -> 0 | I45: =ROUND(AC44*(1+N('My Debts'!$D$13)/12),2) -> 0 | J45: =ROUND(AD44*(1+N('My Debts'!$D$14)/12),2) -> 0 | K45: =ROUND(AE44*(1+N('My Debts'!$D$15)/12),2) -> 0 | L45: =MIN(N('My Debts'!$E$6),B45) -> 0 | M45: =MIN(N('My Debts'!$E$7),C45) -> 0 | N45: =MIN(N('My Debts'!$E$8),D45) -> 0 | O45: =MIN(N('My Debts'!$E$9),E45) -> 0 | P45: =MIN(N('My Debts'!$E$10),F45) -> 0 | Q45: =MIN(N('My Debts'!$E$11),G45) -> 0 | R45: =MIN(N('My Debts'!$E$12),H45) -> 0 | S45: =MIN(N('My Debts'!$E$13),I45) -> 0 | T45: =MIN(N('My Debts'!$E$14),J45) -> 0 | U45: =MIN(N('My Debts'!$E$15),K45) -> 0 | V45: =ROUND(B45-L45-MIN(B45-L45,MAX(0,$AF45-SUMPRODUCT(--($B$4:$K$4<B$4),$B45:$K45-$L45:$U45))),2) -> 0 | W45: =ROUND(C45-M45-MIN(C45-M45,MAX(0,$AF45-SUMPRODUCT(--($B$4:$K$4<C$4),$B45:$K45-$L45:$U45))),2) -> 0 | X45: =ROUND(D45-N45-MIN(D45-N45,MAX(0,$AF45-SUMPRODUCT(--($B$4:$K$4<D$4),$B45:$K45-$L45:$U45))),2) -> 0 | Y45: =ROUND(E45-O45-MIN(E45-O45,MAX(0,$AF45-SUMPRODUCT(--($B$4:$K$4<E$4),$B45:$K45-$L45:$U45))),2) -> 0 | Z45: =ROUND(F45-P45-MIN(F45-P45,MAX(0,$AF45-SUMPRODUCT(--($B$4:$K$4<F$4),$B45:$K45-$L45:$U45))),2) -> 0 | AA45: =ROUND(G45-Q45-MIN(G45-Q45,MAX(0,$AF45-SUMPRODUCT(--($B$4:$K$4<G$4),$B45:$K45-$L45:$U45))),2) -> 0 | AB45: =ROUND(H45-R45-MIN(H45-R45,MAX(0,$AF45-SUMPRODUCT(--($B$4:$K$4<H$4),$B45:$K45-$L45:$U45))),2) -> 0 | AC45: =ROUND(I45-S45-MIN(I45-S45,MAX(0,$AF45-SUMPRODUCT(--($B$4:$K$4<I$4),$B45:$K45-$L45:$U45))),2) -> 0 | ... AE45: =ROUND(K45-U45-MIN(K45-U45,MAX(0,$AF45-SUMPRODUCT(--($B$4:$K$4<K$4),$B45:$K45-$L45:$U45))),2) -> 0 | AF45: =MAX(0,'Start Here'!$C$5-SUM($L45:$U45)) -> 1200 | AG45: =SUM(V45:AE45) -> 0 | AH45: =SUM(B45:K45)-AG44 -> 0
A46: =DATE(YEAR('Start Here'!$C$6),MONTH('Start Here'!$C$6)+39,1) -> 47484 | B46: =ROUND(V45*(1+N('My Debts'!$D$6)/12),2) -> 0 | C46: =ROUND(W45*(1+N('My Debts'!$D$7)/12),2) -> 0 | D46: =ROUND(X45*(1+N('My Debts'!$D$8)/12),2) -> 0 | E46: =ROUND(Y45*(1+N('My Debts'!$D$9)/12),2) -> 0 | F46: =ROUND(Z45*(1+N('My Debts'!$D$10)/12),2) -> 0 | G46: =ROUND(AA45*(1+N('My Debts'!$D$11)/12),2) -> 0 | H46: =ROUND(AB45*(1+N('My Debts'!$D$12)/12),2) -> 0 | I46: =ROUND(AC45*(1+N('My Debts'!$D$13)/12),2) -> 0 | J46: =ROUND(AD45*(1+N('My Debts'!$D$14)/12),2) -> 0 | K46: =ROUND(AE45*(1+N('My Debts'!$D$15)/12),2) -> 0 | L46: =MIN(N('My Debts'!$E$6),B46) -> 0 | M46: =MIN(N('My Debts'!$E$7),C46) -> 0 | N46: =MIN(N('My Debts'!$E$8),D46) -> 0 | O46: =MIN(N('My Debts'!$E$9),E46) -> 0 | P46: =MIN(N('My Debts'!$E$10),F46) -> 0 | Q46: =MIN(N('My Debts'!$E$11),G46) -> 0 | R46: =MIN(N('My Debts'!$E$12),H46) -> 0 | S46: =MIN(N('My Debts'!$E$13),I46) -> 0 | T46: =MIN(N('My Debts'!$E$14),J46) -> 0 | U46: =MIN(N('My Debts'!$E$15),K46) -> 0 | V46: =ROUND(B46-L46-MIN(B46-L46,MAX(0,$AF46-SUMPRODUCT(--($B$4:$K$4<B$4),$B46:$K46-$L46:$U46))),2) -> 0 | W46: =ROUND(C46-M46-MIN(C46-M46,MAX(0,$AF46-SUMPRODUCT(--($B$4:$K$4<C$4),$B46:$K46-$L46:$U46))),2) -> 0 | X46: =ROUND(D46-N46-MIN(D46-N46,MAX(0,$AF46-SUMPRODUCT(--($B$4:$K$4<D$4),$B46:$K46-$L46:$U46))),2) -> 0 | Y46: =ROUND(E46-O46-MIN(E46-O46,MAX(0,$AF46-SUMPRODUCT(--($B$4:$K$4<E$4),$B46:$K46-$L46:$U46))),2) -> 0 | Z46: =ROUND(F46-P46-MIN(F46-P46,MAX(0,$AF46-SUMPRODUCT(--($B$4:$K$4<F$4),$B46:$K46-$L46:$U46))),2) -> 0 | AA46: =ROUND(G46-Q46-MIN(G46-Q46,MAX(0,$AF46-SUMPRODUCT(--($B$4:$K$4<G$4),$B46:$K46-$L46:$U46))),2) -> 0 | AB46: =ROUND(H46-R46-MIN(H46-R46,MAX(0,$AF46-SUMPRODUCT(--($B$4:$K$4<H$4),$B46:$K46-$L46:$U46))),2) -> 0 | AC46: =ROUND(I46-S46-MIN(I46-S46,MAX(0,$AF46-SUMPRODUCT(--($B$4:$K$4<I$4),$B46:$K46-$L46:$U46))),2) -> 0 | ... AE46: =ROUND(K46-U46-MIN(K46-U46,MAX(0,$AF46-SUMPRODUCT(--($B$4:$K$4<K$4),$B46:$K46-$L46:$U46))),2) -> 0 | AF46: =MAX(0,'Start Here'!$C$5-SUM($L46:$U46)) -> 1200 | AG46: =SUM(V46:AE46) -> 0 | AH46: =SUM(B46:K46)-AG45 -> 0
A47: =DATE(YEAR('Start Here'!$C$6),MONTH('Start Here'!$C$6)+40,1) -> 47515 | B47: =ROUND(V46*(1+N('My Debts'!$D$6)/12),2) -> 0 | C47: =ROUND(W46*(1+N('My Debts'!$D$7)/12),2) -> 0 | D47: =ROUND(X46*(1+N('My Debts'!$D$8)/12),2) -> 0 | E47: =ROUND(Y46*(1+N('My Debts'!$D$9)/12),2) -> 0 | F47: =ROUND(Z46*(1+N('My Debts'!$D$10)/12),2) -> 0 | G47: =ROUND(AA46*(1+N('My Debts'!$D$11)/12),2) -> 0 | H47: =ROUND(AB46*(1+N('My Debts'!$D$12)/12),2) -> 0 | I47: =ROUND(AC46*(1+N('My Debts'!$D$13)/12),2) -> 0 | J47: =ROUND(AD46*(1+N('My Debts'!$D$14)/12),2) -> 0 | K47: =ROUND(AE46*(1+N('My Debts'!$D$15)/12),2) -> 0 | L47: =MIN(N('My Debts'!$E$6),B47) -> 0 | M47: =MIN(N('My Debts'!$E$7),C47) -> 0 | N47: =MIN(N('My Debts'!$E$8),D47) -> 0 | O47: =MIN(N('My Debts'!$E$9),E47) -> 0 | P47: =MIN(N('My Debts'!$E$10),F47) -> 0 | Q47: =MIN(N('My Debts'!$E$11),G47) -> 0 | R47: =MIN(N('My Debts'!$E$12),H47) -> 0 | S47: =MIN(N('My Debts'!$E$13),I47) -> 0 | T47: =MIN(N('My Debts'!$E$14),J47) -> 0 | U47: =MIN(N('My Debts'!$E$15),K47) -> 0 | V47: =ROUND(B47-L47-MIN(B47-L47,MAX(0,$AF47-SUMPRODUCT(--($B$4:$K$4<B$4),$B47:$K47-$L47:$U47))),2) -> 0 | W47: =ROUND(C47-M47-MIN(C47-M47,MAX(0,$AF47-SUMPRODUCT(--($B$4:$K$4<C$4),$B47:$K47-$L47:$U47))),2) -> 0 | X47: =ROUND(D47-N47-MIN(D47-N47,MAX(0,$AF47-SUMPRODUCT(--($B$4:$K$4<D$4),$B47:$K47-$L47:$U47))),2) -> 0 | Y47: =ROUND(E47-O47-MIN(E47-O47,MAX(0,$AF47-SUMPRODUCT(--($B$4:$K$4<E$4),$B47:$K47-$L47:$U47))),2) -> 0 | Z47: =ROUND(F47-P47-MIN(F47-P47,MAX(0,$AF47-SUMPRODUCT(--($B$4:$K$4<F$4),$B47:$K47-$L47:$U47))),2) -> 0 | AA47: =ROUND(G47-Q47-MIN(G47-Q47,MAX(0,$AF47-SUMPRODUCT(--($B$4:$K$4<G$4),$B47:$K47-$L47:$U47))),2) -> 0 | AB47: =ROUND(H47-R47-MIN(H47-R47,MAX(0,$AF47-SUMPRODUCT(--($B$4:$K$4<H$4),$B47:$K47-$L47:$U47))),2) -> 0 | AC47: =ROUND(I47-S47-MIN(I47-S47,MAX(0,$AF47-SUMPRODUCT(--($B$4:$K$4<I$4),$B47:$K47-$L47:$U47))),2) -> 0 | ... AE47: =ROUND(K47-U47-MIN(K47-U47,MAX(0,$AF47-SUMPRODUCT(--($B$4:$K$4<K$4),$B47:$K47-$L47:$U47))),2) -> 0 | AF47: =MAX(0,'Start Here'!$C$5-SUM($L47:$U47)) -> 1200 | AG47: =SUM(V47:AE47) -> 0 | AH47: =SUM(B47:K47)-AG46 -> 0
A48: =DATE(YEAR('Start Here'!$C$6),MONTH('Start Here'!$C$6)+41,1) -> 47543 | B48: =ROUND(V47*(1+N('My Debts'!$D$6)/12),2) -> 0 | C48: =ROUND(W47*(1+N('My Debts'!$D$7)/12),2) -> 0 | D48: =ROUND(X47*(1+N('My Debts'!$D$8)/12),2) -> 0 | E48: =ROUND(Y47*(1+N('My Debts'!$D$9)/12),2) -> 0 | F48: =ROUND(Z47*(1+N('My Debts'!$D$10)/12),2) -> 0 | G48: =ROUND(AA47*(1+N('My Debts'!$D$11)/12),2) -> 0 | H48: =ROUND(AB47*(1+N('My Debts'!$D$12)/12),2) -> 0 | I48: =ROUND(AC47*(1+N('My Debts'!$D$13)/12),2) -> 0 | J48: =ROUND(AD47*(1+N('My Debts'!$D$14)/12),2) -> 0 | K48: =ROUND(AE47*(1+N('My Debts'!$D$15)/12),2) -> 0 | L48: =MIN(N('My Debts'!$E$6),B48) -> 0 | M48: =MIN(N('My Debts'!$E$7),C48) -> 0 | N48: =MIN(N('My Debts'!$E$8),D48) -> 0 | O48: =MIN(N('My Debts'!$E$9),E48) -> 0 | P48: =MIN(N('My Debts'!$E$10),F48) -> 0 | Q48: =MIN(N('My Debts'!$E$11),G48) -> 0 | R48: =MIN(N('My Debts'!$E$12),H48) -> 0 | S48: =MIN(N('My Debts'!$E$13),I48) -> 0 | T48: =MIN(N('My Debts'!$E$14),J48) -> 0 | U48: =MIN(N('My Debts'!$E$15),K48) -> 0 | V48: =ROUND(B48-L48-MIN(B48-L48,MAX(0,$AF48-SUMPRODUCT(--($B$4:$K$4<B$4),$B48:$K48-$L48:$U48))),2) -> 0 | W48: =ROUND(C48-M48-MIN(C48-M48,MAX(0,$AF48-SUMPRODUCT(--($B$4:$K$4<C$4),$B48:$K48-$L48:$U48))),2) -> 0 | X48: =ROUND(D48-N48-MIN(D48-N48,MAX(0,$AF48-SUMPRODUCT(--($B$4:$K$4<D$4),$B48:$K48-$L48:$U48))),2) -> 0 | Y48: =ROUND(E48-O48-MIN(E48-O48,MAX(0,$AF48-SUMPRODUCT(--($B$4:$K$4<E$4),$B48:$K48-$L48:$U48))),2) -> 0 | Z48: =ROUND(F48-P48-MIN(F48-P48,MAX(0,$AF48-SUMPRODUCT(--($B$4:$K$4<F$4),$B48:$K48-$L48:$U48))),2) -> 0 | AA48: =ROUND(G48-Q48-MIN(G48-Q48,MAX(0,$AF48-SUMPRODUCT(--($B$4:$K$4<G$4),$B48:$K48-$L48:$U48))),2) -> 0 | AB48: =ROUND(H48-R48-MIN(H48-R48,MAX(0,$AF48-SUMPRODUCT(--($B$4:$K$4<H$4),$B48:$K48-$L48:$U48))),2) -> 0 | AC48: =ROUND(I48-S48-MIN(I48-S48,MAX(0,$AF48-SUMPRODUCT(--($B$4:$K$4<I$4),$B48:$K48-$L48:$U48))),2) -> 0 | ... AE48: =ROUND(K48-U48-MIN(K48-U48,MAX(0,$AF48-SUMPRODUCT(--($B$4:$K$4<K$4),$B48:$K48-$L48:$U48))),2) -> 0 | AF48: =MAX(0,'Start Here'!$C$5-SUM($L48:$U48)) -> 1200 | AG48: =SUM(V48:AE48) -> 0 | AH48: =SUM(B48:K48)-AG47 -> 0
A49: =DATE(YEAR('Start Here'!$C$6),MONTH('Start Here'!$C$6)+42,1) -> 47574 | B49: =ROUND(V48*(1+N('My Debts'!$D$6)/12),2) -> 0 | C49: =ROUND(W48*(1+N('My Debts'!$D$7)/12),2) -> 0 | D49: =ROUND(X48*(1+N('My Debts'!$D$8)/12),2) -> 0 | E49: =ROUND(Y48*(1+N('My Debts'!$D$9)/12),2) -> 0 | F49: =ROUND(Z48*(1+N('My Debts'!$D$10)/12),2) -> 0 | G49: =ROUND(AA48*(1+N('My Debts'!$D$11)/12),2) -> 0 | H49: =ROUND(AB48*(1+N('My Debts'!$D$12)/12),2) -> 0 | I49: =ROUND(AC48*(1+N('My Debts'!$D$13)/12),2) -> 0 | J49: =ROUND(AD48*(1+N('My Debts'!$D$14)/12),2) -> 0 | K49: =ROUND(AE48*(1+N('My Debts'!$D$15)/12),2) -> 0 | L49: =MIN(N('My Debts'!$E$6),B49) -> 0 | M49: =MIN(N('My Debts'!$E$7),C49) -> 0 | N49: =MIN(N('My Debts'!$E$8),D49) -> 0 | O49: =MIN(N('My Debts'!$E$9),E49) -> 0 | P49: =MIN(N('My Debts'!$E$10),F49) -> 0 | Q49: =MIN(N('My Debts'!$E$11),G49) -> 0 | R49: =MIN(N('My Debts'!$E$12),H49) -> 0 | S49: =MIN(N('My Debts'!$E$13),I49) -> 0 | T49: =MIN(N('My Debts'!$E$14),J49) -> 0 | U49: =MIN(N('My Debts'!$E$15),K49) -> 0 | V49: =ROUND(B49-L49-MIN(B49-L49,MAX(0,$AF49-SUMPRODUCT(--($B$4:$K$4<B$4),$B49:$K49-$L49:$U49))),2) -> 0 | W49: =ROUND(C49-M49-MIN(C49-M49,MAX(0,$AF49-SUMPRODUCT(--($B$4:$K$4<C$4),$B49:$K49-$L49:$U49))),2) -> 0 | X49: =ROUND(D49-N49-MIN(D49-N49,MAX(0,$AF49-SUMPRODUCT(--($B$4:$K$4<D$4),$B49:$K49-$L49:$U49))),2) -> 0 | Y49: =ROUND(E49-O49-MIN(E49-O49,MAX(0,$AF49-SUMPRODUCT(--($B$4:$K$4<E$4),$B49:$K49-$L49:$U49))),2) -> 0 | Z49: =ROUND(F49-P49-MIN(F49-P49,MAX(0,$AF49-SUMPRODUCT(--($B$4:$K$4<F$4),$B49:$K49-$L49:$U49))),2) -> 0 | AA49: =ROUND(G49-Q49-MIN(G49-Q49,MAX(0,$AF49-SUMPRODUCT(--($B$4:$K$4<G$4),$B49:$K49-$L49:$U49))),2) -> 0 | AB49: =ROUND(H49-R49-MIN(H49-R49,MAX(0,$AF49-SUMPRODUCT(--($B$4:$K$4<H$4),$B49:$K49-$L49:$U49))),2) -> 0 | AC49: =ROUND(I49-S49-MIN(I49-S49,MAX(0,$AF49-SUMPRODUCT(--($B$4:$K$4<I$4),$B49:$K49-$L49:$U49))),2) -> 0 | ... AE49: =ROUND(K49-U49-MIN(K49-U49,MAX(0,$AF49-SUMPRODUCT(--($B$4:$K$4<K$4),$B49:$K49-$L49:$U49))),2) -> 0 | AF49: =MAX(0,'Start Here'!$C$5-SUM($L49:$U49)) -> 1200 | AG49: =SUM(V49:AE49) -> 0 | AH49: =SUM(B49:K49)-AG48 -> 0
A50: =DATE(YEAR('Start Here'!$C$6),MONTH('Start Here'!$C$6)+43,1) -> 47604 | B50: =ROUND(V49*(1+N('My Debts'!$D$6)/12),2) -> 0 | C50: =ROUND(W49*(1+N('My Debts'!$D$7)/12),2) -> 0 | D50: =ROUND(X49*(1+N('My Debts'!$D$8)/12),2) -> 0 | E50: =ROUND(Y49*(1+N('My Debts'!$D$9)/12),2) -> 0 | F50: =ROUND(Z49*(1+N('My Debts'!$D$10)/12),2) -> 0 | G50: =ROUND(AA49*(1+N('My Debts'!$D$11)/12),2) -> 0 | H50: =ROUND(AB49*(1+N('My Debts'!$D$12)/12),2) -> 0 | I50: =ROUND(AC49*(1+N('My Debts'!$D$13)/12),2) -> 0 | J50: =ROUND(AD49*(1+N('My Debts'!$D$14)/12),2) -> 0 | K50: =ROUND(AE49*(1+N('My Debts'!$D$15)/12),2) -> 0 | L50: =MIN(N('My Debts'!$E$6),B50) -> 0 | M50: =MIN(N('My Debts'!$E$7),C50) -> 0 | N50: =MIN(N('My Debts'!$E$8),D50) -> 0 | O50: =MIN(N('My Debts'!$E$9),E50) -> 0 | P50: =MIN(N('My Debts'!$E$10),F50) -> 0 | Q50: =MIN(N('My Debts'!$E$11),G50) -> 0 | R50: =MIN(N('My Debts'!$E$12),H50) -> 0 | S50: =MIN(N('My Debts'!$E$13),I50) -> 0 | T50: =MIN(N('My Debts'!$E$14),J50) -> 0 | U50: =MIN(N('My Debts'!$E$15),K50) -> 0 | V50: =ROUND(B50-L50-MIN(B50-L50,MAX(0,$AF50-SUMPRODUCT(--($B$4:$K$4<B$4),$B50:$K50-$L50:$U50))),2) -> 0 | W50: =ROUND(C50-M50-MIN(C50-M50,MAX(0,$AF50-SUMPRODUCT(--($B$4:$K$4<C$4),$B50:$K50-$L50:$U50))),2) -> 0 | X50: =ROUND(D50-N50-MIN(D50-N50,MAX(0,$AF50-SUMPRODUCT(--($B$4:$K$4<D$4),$B50:$K50-$L50:$U50))),2) -> 0 | Y50: =ROUND(E50-O50-MIN(E50-O50,MAX(0,$AF50-SUMPRODUCT(--($B$4:$K$4<E$4),$B50:$K50-$L50:$U50))),2) -> 0 | Z50: =ROUND(F50-P50-MIN(F50-P50,MAX(0,$AF50-SUMPRODUCT(--($B$4:$K$4<F$4),$B50:$K50-$L50:$U50))),2) -> 0 | AA50: =ROUND(G50-Q50-MIN(G50-Q50,MAX(0,$AF50-SUMPRODUCT(--($B$4:$K$4<G$4),$B50:$K50-$L50:$U50))),2) -> 0 | AB50: =ROUND(H50-R50-MIN(H50-R50,MAX(0,$AF50-SUMPRODUCT(--($B$4:$K$4<H$4),$B50:$K50-$L50:$U50))),2) -> 0 | AC50: =ROUND(I50-S50-MIN(I50-S50,MAX(0,$AF50-SUMPRODUCT(--($B$4:$K$4<I$4),$B50:$K50-$L50:$U50))),2) -> 0 | ... AE50: =ROUND(K50-U50-MIN(K50-U50,MAX(0,$AF50-SUMPRODUCT(--($B$4:$K$4<K$4),$B50:$K50-$L50:$U50))),2) -> 0 | AF50: =MAX(0,'Start Here'!$C$5-SUM($L50:$U50)) -> 1200 | AG50: =SUM(V50:AE50) -> 0 | AH50: =SUM(B50:K50)-AG49 -> 0
A51: =DATE(YEAR('Start Here'!$C$6),MONTH('Start Here'!$C$6)+44,1) -> 47635 | B51: =ROUND(V50*(1+N('My Debts'!$D$6)/12),2) -> 0 | C51: =ROUND(W50*(1+N('My Debts'!$D$7)/12),2) -> 0 | D51: =ROUND(X50*(1+N('My Debts'!$D$8)/12),2) -> 0 | E51: =ROUND(Y50*(1+N('My Debts'!$D$9)/12),2) -> 0 | F51: =ROUND(Z50*(1+N('My Debts'!$D$10)/12),2) -> 0 | G51: =ROUND(AA50*(1+N('My Debts'!$D$11)/12),2) -> 0 | H51: =ROUND(AB50*(1+N('My Debts'!$D$12)/12),2) -> 0 | I51: =ROUND(AC50*(1+N('My Debts'!$D$13)/12),2) -> 0 | J51: =ROUND(AD50*(1+N('My Debts'!$D$14)/12),2) -> 0 | K51: =ROUND(AE50*(1+N('My Debts'!$D$15)/12),2) -> 0 | L51: =MIN(N('My Debts'!$E$6),B51) -> 0 | M51: =MIN(N('My Debts'!$E$7),C51) -> 0 | N51: =MIN(N('My Debts'!$E$8),D51) -> 0 | O51: =MIN(N('My Debts'!$E$9),E51) -> 0 | P51: =MIN(N('My Debts'!$E$10),F51) -> 0 | Q51: =MIN(N('My Debts'!$E$11),G51) -> 0 | R51: =MIN(N('My Debts'!$E$12),H51) -> 0 | S51: =MIN(N('My Debts'!$E$13),I51) -> 0 | T51: =MIN(N('My Debts'!$E$14),J51) -> 0 | U51: =MIN(N('My Debts'!$E$15),K51) -> 0 | V51: =ROUND(B51-L51-MIN(B51-L51,MAX(0,$AF51-SUMPRODUCT(--($B$4:$K$4<B$4),$B51:$K51-$L51:$U51))),2) -> 0 | W51: =ROUND(C51-M51-MIN(C51-M51,MAX(0,$AF51-SUMPRODUCT(--($B$4:$K$4<C$4),$B51:$K51-$L51:$U51))),2) -> 0 | X51: =ROUND(D51-N51-MIN(D51-N51,MAX(0,$AF51-SUMPRODUCT(--($B$4:$K$4<D$4),$B51:$K51-$L51:$U51))),2) -> 0 | Y51: =ROUND(E51-O51-MIN(E51-O51,MAX(0,$AF51-SUMPRODUCT(--($B$4:$K$4<E$4),$B51:$K51-$L51:$U51))),2) -> 0 | Z51: =ROUND(F51-P51-MIN(F51-P51,MAX(0,$AF51-SUMPRODUCT(--($B$4:$K$4<F$4),$B51:$K51-$L51:$U51))),2) -> 0 | AA51: =ROUND(G51-Q51-MIN(G51-Q51,MAX(0,$AF51-SUMPRODUCT(--($B$4:$K$4<G$4),$B51:$K51-$L51:$U51))),2) -> 0 | AB51: =ROUND(H51-R51-MIN(H51-R51,MAX(0,$AF51-SUMPRODUCT(--($B$4:$K$4<H$4),$B51:$K51-$L51:$U51))),2) -> 0 | AC51: =ROUND(I51-S51-MIN(I51-S51,MAX(0,$AF51-SUMPRODUCT(--($B$4:$K$4<I$4),$B51:$K51-$L51:$U51))),2) -> 0 | ... AE51: =ROUND(K51-U51-MIN(K51-U51,MAX(0,$AF51-SUMPRODUCT(--($B$4:$K$4<K$4),$B51:$K51-$L51:$U51))),2) -> 0 | AF51: =MAX(0,'Start Here'!$C$5-SUM($L51:$U51)) -> 1200 | AG51: =SUM(V51:AE51) -> 0 | AH51: =SUM(B51:K51)-AG50 -> 0
A52: =DATE(YEAR('Start Here'!$C$6),MONTH('Start Here'!$C$6)+45,1) -> 47665 | B52: =ROUND(V51*(1+N('My Debts'!$D$6)/12),2) -> 0 | C52: =ROUND(W51*(1+N('My Debts'!$D$7)/12),2) -> 0 | D52: =ROUND(X51*(1+N('My Debts'!$D$8)/12),2) -> 0 | E52: =ROUND(Y51*(1+N('My Debts'!$D$9)/12),2) -> 0 | F52: =ROUND(Z51*(1+N('My Debts'!$D$10)/12),2) -> 0 | G52: =ROUND(AA51*(1+N('My Debts'!$D$11)/12),2) -> 0 | H52: =ROUND(AB51*(1+N('My Debts'!$D$12)/12),2) -> 0 | I52: =ROUND(AC51*(1+N('My Debts'!$D$13)/12),2) -> 0 | J52: =ROUND(AD51*(1+N('My Debts'!$D$14)/12),2) -> 0 | K52: =ROUND(AE51*(1+N('My Debts'!$D$15)/12),2) -> 0 | L52: =MIN(N('My Debts'!$E$6),B52) -> 0 | M52: =MIN(N('My Debts'!$E$7),C52) -> 0 | N52: =MIN(N('My Debts'!$E$8),D52) -> 0 | O52: =MIN(N('My Debts'!$E$9),E52) -> 0 | P52: =MIN(N('My Debts'!$E$10),F52) -> 0 | Q52: =MIN(N('My Debts'!$E$11),G52) -> 0 | R52: =MIN(N('My Debts'!$E$12),H52) -> 0 | S52: =MIN(N('My Debts'!$E$13),I52) -> 0 | T52: =MIN(N('My Debts'!$E$14),J52) -> 0 | U52: =MIN(N('My Debts'!$E$15),K52) -> 0 | V52: =ROUND(B52-L52-MIN(B52-L52,MAX(0,$AF52-SUMPRODUCT(--($B$4:$K$4<B$4),$B52:$K52-$L52:$U52))),2) -> 0 | W52: =ROUND(C52-M52-MIN(C52-M52,MAX(0,$AF52-SUMPRODUCT(--($B$4:$K$4<C$4),$B52:$K52-$L52:$U52))),2) -> 0 | X52: =ROUND(D52-N52-MIN(D52-N52,MAX(0,$AF52-SUMPRODUCT(--($B$4:$K$4<D$4),$B52:$K52-$L52:$U52))),2) -> 0 | Y52: =ROUND(E52-O52-MIN(E52-O52,MAX(0,$AF52-SUMPRODUCT(--($B$4:$K$4<E$4),$B52:$K52-$L52:$U52))),2) -> 0 | Z52: =ROUND(F52-P52-MIN(F52-P52,MAX(0,$AF52-SUMPRODUCT(--($B$4:$K$4<F$4),$B52:$K52-$L52:$U52))),2) -> 0 | AA52: =ROUND(G52-Q52-MIN(G52-Q52,MAX(0,$AF52-SUMPRODUCT(--($B$4:$K$4<G$4),$B52:$K52-$L52:$U52))),2) -> 0 | AB52: =ROUND(H52-R52-MIN(H52-R52,MAX(0,$AF52-SUMPRODUCT(--($B$4:$K$4<H$4),$B52:$K52-$L52:$U52))),2) -> 0 | AC52: =ROUND(I52-S52-MIN(I52-S52,MAX(0,$AF52-SUMPRODUCT(--($B$4:$K$4<I$4),$B52:$K52-$L52:$U52))),2) -> 0 | ... AE52: =ROUND(K52-U52-MIN(K52-U52,MAX(0,$AF52-SUMPRODUCT(--($B$4:$K$4<K$4),$B52:$K52-$L52:$U52))),2) -> 0 | AF52: =MAX(0,'Start Here'!$C$5-SUM($L52:$U52)) -> 1200 | AG52: =SUM(V52:AE52) -> 0 | AH52: =SUM(B52:K52)-AG51 -> 0
A53: =DATE(YEAR('Start Here'!$C$6),MONTH('Start Here'!$C$6)+46,1) -> 47696 | B53: =ROUND(V52*(1+N('My Debts'!$D$6)/12),2) -> 0 | C53: =ROUND(W52*(1+N('My Debts'!$D$7)/12),2) -> 0 | D53: =ROUND(X52*(1+N('My Debts'!$D$8)/12),2) -> 0 | E53: =ROUND(Y52*(1+N('My Debts'!$D$9)/12),2) -> 0 | F53: =ROUND(Z52*(1+N('My Debts'!$D$10)/12),2) -> 0 | G53: =ROUND(AA52*(1+N('My Debts'!$D$11)/12),2) -> 0 | H53: =ROUND(AB52*(1+N('My Debts'!$D$12)/12),2) -> 0 | I53: =ROUND(AC52*(1+N('My Debts'!$D$13)/12),2) -> 0 | J53: =ROUND(AD52*(1+N('My Debts'!$D$14)/12),2) -> 0 | K53: =ROUND(AE52*(1+N('My Debts'!$D$15)/12),2) -> 0 | L53: =MIN(N('My Debts'!$E$6),B53) -> 0 | M53: =MIN(N('My Debts'!$E$7),C53) -> 0 | N53: =MIN(N('My Debts'!$E$8),D53) -> 0 | O53: =MIN(N('My Debts'!$E$9),E53) -> 0 | P53: =MIN(N('My Debts'!$E$10),F53) -> 0 | Q53: =MIN(N('My Debts'!$E$11),G53) -> 0 | R53: =MIN(N('My Debts'!$E$12),H53) -> 0 | S53: =MIN(N('My Debts'!$E$13),I53) -> 0 | T53: =MIN(N('My Debts'!$E$14),J53) -> 0 | U53: =MIN(N('My Debts'!$E$15),K53) -> 0 | V53: =ROUND(B53-L53-MIN(B53-L53,MAX(0,$AF53-SUMPRODUCT(--($B$4:$K$4<B$4),$B53:$K53-$L53:$U53))),2) -> 0 | W53: =ROUND(C53-M53-MIN(C53-M53,MAX(0,$AF53-SUMPRODUCT(--($B$4:$K$4<C$4),$B53:$K53-$L53:$U53))),2) -> 0 | X53: =ROUND(D53-N53-MIN(D53-N53,MAX(0,$AF53-SUMPRODUCT(--($B$4:$K$4<D$4),$B53:$K53-$L53:$U53))),2) -> 0 | Y53: =ROUND(E53-O53-MIN(E53-O53,MAX(0,$AF53-SUMPRODUCT(--($B$4:$K$4<E$4),$B53:$K53-$L53:$U53))),2) -> 0 | Z53: =ROUND(F53-P53-MIN(F53-P53,MAX(0,$AF53-SUMPRODUCT(--($B$4:$K$4<F$4),$B53:$K53-$L53:$U53))),2) -> 0 | AA53: =ROUND(G53-Q53-MIN(G53-Q53,MAX(0,$AF53-SUMPRODUCT(--($B$4:$K$4<G$4),$B53:$K53-$L53:$U53))),2) -> 0 | AB53: =ROUND(H53-R53-MIN(H53-R53,MAX(0,$AF53-SUMPRODUCT(--($B$4:$K$4<H$4),$B53:$K53-$L53:$U53))),2) -> 0 | AC53: =ROUND(I53-S53-MIN(I53-S53,MAX(0,$AF53-SUMPRODUCT(--($B$4:$K$4<I$4),$B53:$K53-$L53:$U53))),2) -> 0 | ... AE53: =ROUND(K53-U53-MIN(K53-U53,MAX(0,$AF53-SUMPRODUCT(--($B$4:$K$4<K$4),$B53:$K53-$L53:$U53))),2) -> 0 | AF53: =MAX(0,'Start Here'!$C$5-SUM($L53:$U53)) -> 1200 | AG53: =SUM(V53:AE53) -> 0 | AH53: =SUM(B53:K53)-AG52 -> 0
A54: =DATE(YEAR('Start Here'!$C$6),MONTH('Start Here'!$C$6)+47,1) -> 47727 | B54: =ROUND(V53*(1+N('My Debts'!$D$6)/12),2) -> 0 | C54: =ROUND(W53*(1+N('My Debts'!$D$7)/12),2) -> 0 | D54: =ROUND(X53*(1+N('My Debts'!$D$8)/12),2) -> 0 | E54: =ROUND(Y53*(1+N('My Debts'!$D$9)/12),2) -> 0 | F54: =ROUND(Z53*(1+N('My Debts'!$D$10)/12),2) -> 0 | G54: =ROUND(AA53*(1+N('My Debts'!$D$11)/12),2) -> 0 | H54: =ROUND(AB53*(1+N('My Debts'!$D$12)/12),2) -> 0 | I54: =ROUND(AC53*(1+N('My Debts'!$D$13)/12),2) -> 0 | J54: =ROUND(AD53*(1+N('My Debts'!$D$14)/12),2) -> 0 | K54: =ROUND(AE53*(1+N('My Debts'!$D$15)/12),2) -> 0 | L54: =MIN(N('My Debts'!$E$6),B54) -> 0 | M54: =MIN(N('My Debts'!$E$7),C54) -> 0 | N54: =MIN(N('My Debts'!$E$8),D54) -> 0 | O54: =MIN(N('My Debts'!$E$9),E54) -> 0 | P54: =MIN(N('My Debts'!$E$10),F54) -> 0 | Q54: =MIN(N('My Debts'!$E$11),G54) -> 0 | R54: =MIN(N('My Debts'!$E$12),H54) -> 0 | S54: =MIN(N('My Debts'!$E$13),I54) -> 0 | T54: =MIN(N('My Debts'!$E$14),J54) -> 0 | U54: =MIN(N('My Debts'!$E$15),K54) -> 0 | V54: =ROUND(B54-L54-MIN(B54-L54,MAX(0,$AF54-SUMPRODUCT(--($B$4:$K$4<B$4),$B54:$K54-$L54:$U54))),2) -> 0 | W54: =ROUND(C54-M54-MIN(C54-M54,MAX(0,$AF54-SUMPRODUCT(--($B$4:$K$4<C$4),$B54:$K54-$L54:$U54))),2) -> 0 | X54: =ROUND(D54-N54-MIN(D54-N54,MAX(0,$AF54-SUMPRODUCT(--($B$4:$K$4<D$4),$B54:$K54-$L54:$U54))),2) -> 0 | Y54: =ROUND(E54-O54-MIN(E54-O54,MAX(0,$AF54-SUMPRODUCT(--($B$4:$K$4<E$4),$B54:$K54-$L54:$U54))),2) -> 0 | Z54: =ROUND(F54-P54-MIN(F54-P54,MAX(0,$AF54-SUMPRODUCT(--($B$4:$K$4<F$4),$B54:$K54-$L54:$U54))),2) -> 0 | AA54: =ROUND(G54-Q54-MIN(G54-Q54,MAX(0,$AF54-SUMPRODUCT(--($B$4:$K$4<G$4),$B54:$K54-$L54:$U54))),2) -> 0 | AB54: =ROUND(H54-R54-MIN(H54-R54,MAX(0,$AF54-SUMPRODUCT(--($B$4:$K$4<H$4),$B54:$K54-$L54:$U54))),2) -> 0 | AC54: =ROUND(I54-S54-MIN(I54-S54,MAX(0,$AF54-SUMPRODUCT(--($B$4:$K$4<I$4),$B54:$K54-$L54:$U54))),2) -> 0 | ... AE54: =ROUND(K54-U54-MIN(K54-U54,MAX(0,$AF54-SUMPRODUCT(--($B$4:$K$4<K$4),$B54:$K54-$L54:$U54))),2) -> 0 | AF54: =MAX(0,'Start Here'!$C$5-SUM($L54:$U54)) -> 1200 | AG54: =SUM(V54:AE54) -> 0 | AH54: =SUM(B54:K54)-AG53 -> 0
A55: =DATE(YEAR('Start Here'!$C$6),MONTH('Start Here'!$C$6)+48,1) -> 47757 | B55: =ROUND(V54*(1+N('My Debts'!$D$6)/12),2) -> 0 | C55: =ROUND(W54*(1+N('My Debts'!$D$7)/12),2) -> 0 | D55: =ROUND(X54*(1+N('My Debts'!$D$8)/12),2) -> 0 | E55: =ROUND(Y54*(1+N('My Debts'!$D$9)/12),2) -> 0 | F55: =ROUND(Z54*(1+N('My Debts'!$D$10)/12),2) -> 0 | G55: =ROUND(AA54*(1+N('My Debts'!$D$11)/12),2) -> 0 | H55: =ROUND(AB54*(1+N('My Debts'!$D$12)/12),2) -> 0 | I55: =ROUND(AC54*(1+N('My Debts'!$D$13)/12),2) -> 0 | J55: =ROUND(AD54*(1+N('My Debts'!$D$14)/12),2) -> 0 | K55: =ROUND(AE54*(1+N('My Debts'!$D$15)/12),2) -> 0 | L55: =MIN(N('My Debts'!$E$6),B55) -> 0 | M55: =MIN(N('My Debts'!$E$7),C55) -> 0 | N55: =MIN(N('My Debts'!$E$8),D55) -> 0 | O55: =MIN(N('My Debts'!$E$9),E55) -> 0 | P55: =MIN(N('My Debts'!$E$10),F55) -> 0 | Q55: =MIN(N('My Debts'!$E$11),G55) -> 0 | R55: =MIN(N('My Debts'!$E$12),H55) -> 0 | S55: =MIN(N('My Debts'!$E$13),I55) -> 0 | T55: =MIN(N('My Debts'!$E$14),J55) -> 0 | U55: =MIN(N('My Debts'!$E$15),K55) -> 0 | V55: =ROUND(B55-L55-MIN(B55-L55,MAX(0,$AF55-SUMPRODUCT(--($B$4:$K$4<B$4),$B55:$K55-$L55:$U55))),2) -> 0 | W55: =ROUND(C55-M55-MIN(C55-M55,MAX(0,$AF55-SUMPRODUCT(--($B$4:$K$4<C$4),$B55:$K55-$L55:$U55))),2) -> 0 | X55: =ROUND(D55-N55-MIN(D55-N55,MAX(0,$AF55-SUMPRODUCT(--($B$4:$K$4<D$4),$B55:$K55-$L55:$U55))),2) -> 0 | Y55: =ROUND(E55-O55-MIN(E55-O55,MAX(0,$AF55-SUMPRODUCT(--($B$4:$K$4<E$4),$B55:$K55-$L55:$U55))),2) -> 0 | Z55: =ROUND(F55-P55-MIN(F55-P55,MAX(0,$AF55-SUMPRODUCT(--($B$4:$K$4<F$4),$B55:$K55-$L55:$U55))),2) -> 0 | AA55: =ROUND(G55-Q55-MIN(G55-Q55,MAX(0,$AF55-SUMPRODUCT(--($B$4:$K$4<G$4),$B55:$K55-$L55:$U55))),2) -> 0 | AB55: =ROUND(H55-R55-MIN(H55-R55,MAX(0,$AF55-SUMPRODUCT(--($B$4:$K$4<H$4),$B55:$K55-$L55:$U55))),2) -> 0 | AC55: =ROUND(I55-S55-MIN(I55-S55,MAX(0,$AF55-SUMPRODUCT(--($B$4:$K$4<I$4),$B55:$K55-$L55:$U55))),2) -> 0 | ... AE55: =ROUND(K55-U55-MIN(K55-U55,MAX(0,$AF55-SUMPRODUCT(--($B$4:$K$4<K$4),$B55:$K55-$L55:$U55))),2) -> 0 | AF55: =MAX(0,'Start Here'!$C$5-SUM($L55:$U55)) -> 1200 | AG55: =SUM(V55:AE55) -> 0 | AH55: =SUM(B55:K55)-AG54 -> 0
A56: =DATE(YEAR('Start Here'!$C$6),MONTH('Start Here'!$C$6)+49,1) -> 47788 | B56: =ROUND(V55*(1+N('My Debts'!$D$6)/12),2) -> 0 | C56: =ROUND(W55*(1+N('My Debts'!$D$7)/12),2) -> 0 | D56: =ROUND(X55*(1+N('My Debts'!$D$8)/12),2) -> 0 | E56: =ROUND(Y55*(1+N('My Debts'!$D$9)/12),2) -> 0 | F56: =ROUND(Z55*(1+N('My Debts'!$D$10)/12),2) -> 0 | G56: =ROUND(AA55*(1+N('My Debts'!$D$11)/12),2) -> 0 | H56: =ROUND(AB55*(1+N('My Debts'!$D$12)/12),2) -> 0 | I56: =ROUND(AC55*(1+N('My Debts'!$D$13)/12),2) -> 0 | J56: =ROUND(AD55*(1+N('My Debts'!$D$14)/12),2) -> 0 | K56: =ROUND(AE55*(1+N('My Debts'!$D$15)/12),2) -> 0 | L56: =MIN(N('My Debts'!$E$6),B56) -> 0 | M56: =MIN(N('My Debts'!$E$7),C56) -> 0 | N56: =MIN(N('My Debts'!$E$8),D56) -> 0 | O56: =MIN(N('My Debts'!$E$9),E56) -> 0 | P56: =MIN(N('My Debts'!$E$10),F56) -> 0 | Q56: =MIN(N('My Debts'!$E$11),G56) -> 0 | R56: =MIN(N('My Debts'!$E$12),H56) -> 0 | S56: =MIN(N('My Debts'!$E$13),I56) -> 0 | T56: =MIN(N('My Debts'!$E$14),J56) -> 0 | U56: =MIN(N('My Debts'!$E$15),K56) -> 0 | V56: =ROUND(B56-L56-MIN(B56-L56,MAX(0,$AF56-SUMPRODUCT(--($B$4:$K$4<B$4),$B56:$K56-$L56:$U56))),2) -> 0 | W56: =ROUND(C56-M56-MIN(C56-M56,MAX(0,$AF56-SUMPRODUCT(--($B$4:$K$4<C$4),$B56:$K56-$L56:$U56))),2) -> 0 | X56: =ROUND(D56-N56-MIN(D56-N56,MAX(0,$AF56-SUMPRODUCT(--($B$4:$K$4<D$4),$B56:$K56-$L56:$U56))),2) -> 0 | Y56: =ROUND(E56-O56-MIN(E56-O56,MAX(0,$AF56-SUMPRODUCT(--($B$4:$K$4<E$4),$B56:$K56-$L56:$U56))),2) -> 0 | Z56: =ROUND(F56-P56-MIN(F56-P56,MAX(0,$AF56-SUMPRODUCT(--($B$4:$K$4<F$4),$B56:$K56-$L56:$U56))),2) -> 0 | AA56: =ROUND(G56-Q56-MIN(G56-Q56,MAX(0,$AF56-SUMPRODUCT(--($B$4:$K$4<G$4),$B56:$K56-$L56:$U56))),2) -> 0 | AB56: =ROUND(H56-R56-MIN(H56-R56,MAX(0,$AF56-SUMPRODUCT(--($B$4:$K$4<H$4),$B56:$K56-$L56:$U56))),2) -> 0 | AC56: =ROUND(I56-S56-MIN(I56-S56,MAX(0,$AF56-SUMPRODUCT(--($B$4:$K$4<I$4),$B56:$K56-$L56:$U56))),2) -> 0 | ... AE56: =ROUND(K56-U56-MIN(K56-U56,MAX(0,$AF56-SUMPRODUCT(--($B$4:$K$4<K$4),$B56:$K56-$L56:$U56))),2) -> 0 | AF56: =MAX(0,'Start Here'!$C$5-SUM($L56:$U56)) -> 1200 | AG56: =SUM(V56:AE56) -> 0 | AH56: =SUM(B56:K56)-AG55 -> 0
A57: =DATE(YEAR('Start Here'!$C$6),MONTH('Start Here'!$C$6)+50,1) -> 47818 | B57: =ROUND(V56*(1+N('My Debts'!$D$6)/12),2) -> 0 | C57: =ROUND(W56*(1+N('My Debts'!$D$7)/12),2) -> 0 | D57: =ROUND(X56*(1+N('My Debts'!$D$8)/12),2) -> 0 | E57: =ROUND(Y56*(1+N('My Debts'!$D$9)/12),2) -> 0 | F57: =ROUND(Z56*(1+N('My Debts'!$D$10)/12),2) -> 0 | G57: =ROUND(AA56*(1+N('My Debts'!$D$11)/12),2) -> 0 | H57: =ROUND(AB56*(1+N('My Debts'!$D$12)/12),2) -> 0 | I57: =ROUND(AC56*(1+N('My Debts'!$D$13)/12),2) -> 0 | J57: =ROUND(AD56*(1+N('My Debts'!$D$14)/12),2) -> 0 | K57: =ROUND(AE56*(1+N('My Debts'!$D$15)/12),2) -> 0 | L57: =MIN(N('My Debts'!$E$6),B57) -> 0 | M57: =MIN(N('My Debts'!$E$7),C57) -> 0 | N57: =MIN(N('My Debts'!$E$8),D57) -> 0 | O57: =MIN(N('My Debts'!$E$9),E57) -> 0 | P57: =MIN(N('My Debts'!$E$10),F57) -> 0 | Q57: =MIN(N('My Debts'!$E$11),G57) -> 0 | R57: =MIN(N('My Debts'!$E$12),H57) -> 0 | S57: =MIN(N('My Debts'!$E$13),I57) -> 0 | T57: =MIN(N('My Debts'!$E$14),J57) -> 0 | U57: =MIN(N('My Debts'!$E$15),K57) -> 0 | V57: =ROUND(B57-L57-MIN(B57-L57,MAX(0,$AF57-SUMPRODUCT(--($B$4:$K$4<B$4),$B57:$K57-$L57:$U57))),2) -> 0 | W57: =ROUND(C57-M57-MIN(C57-M57,MAX(0,$AF57-SUMPRODUCT(--($B$4:$K$4<C$4),$B57:$K57-$L57:$U57))),2) -> 0 | X57: =ROUND(D57-N57-MIN(D57-N57,MAX(0,$AF57-SUMPRODUCT(--($B$4:$K$4<D$4),$B57:$K57-$L57:$U57))),2) -> 0 | Y57: =ROUND(E57-O57-MIN(E57-O57,MAX(0,$AF57-SUMPRODUCT(--($B$4:$K$4<E$4),$B57:$K57-$L57:$U57))),2) -> 0 | Z57: =ROUND(F57-P57-MIN(F57-P57,MAX(0,$AF57-SUMPRODUCT(--($B$4:$K$4<F$4),$B57:$K57-$L57:$U57))),2) -> 0 | AA57: =ROUND(G57-Q57-MIN(G57-Q57,MAX(0,$AF57-SUMPRODUCT(--($B$4:$K$4<G$4),$B57:$K57-$L57:$U57))),2) -> 0 | AB57: =ROUND(H57-R57-MIN(H57-R57,MAX(0,$AF57-SUMPRODUCT(--($B$4:$K$4<H$4),$B57:$K57-$L57:$U57))),2) -> 0 | AC57: =ROUND(I57-S57-MIN(I57-S57,MAX(0,$AF57-SUMPRODUCT(--($B$4:$K$4<I$4),$B57:$K57-$L57:$U57))),2) -> 0 | ... AE57: =ROUND(K57-U57-MIN(K57-U57,MAX(0,$AF57-SUMPRODUCT(--($B$4:$K$4<K$4),$B57:$K57-$L57:$U57))),2) -> 0 | AF57: =MAX(0,'Start Here'!$C$5-SUM($L57:$U57)) -> 1200 | AG57: =SUM(V57:AE57) -> 0 | AH57: =SUM(B57:K57)-AG56 -> 0
A58: =DATE(YEAR('Start Here'!$C$6),MONTH('Start Here'!$C$6)+51,1) -> 47849 | B58: =ROUND(V57*(1+N('My Debts'!$D$6)/12),2) -> 0 | C58: =ROUND(W57*(1+N('My Debts'!$D$7)/12),2) -> 0 | D58: =ROUND(X57*(1+N('My Debts'!$D$8)/12),2) -> 0 | E58: =ROUND(Y57*(1+N('My Debts'!$D$9)/12),2) -> 0 | F58: =ROUND(Z57*(1+N('My Debts'!$D$10)/12),2) -> 0 | G58: =ROUND(AA57*(1+N('My Debts'!$D$11)/12),2) -> 0 | H58: =ROUND(AB57*(1+N('My Debts'!$D$12)/12),2) -> 0 | I58: =ROUND(AC57*(1+N('My Debts'!$D$13)/12),2) -> 0 | J58: =ROUND(AD57*(1+N('My Debts'!$D$14)/12),2) -> 0 | K58: =ROUND(AE57*(1+N('My Debts'!$D$15)/12),2) -> 0 | L58: =MIN(N('My Debts'!$E$6),B58) -> 0 | M58: =MIN(N('My Debts'!$E$7),C58) -> 0 | N58: =MIN(N('My Debts'!$E$8),D58) -> 0 | O58: =MIN(N('My Debts'!$E$9),E58) -> 0 | P58: =MIN(N('My Debts'!$E$10),F58) -> 0 | Q58: =MIN(N('My Debts'!$E$11),G58) -> 0 | R58: =MIN(N('My Debts'!$E$12),H58) -> 0 | S58: =MIN(N('My Debts'!$E$13),I58) -> 0 | T58: =MIN(N('My Debts'!$E$14),J58) -> 0 | U58: =MIN(N('My Debts'!$E$15),K58) -> 0 | V58: =ROUND(B58-L58-MIN(B58-L58,MAX(0,$AF58-SUMPRODUCT(--($B$4:$K$4<B$4),$B58:$K58-$L58:$U58))),2) -> 0 | W58: =ROUND(C58-M58-MIN(C58-M58,MAX(0,$AF58-SUMPRODUCT(--($B$4:$K$4<C$4),$B58:$K58-$L58:$U58))),2) -> 0 | X58: =ROUND(D58-N58-MIN(D58-N58,MAX(0,$AF58-SUMPRODUCT(--($B$4:$K$4<D$4),$B58:$K58-$L58:$U58))),2) -> 0 | Y58: =ROUND(E58-O58-MIN(E58-O58,MAX(0,$AF58-SUMPRODUCT(--($B$4:$K$4<E$4),$B58:$K58-$L58:$U58))),2) -> 0 | Z58: =ROUND(F58-P58-MIN(F58-P58,MAX(0,$AF58-SUMPRODUCT(--($B$4:$K$4<F$4),$B58:$K58-$L58:$U58))),2) -> 0 | AA58: =ROUND(G58-Q58-MIN(G58-Q58,MAX(0,$AF58-SUMPRODUCT(--($B$4:$K$4<G$4),$B58:$K58-$L58:$U58))),2) -> 0 | AB58: =ROUND(H58-R58-MIN(H58-R58,MAX(0,$AF58-SUMPRODUCT(--($B$4:$K$4<H$4),$B58:$K58-$L58:$U58))),2) -> 0 | AC58: =ROUND(I58-S58-MIN(I58-S58,MAX(0,$AF58-SUMPRODUCT(--($B$4:$K$4<I$4),$B58:$K58-$L58:$U58))),2) -> 0 | ... AE58: =ROUND(K58-U58-MIN(K58-U58,MAX(0,$AF58-SUMPRODUCT(--($B$4:$K$4<K$4),$B58:$K58-$L58:$U58))),2) -> 0 | AF58: =MAX(0,'Start Here'!$C$5-SUM($L58:$U58)) -> 1200 | AG58: =SUM(V58:AE58) -> 0 | AH58: =SUM(B58:K58)-AG57 -> 0
A59: =DATE(YEAR('Start Here'!$C$6),MONTH('Start Here'!$C$6)+52,1) -> 47880 | B59: =ROUND(V58*(1+N('My Debts'!$D$6)/12),2) -> 0 | C59: =ROUND(W58*(1+N('My Debts'!$D$7)/12),2) -> 0 | D59: =ROUND(X58*(1+N('My Debts'!$D$8)/12),2) -> 0 | E59: =ROUND(Y58*(1+N('My Debts'!$D$9)/12),2) -> 0 | F59: =ROUND(Z58*(1+N('My Debts'!$D$10)/12),2) -> 0 | G59: =ROUND(AA58*(1+N('My Debts'!$D$11)/12),2) -> 0 | H59: =ROUND(AB58*(1+N('My Debts'!$D$12)/12),2) -> 0 | I59: =ROUND(AC58*(1+N('My Debts'!$D$13)/12),2) -> 0 | J59: =ROUND(AD58*(1+N('My Debts'!$D$14)/12),2) -> 0 | K59: =ROUND(AE58*(1+N('My Debts'!$D$15)/12),2) -> 0 | L59: =MIN(N('My Debts'!$E$6),B59) -> 0 | M59: =MIN(N('My Debts'!$E$7),C59) -> 0 | N59: =MIN(N('My Debts'!$E$8),D59) -> 0 | O59: =MIN(N('My Debts'!$E$9),E59) -> 0 | P59: =MIN(N('My Debts'!$E$10),F59) -> 0 | Q59: =MIN(N('My Debts'!$E$11),G59) -> 0 | R59: =MIN(N('My Debts'!$E$12),H59) -> 0 | S59: =MIN(N('My Debts'!$E$13),I59) -> 0 | T59: =MIN(N('My Debts'!$E$14),J59) -> 0 | U59: =MIN(N('My Debts'!$E$15),K59) -> 0 | V59: =ROUND(B59-L59-MIN(B59-L59,MAX(0,$AF59-SUMPRODUCT(--($B$4:$K$4<B$4),$B59:$K59-$L59:$U59))),2) -> 0 | W59: =ROUND(C59-M59-MIN(C59-M59,MAX(0,$AF59-SUMPRODUCT(--($B$4:$K$4<C$4),$B59:$K59-$L59:$U59))),2) -> 0 | X59: =ROUND(D59-N59-MIN(D59-N59,MAX(0,$AF59-SUMPRODUCT(--($B$4:$K$4<D$4),$B59:$K59-$L59:$U59))),2) -> 0 | Y59: =ROUND(E59-O59-MIN(E59-O59,MAX(0,$AF59-SUMPRODUCT(--($B$4:$K$4<E$4),$B59:$K59-$L59:$U59))),2) -> 0 | Z59: =ROUND(F59-P59-MIN(F59-P59,MAX(0,$AF59-SUMPRODUCT(--($B$4:$K$4<F$4),$B59:$K59-$L59:$U59))),2) -> 0 | AA59: =ROUND(G59-Q59-MIN(G59-Q59,MAX(0,$AF59-SUMPRODUCT(--($B$4:$K$4<G$4),$B59:$K59-$L59:$U59))),2) -> 0 | AB59: =ROUND(H59-R59-MIN(H59-R59,MAX(0,$AF59-SUMPRODUCT(--($B$4:$K$4<H$4),$B59:$K59-$L59:$U59))),2) -> 0 | AC59: =ROUND(I59-S59-MIN(I59-S59,MAX(0,$AF59-SUMPRODUCT(--($B$4:$K$4<I$4),$B59:$K59-$L59:$U59))),2) -> 0 | ... AE59: =ROUND(K59-U59-MIN(K59-U59,MAX(0,$AF59-SUMPRODUCT(--($B$4:$K$4<K$4),$B59:$K59-$L59:$U59))),2) -> 0 | AF59: =MAX(0,'Start Here'!$C$5-SUM($L59:$U59)) -> 1200 | AG59: =SUM(V59:AE59) -> 0 | AH59: =SUM(B59:K59)-AG58 -> 0
A60: =DATE(YEAR('Start Here'!$C$6),MONTH('Start Here'!$C$6)+53,1) -> 47908 | B60: =ROUND(V59*(1+N('My Debts'!$D$6)/12),2) -> 0 | C60: =ROUND(W59*(1+N('My Debts'!$D$7)/12),2) -> 0 | D60: =ROUND(X59*(1+N('My Debts'!$D$8)/12),2) -> 0 | E60: =ROUND(Y59*(1+N('My Debts'!$D$9)/12),2) -> 0 | F60: =ROUND(Z59*(1+N('My Debts'!$D$10)/12),2) -> 0 | G60: =ROUND(AA59*(1+N('My Debts'!$D$11)/12),2) -> 0 | H60: =ROUND(AB59*(1+N('My Debts'!$D$12)/12),2) -> 0 | I60: =ROUND(AC59*(1+N('My Debts'!$D$13)/12),2) -> 0 | J60: =ROUND(AD59*(1+N('My Debts'!$D$14)/12),2) -> 0 | K60: =ROUND(AE59*(1+N('My Debts'!$D$15)/12),2) -> 0 | L60: =MIN(N('My Debts'!$E$6),B60) -> 0 | M60: =MIN(N('My Debts'!$E$7),C60) -> 0 | N60: =MIN(N('My Debts'!$E$8),D60) -> 0 | O60: =MIN(N('My Debts'!$E$9),E60) -> 0 | P60: =MIN(N('My Debts'!$E$10),F60) -> 0 | Q60: =MIN(N('My Debts'!$E$11),G60) -> 0 | R60: =MIN(N('My Debts'!$E$12),H60) -> 0 | S60: =MIN(N('My Debts'!$E$13),I60) -> 0 | T60: =MIN(N('My Debts'!$E$14),J60) -> 0 | U60: =MIN(N('My Debts'!$E$15),K60) -> 0 | V60: =ROUND(B60-L60-MIN(B60-L60,MAX(0,$AF60-SUMPRODUCT(--($B$4:$K$4<B$4),$B60:$K60-$L60:$U60))),2) -> 0 | W60: =ROUND(C60-M60-MIN(C60-M60,MAX(0,$AF60-SUMPRODUCT(--($B$4:$K$4<C$4),$B60:$K60-$L60:$U60))),2) -> 0 | X60: =ROUND(D60-N60-MIN(D60-N60,MAX(0,$AF60-SUMPRODUCT(--($B$4:$K$4<D$4),$B60:$K60-$L60:$U60))),2) -> 0 | Y60: =ROUND(E60-O60-MIN(E60-O60,MAX(0,$AF60-SUMPRODUCT(--($B$4:$K$4<E$4),$B60:$K60-$L60:$U60))),2) -> 0 | Z60: =ROUND(F60-P60-MIN(F60-P60,MAX(0,$AF60-SUMPRODUCT(--($B$4:$K$4<F$4),$B60:$K60-$L60:$U60))),2) -> 0 | AA60: =ROUND(G60-Q60-MIN(G60-Q60,MAX(0,$AF60-SUMPRODUCT(--($B$4:$K$4<G$4),$B60:$K60-$L60:$U60))),2) -> 0 | AB60: =ROUND(H60-R60-MIN(H60-R60,MAX(0,$AF60-SUMPRODUCT(--($B$4:$K$4<H$4),$B60:$K60-$L60:$U60))),2) -> 0 | AC60: =ROUND(I60-S60-MIN(I60-S60,MAX(0,$AF60-SUMPRODUCT(--($B$4:$K$4<I$4),$B60:$K60-$L60:$U60))),2) -> 0 | ... AE60: =ROUND(K60-U60-MIN(K60-U60,MAX(0,$AF60-SUMPRODUCT(--($B$4:$K$4<K$4),$B60:$K60-$L60:$U60))),2) -> 0 | AF60: =MAX(0,'Start Here'!$C$5-SUM($L60:$U60)) -> 1200 | AG60: =SUM(V60:AE60) -> 0 | AH60: =SUM(B60:K60)-AG59 -> 0
A61: =DATE(YEAR('Start Here'!$C$6),MONTH('Start Here'!$C$6)+54,1) -> 47939 | B61: =ROUND(V60*(1+N('My Debts'!$D$6)/12),2) -> 0 | C61: =ROUND(W60*(1+N('My Debts'!$D$7)/12),2) -> 0 | D61: =ROUND(X60*(1+N('My Debts'!$D$8)/12),2) -> 0 | E61: =ROUND(Y60*(1+N('My Debts'!$D$9)/12),2) -> 0 | F61: =ROUND(Z60*(1+N('My Debts'!$D$10)/12),2) -> 0 | G61: =ROUND(AA60*(1+N('My Debts'!$D$11)/12),2) -> 0 | H61: =ROUND(AB60*(1+N('My Debts'!$D$12)/12),2) -> 0 | I61: =ROUND(AC60*(1+N('My Debts'!$D$13)/12),2) -> 0 | J61: =ROUND(AD60*(1+N('My Debts'!$D$14)/12),2) -> 0 | K61: =ROUND(AE60*(1+N('My Debts'!$D$15)/12),2) -> 0 | L61: =MIN(N('My Debts'!$E$6),B61) -> 0 | M61: =MIN(N('My Debts'!$E$7),C61) -> 0 | N61: =MIN(N('My Debts'!$E$8),D61) -> 0 | O61: =MIN(N('My Debts'!$E$9),E61) -> 0 | P61: =MIN(N('My Debts'!$E$10),F61) -> 0 | Q61: =MIN(N('My Debts'!$E$11),G61) -> 0 | R61: =MIN(N('My Debts'!$E$12),H61) -> 0 | S61: =MIN(N('My Debts'!$E$13),I61) -> 0 | T61: =MIN(N('My Debts'!$E$14),J61) -> 0 | U61: =MIN(N('My Debts'!$E$15),K61) -> 0 | V61: =ROUND(B61-L61-MIN(B61-L61,MAX(0,$AF61-SUMPRODUCT(--($B$4:$K$4<B$4),$B61:$K61-$L61:$U61))),2) -> 0 | W61: =ROUND(C61-M61-MIN(C61-M61,MAX(0,$AF61-SUMPRODUCT(--($B$4:$K$4<C$4),$B61:$K61-$L61:$U61))),2) -> 0 | X61: =ROUND(D61-N61-MIN(D61-N61,MAX(0,$AF61-SUMPRODUCT(--($B$4:$K$4<D$4),$B61:$K61-$L61:$U61))),2) -> 0 | Y61: =ROUND(E61-O61-MIN(E61-O61,MAX(0,$AF61-SUMPRODUCT(--($B$4:$K$4<E$4),$B61:$K61-$L61:$U61))),2) -> 0 | Z61: =ROUND(F61-P61-MIN(F61-P61,MAX(0,$AF61-SUMPRODUCT(--($B$4:$K$4<F$4),$B61:$K61-$L61:$U61))),2) -> 0 | AA61: =ROUND(G61-Q61-MIN(G61-Q61,MAX(0,$AF61-SUMPRODUCT(--($B$4:$K$4<G$4),$B61:$K61-$L61:$U61))),2) -> 0 | AB61: =ROUND(H61-R61-MIN(H61-R61,MAX(0,$AF61-SUMPRODUCT(--($B$4:$K$4<H$4),$B61:$K61-$L61:$U61))),2) -> 0 | AC61: =ROUND(I61-S61-MIN(I61-S61,MAX(0,$AF61-SUMPRODUCT(--($B$4:$K$4<I$4),$B61:$K61-$L61:$U61))),2) -> 0 | ... AE61: =ROUND(K61-U61-MIN(K61-U61,MAX(0,$AF61-SUMPRODUCT(--($B$4:$K$4<K$4),$B61:$K61-$L61:$U61))),2) -> 0 | AF61: =MAX(0,'Start Here'!$C$5-SUM($L61:$U61)) -> 1200 | AG61: =SUM(V61:AE61) -> 0 | AH61: =SUM(B61:K61)-AG60 -> 0
A62: =DATE(YEAR('Start Here'!$C$6),MONTH('Start Here'!$C$6)+55,1) -> 47969 | B62: =ROUND(V61*(1+N('My Debts'!$D$6)/12),2) -> 0 | C62: =ROUND(W61*(1+N('My Debts'!$D$7)/12),2) -> 0 | D62: =ROUND(X61*(1+N('My Debts'!$D$8)/12),2) -> 0 | E62: =ROUND(Y61*(1+N('My Debts'!$D$9)/12),2) -> 0 | F62: =ROUND(Z61*(1+N('My Debts'!$D$10)/12),2) -> 0 | G62: =ROUND(AA61*(1+N('My Debts'!$D$11)/12),2) -> 0 | H62: =ROUND(AB61*(1+N('My Debts'!$D$12)/12),2) -> 0 | I62: =ROUND(AC61*(1+N('My Debts'!$D$13)/12),2) -> 0 | J62: =ROUND(AD61*(1+N('My Debts'!$D$14)/12),2) -> 0 | K62: =ROUND(AE61*(1+N('My Debts'!$D$15)/12),2) -> 0 | L62: =MIN(N('My Debts'!$E$6),B62) -> 0 | M62: =MIN(N('My Debts'!$E$7),C62) -> 0 | N62: =MIN(N('My Debts'!$E$8),D62) -> 0 | O62: =MIN(N('My Debts'!$E$9),E62) -> 0 | P62: =MIN(N('My Debts'!$E$10),F62) -> 0 | Q62: =MIN(N('My Debts'!$E$11),G62) -> 0 | R62: =MIN(N('My Debts'!$E$12),H62) -> 0 | S62: =MIN(N('My Debts'!$E$13),I62) -> 0 | T62: =MIN(N('My Debts'!$E$14),J62) -> 0 | U62: =MIN(N('My Debts'!$E$15),K62) -> 0 | V62: =ROUND(B62-L62-MIN(B62-L62,MAX(0,$AF62-SUMPRODUCT(--($B$4:$K$4<B$4),$B62:$K62-$L62:$U62))),2) -> 0 | W62: =ROUND(C62-M62-MIN(C62-M62,MAX(0,$AF62-SUMPRODUCT(--($B$4:$K$4<C$4),$B62:$K62-$L62:$U62))),2) -> 0 | X62: =ROUND(D62-N62-MIN(D62-N62,MAX(0,$AF62-SUMPRODUCT(--($B$4:$K$4<D$4),$B62:$K62-$L62:$U62))),2) -> 0 | Y62: =ROUND(E62-O62-MIN(E62-O62,MAX(0,$AF62-SUMPRODUCT(--($B$4:$K$4<E$4),$B62:$K62-$L62:$U62))),2) -> 0 | Z62: =ROUND(F62-P62-MIN(F62-P62,MAX(0,$AF62-SUMPRODUCT(--($B$4:$K$4<F$4),$B62:$K62-$L62:$U62))),2) -> 0 | AA62: =ROUND(G62-Q62-MIN(G62-Q62,MAX(0,$AF62-SUMPRODUCT(--($B$4:$K$4<G$4),$B62:$K62-$L62:$U62))),2) -> 0 | AB62: =ROUND(H62-R62-MIN(H62-R62,MAX(0,$AF62-SUMPRODUCT(--($B$4:$K$4<H$4),$B62:$K62-$L62:$U62))),2) -> 0 | AC62: =ROUND(I62-S62-MIN(I62-S62,MAX(0,$AF62-SUMPRODUCT(--($B$4:$K$4<I$4),$B62:$K62-$L62:$U62))),2) -> 0 | ... AE62: =ROUND(K62-U62-MIN(K62-U62,MAX(0,$AF62-SUMPRODUCT(--($B$4:$K$4<K$4),$B62:$K62-$L62:$U62))),2) -> 0 | AF62: =MAX(0,'Start Here'!$C$5-SUM($L62:$U62)) -> 1200 | AG62: =SUM(V62:AE62) -> 0 | AH62: =SUM(B62:K62)-AG61 -> 0
A63: =DATE(YEAR('Start Here'!$C$6),MONTH('Start Here'!$C$6)+56,1) -> 48000 | B63: =ROUND(V62*(1+N('My Debts'!$D$6)/12),2) -> 0 | C63: =ROUND(W62*(1+N('My Debts'!$D$7)/12),2) -> 0 | D63: =ROUND(X62*(1+N('My Debts'!$D$8)/12),2) -> 0 | E63: =ROUND(Y62*(1+N('My Debts'!$D$9)/12),2) -> 0 | F63: =ROUND(Z62*(1+N('My Debts'!$D$10)/12),2) -> 0 | G63: =ROUND(AA62*(1+N('My Debts'!$D$11)/12),2) -> 0 | H63: =ROUND(AB62*(1+N('My Debts'!$D$12)/12),2) -> 0 | I63: =ROUND(AC62*(1+N('My Debts'!$D$13)/12),2) -> 0 | J63: =ROUND(AD62*(1+N('My Debts'!$D$14)/12),2) -> 0 | K63: =ROUND(AE62*(1+N('My Debts'!$D$15)/12),2) -> 0 | L63: =MIN(N('My Debts'!$E$6),B63) -> 0 | M63: =MIN(N('My Debts'!$E$7),C63) -> 0 | N63: =MIN(N('My Debts'!$E$8),D63) -> 0 | O63: =MIN(N('My Debts'!$E$9),E63) -> 0 | P63: =MIN(N('My Debts'!$E$10),F63) -> 0 | Q63: =MIN(N('My Debts'!$E$11),G63) -> 0 | R63: =MIN(N('My Debts'!$E$12),H63) -> 0 | S63: =MIN(N('My Debts'!$E$13),I63) -> 0 | T63: =MIN(N('My Debts'!$E$14),J63) -> 0 | U63: =MIN(N('My Debts'!$E$15),K63) -> 0 | V63: =ROUND(B63-L63-MIN(B63-L63,MAX(0,$AF63-SUMPRODUCT(--($B$4:$K$4<B$4),$B63:$K63-$L63:$U63))),2) -> 0 | W63: =ROUND(C63-M63-MIN(C63-M63,MAX(0,$AF63-SUMPRODUCT(--($B$4:$K$4<C$4),$B63:$K63-$L63:$U63))),2) -> 0 | X63: =ROUND(D63-N63-MIN(D63-N63,MAX(0,$AF63-SUMPRODUCT(--($B$4:$K$4<D$4),$B63:$K63-$L63:$U63))),2) -> 0 | Y63: =ROUND(E63-O63-MIN(E63-O63,MAX(0,$AF63-SUMPRODUCT(--($B$4:$K$4<E$4),$B63:$K63-$L63:$U63))),2) -> 0 | Z63: =ROUND(F63-P63-MIN(F63-P63,MAX(0,$AF63-SUMPRODUCT(--($B$4:$K$4<F$4),$B63:$K63-$L63:$U63))),2) -> 0 | AA63: =ROUND(G63-Q63-MIN(G63-Q63,MAX(0,$AF63-SUMPRODUCT(--($B$4:$K$4<G$4),$B63:$K63-$L63:$U63))),2) -> 0 | AB63: =ROUND(H63-R63-MIN(H63-R63,MAX(0,$AF63-SUMPRODUCT(--($B$4:$K$4<H$4),$B63:$K63-$L63:$U63))),2) -> 0 | AC63: =ROUND(I63-S63-MIN(I63-S63,MAX(0,$AF63-SUMPRODUCT(--($B$4:$K$4<I$4),$B63:$K63-$L63:$U63))),2) -> 0 | ... AE63: =ROUND(K63-U63-MIN(K63-U63,MAX(0,$AF63-SUMPRODUCT(--($B$4:$K$4<K$4),$B63:$K63-$L63:$U63))),2) -> 0 | AF63: =MAX(0,'Start Here'!$C$5-SUM($L63:$U63)) -> 1200 | AG63: =SUM(V63:AE63) -> 0 | AH63: =SUM(B63:K63)-AG62 -> 0
A64: =DATE(YEAR('Start Here'!$C$6),MONTH('Start Here'!$C$6)+57,1) -> 48030 | B64: =ROUND(V63*(1+N('My Debts'!$D$6)/12),2) -> 0 | C64: =ROUND(W63*(1+N('My Debts'!$D$7)/12),2) -> 0 | D64: =ROUND(X63*(1+N('My Debts'!$D$8)/12),2) -> 0 | E64: =ROUND(Y63*(1+N('My Debts'!$D$9)/12),2) -> 0 | F64: =ROUND(Z63*(1+N('My Debts'!$D$10)/12),2) -> 0 | G64: =ROUND(AA63*(1+N('My Debts'!$D$11)/12),2) -> 0 | H64: =ROUND(AB63*(1+N('My Debts'!$D$12)/12),2) -> 0 | I64: =ROUND(AC63*(1+N('My Debts'!$D$13)/12),2) -> 0 | J64: =ROUND(AD63*(1+N('My Debts'!$D$14)/12),2) -> 0 | K64: =ROUND(AE63*(1+N('My Debts'!$D$15)/12),2) -> 0 | L64: =MIN(N('My Debts'!$E$6),B64) -> 0 | M64: =MIN(N('My Debts'!$E$7),C64) -> 0 | N64: =MIN(N('My Debts'!$E$8),D64) -> 0 | O64: =MIN(N('My Debts'!$E$9),E64) -> 0 | P64: =MIN(N('My Debts'!$E$10),F64) -> 0 | Q64: =MIN(N('My Debts'!$E$11),G64) -> 0 | R64: =MIN(N('My Debts'!$E$12),H64) -> 0 | S64: =MIN(N('My Debts'!$E$13),I64) -> 0 | T64: =MIN(N('My Debts'!$E$14),J64) -> 0 | U64: =MIN(N('My Debts'!$E$15),K64) -> 0 | V64: =ROUND(B64-L64-MIN(B64-L64,MAX(0,$AF64-SUMPRODUCT(--($B$4:$K$4<B$4),$B64:$K64-$L64:$U64))),2) -> 0 | W64: =ROUND(C64-M64-MIN(C64-M64,MAX(0,$AF64-SUMPRODUCT(--($B$4:$K$4<C$4),$B64:$K64-$L64:$U64))),2) -> 0 | X64: =ROUND(D64-N64-MIN(D64-N64,MAX(0,$AF64-SUMPRODUCT(--($B$4:$K$4<D$4),$B64:$K64-$L64:$U64))),2) -> 0 | Y64: =ROUND(E64-O64-MIN(E64-O64,MAX(0,$AF64-SUMPRODUCT(--($B$4:$K$4<E$4),$B64:$K64-$L64:$U64))),2) -> 0 | Z64: =ROUND(F64-P64-MIN(F64-P64,MAX(0,$AF64-SUMPRODUCT(--($B$4:$K$4<F$4),$B64:$K64-$L64:$U64))),2) -> 0 | AA64: =ROUND(G64-Q64-MIN(G64-Q64,MAX(0,$AF64-SUMPRODUCT(--($B$4:$K$4<G$4),$B64:$K64-$L64:$U64))),2) -> 0 | AB64: =ROUND(H64-R64-MIN(H64-R64,MAX(0,$AF64-SUMPRODUCT(--($B$4:$K$4<H$4),$B64:$K64-$L64:$U64))),2) -> 0 | AC64: =ROUND(I64-S64-MIN(I64-S64,MAX(0,$AF64-SUMPRODUCT(--($B$4:$K$4<I$4),$B64:$K64-$L64:$U64))),2) -> 0 | ... AE64: =ROUND(K64-U64-MIN(K64-U64,MAX(0,$AF64-SUMPRODUCT(--($B$4:$K$4<K$4),$B64:$K64-$L64:$U64))),2) -> 0 | AF64: =MAX(0,'Start Here'!$C$5-SUM($L64:$U64)) -> 1200 | AG64: =SUM(V64:AE64) -> 0 | AH64: =SUM(B64:K64)-AG63 -> 0
A65: =DATE(YEAR('Start Here'!$C$6),MONTH('Start Here'!$C$6)+58,1) -> 48061 | B65: =ROUND(V64*(1+N('My Debts'!$D$6)/12),2) -> 0 | C65: =ROUND(W64*(1+N('My Debts'!$D$7)/12),2) -> 0 | D65: =ROUND(X64*(1+N('My Debts'!$D$8)/12),2) -> 0 | E65: =ROUND(Y64*(1+N('My Debts'!$D$9)/12),2) -> 0 | F65: =ROUND(Z64*(1+N('My Debts'!$D$10)/12),2) -> 0 | G65: =ROUND(AA64*(1+N('My Debts'!$D$11)/12),2) -> 0 | H65: =ROUND(AB64*(1+N('My Debts'!$D$12)/12),2) -> 0 | I65: =ROUND(AC64*(1+N('My Debts'!$D$13)/12),2) -> 0 | J65: =ROUND(AD64*(1+N('My Debts'!$D$14)/12),2) -> 0 | K65: =ROUND(AE64*(1+N('My Debts'!$D$15)/12),2) -> 0 | L65: =MIN(N('My Debts'!$E$6),B65) -> 0 | M65: =MIN(N('My Debts'!$E$7),C65) -> 0 | N65: =MIN(N('My Debts'!$E$8),D65) -> 0 | O65: =MIN(N('My Debts'!$E$9),E65) -> 0 | P65: =MIN(N('My Debts'!$E$10),F65) -> 0 | Q65: =MIN(N('My Debts'!$E$11),G65) -> 0 | R65: =MIN(N('My Debts'!$E$12),H65) -> 0 | S65: =MIN(N('My Debts'!$E$13),I65) -> 0 | T65: =MIN(N('My Debts'!$E$14),J65) -> 0 | U65: =MIN(N('My Debts'!$E$15),K65) -> 0 | V65: =ROUND(B65-L65-MIN(B65-L65,MAX(0,$AF65-SUMPRODUCT(--($B$4:$K$4<B$4),$B65:$K65-$L65:$U65))),2) -> 0 | W65: =ROUND(C65-M65-MIN(C65-M65,MAX(0,$AF65-SUMPRODUCT(--($B$4:$K$4<C$4),$B65:$K65-$L65:$U65))),2) -> 0 | X65: =ROUND(D65-N65-MIN(D65-N65,MAX(0,$AF65-SUMPRODUCT(--($B$4:$K$4<D$4),$B65:$K65-$L65:$U65))),2) -> 0 | Y65: =ROUND(E65-O65-MIN(E65-O65,MAX(0,$AF65-SUMPRODUCT(--($B$4:$K$4<E$4),$B65:$K65-$L65:$U65))),2) -> 0 | Z65: =ROUND(F65-P65-MIN(F65-P65,MAX(0,$AF65-SUMPRODUCT(--($B$4:$K$4<F$4),$B65:$K65-$L65:$U65))),2) -> 0 | AA65: =ROUND(G65-Q65-MIN(G65-Q65,MAX(0,$AF65-SUMPRODUCT(--($B$4:$K$4<G$4),$B65:$K65-$L65:$U65))),2) -> 0 | AB65: =ROUND(H65-R65-MIN(H65-R65,MAX(0,$AF65-SUMPRODUCT(--($B$4:$K$4<H$4),$B65:$K65-$L65:$U65))),2) -> 0 | AC65: =ROUND(I65-S65-MIN(I65-S65,MAX(0,$AF65-SUMPRODUCT(--($B$4:$K$4<I$4),$B65:$K65-$L65:$U65))),2) -> 0 | ... AE65: =ROUND(K65-U65-MIN(K65-U65,MAX(0,$AF65-SUMPRODUCT(--($B$4:$K$4<K$4),$B65:$K65-$L65:$U65))),2) -> 0 | AF65: =MAX(0,'Start Here'!$C$5-SUM($L65:$U65)) -> 1200 | AG65: =SUM(V65:AE65) -> 0 | AH65: =SUM(B65:K65)-AG64 -> 0
A66: =DATE(YEAR('Start Here'!$C$6),MONTH('Start Here'!$C$6)+59,1) -> 48092 | B66: =ROUND(V65*(1+N('My Debts'!$D$6)/12),2) -> 0 | C66: =ROUND(W65*(1+N('My Debts'!$D$7)/12),2) -> 0 | D66: =ROUND(X65*(1+N('My Debts'!$D$8)/12),2) -> 0 | E66: =ROUND(Y65*(1+N('My Debts'!$D$9)/12),2) -> 0 | F66: =ROUND(Z65*(1+N('My Debts'!$D$10)/12),2) -> 0 | G66: =ROUND(AA65*(1+N('My Debts'!$D$11)/12),2) -> 0 | H66: =ROUND(AB65*(1+N('My Debts'!$D$12)/12),2) -> 0 | I66: =ROUND(AC65*(1+N('My Debts'!$D$13)/12),2) -> 0 | J66: =ROUND(AD65*(1+N('My Debts'!$D$14)/12),2) -> 0 | K66: =ROUND(AE65*(1+N('My Debts'!$D$15)/12),2) -> 0 | L66: =MIN(N('My Debts'!$E$6),B66) -> 0 | M66: =MIN(N('My Debts'!$E$7),C66) -> 0 | N66: =MIN(N('My Debts'!$E$8),D66) -> 0 | O66: =MIN(N('My Debts'!$E$9),E66) -> 0 | P66: =MIN(N('My Debts'!$E$10),F66) -> 0 | Q66: =MIN(N('My Debts'!$E$11),G66) -> 0 | R66: =MIN(N('My Debts'!$E$12),H66) -> 0 | S66: =MIN(N('My Debts'!$E$13),I66) -> 0 | T66: =MIN(N('My Debts'!$E$14),J66) -> 0 | U66: =MIN(N('My Debts'!$E$15),K66) -> 0 | V66: =ROUND(B66-L66-MIN(B66-L66,MAX(0,$AF66-SUMPRODUCT(--($B$4:$K$4<B$4),$B66:$K66-$L66:$U66))),2) -> 0 | W66: =ROUND(C66-M66-MIN(C66-M66,MAX(0,$AF66-SUMPRODUCT(--($B$4:$K$4<C$4),$B66:$K66-$L66:$U66))),2) -> 0 | X66: =ROUND(D66-N66-MIN(D66-N66,MAX(0,$AF66-SUMPRODUCT(--($B$4:$K$4<D$4),$B66:$K66-$L66:$U66))),2) -> 0 | Y66: =ROUND(E66-O66-MIN(E66-O66,MAX(0,$AF66-SUMPRODUCT(--($B$4:$K$4<E$4),$B66:$K66-$L66:$U66))),2) -> 0 | Z66: =ROUND(F66-P66-MIN(F66-P66,MAX(0,$AF66-SUMPRODUCT(--($B$4:$K$4<F$4),$B66:$K66-$L66:$U66))),2) -> 0 | AA66: =ROUND(G66-Q66-MIN(G66-Q66,MAX(0,$AF66-SUMPRODUCT(--($B$4:$K$4<G$4),$B66:$K66-$L66:$U66))),2) -> 0 | AB66: =ROUND(H66-R66-MIN(H66-R66,MAX(0,$AF66-SUMPRODUCT(--($B$4:$K$4<H$4),$B66:$K66-$L66:$U66))),2) -> 0 | AC66: =ROUND(I66-S66-MIN(I66-S66,MAX(0,$AF66-SUMPRODUCT(--($B$4:$K$4<I$4),$B66:$K66-$L66:$U66))),2) -> 0 | ... AE66: =ROUND(K66-U66-MIN(K66-U66,MAX(0,$AF66-SUMPRODUCT(--($B$4:$K$4<K$4),$B66:$K66-$L66:$U66))),2) -> 0 | AF66: =MAX(0,'Start Here'!$C$5-SUM($L66:$U66)) -> 1200 | AG66: =SUM(V66:AE66) -> 0 | AH66: =SUM(B66:K66)-AG65 -> 0
A67: =DATE(YEAR('Start Here'!$C$6),MONTH('Start Here'!$C$6)+60,1) -> 48122 | B67: =ROUND(V66*(1+N('My Debts'!$D$6)/12),2) -> 0 | C67: =ROUND(W66*(1+N('My Debts'!$D$7)/12),2) -> 0 | D67: =ROUND(X66*(1+N('My Debts'!$D$8)/12),2) -> 0 | E67: =ROUND(Y66*(1+N('My Debts'!$D$9)/12),2) -> 0 | F67: =ROUND(Z66*(1+N('My Debts'!$D$10)/12),2) -> 0 | G67: =ROUND(AA66*(1+N('My Debts'!$D$11)/12),2) -> 0 | H67: =ROUND(AB66*(1+N('My Debts'!$D$12)/12),2) -> 0 | I67: =ROUND(AC66*(1+N('My Debts'!$D$13)/12),2) -> 0 | J67: =ROUND(AD66*(1+N('My Debts'!$D$14)/12),2) -> 0 | K67: =ROUND(AE66*(1+N('My Debts'!$D$15)/12),2) -> 0 | L67: =MIN(N('My Debts'!$E$6),B67) -> 0 | M67: =MIN(N('My Debts'!$E$7),C67) -> 0 | N67: =MIN(N('My Debts'!$E$8),D67) -> 0 | O67: =MIN(N('My Debts'!$E$9),E67) -> 0 | P67: =MIN(N('My Debts'!$E$10),F67) -> 0 | Q67: =MIN(N('My Debts'!$E$11),G67) -> 0 | R67: =MIN(N('My Debts'!$E$12),H67) -> 0 | S67: =MIN(N('My Debts'!$E$13),I67) -> 0 | T67: =MIN(N('My Debts'!$E$14),J67) -> 0 | U67: =MIN(N('My Debts'!$E$15),K67) -> 0 | V67: =ROUND(B67-L67-MIN(B67-L67,MAX(0,$AF67-SUMPRODUCT(--($B$4:$K$4<B$4),$B67:$K67-$L67:$U67))),2) -> 0 | W67: =ROUND(C67-M67-MIN(C67-M67,MAX(0,$AF67-SUMPRODUCT(--($B$4:$K$4<C$4),$B67:$K67-$L67:$U67))),2) -> 0 | X67: =ROUND(D67-N67-MIN(D67-N67,MAX(0,$AF67-SUMPRODUCT(--($B$4:$K$4<D$4),$B67:$K67-$L67:$U67))),2) -> 0 | Y67: =ROUND(E67-O67-MIN(E67-O67,MAX(0,$AF67-SUMPRODUCT(--($B$4:$K$4<E$4),$B67:$K67-$L67:$U67))),2) -> 0 | Z67: =ROUND(F67-P67-MIN(F67-P67,MAX(0,$AF67-SUMPRODUCT(--($B$4:$K$4<F$4),$B67:$K67-$L67:$U67))),2) -> 0 | AA67: =ROUND(G67-Q67-MIN(G67-Q67,MAX(0,$AF67-SUMPRODUCT(--($B$4:$K$4<G$4),$B67:$K67-$L67:$U67))),2) -> 0 | AB67: =ROUND(H67-R67-MIN(H67-R67,MAX(0,$AF67-SUMPRODUCT(--($B$4:$K$4<H$4),$B67:$K67-$L67:$U67))),2) -> 0 | AC67: =ROUND(I67-S67-MIN(I67-S67,MAX(0,$AF67-SUMPRODUCT(--($B$4:$K$4<I$4),$B67:$K67-$L67:$U67))),2) -> 0 | ... AE67: =ROUND(K67-U67-MIN(K67-U67,MAX(0,$AF67-SUMPRODUCT(--($B$4:$K$4<K$4),$B67:$K67-$L67:$U67))),2) -> 0 | AF67: =MAX(0,'Start Here'!$C$5-SUM($L67:$U67)) -> 1200 | AG67: =SUM(V67:AE67) -> 0 | AH67: =SUM(B67:K67)-AG66 -> 0
A68: =DATE(YEAR('Start Here'!$C$6),MONTH('Start Here'!$C$6)+61,1) -> 48153 | B68: =ROUND(V67*(1+N('My Debts'!$D$6)/12),2) -> 0 | C68: =ROUND(W67*(1+N('My Debts'!$D$7)/12),2) -> 0 | D68: =ROUND(X67*(1+N('My Debts'!$D$8)/12),2) -> 0 | E68: =ROUND(Y67*(1+N('My Debts'!$D$9)/12),2) -> 0 | F68: =ROUND(Z67*(1+N('My Debts'!$D$10)/12),2) -> 0 | G68: =ROUND(AA67*(1+N('My Debts'!$D$11)/12),2) -> 0 | H68: =ROUND(AB67*(1+N('My Debts'!$D$12)/12),2) -> 0 | I68: =ROUND(AC67*(1+N('My Debts'!$D$13)/12),2) -> 0 | J68: =ROUND(AD67*(1+N('My Debts'!$D$14)/12),2) -> 0 | K68: =ROUND(AE67*(1+N('My Debts'!$D$15)/12),2) -> 0 | L68: =MIN(N('My Debts'!$E$6),B68) -> 0 | M68: =MIN(N('My Debts'!$E$7),C68) -> 0 | N68: =MIN(N('My Debts'!$E$8),D68) -> 0 | O68: =MIN(N('My Debts'!$E$9),E68) -> 0 | P68: =MIN(N('My Debts'!$E$10),F68) -> 0 | Q68: =MIN(N('My Debts'!$E$11),G68) -> 0 | R68: =MIN(N('My Debts'!$E$12),H68) -> 0 | S68: =MIN(N('My Debts'!$E$13),I68) -> 0 | T68: =MIN(N('My Debts'!$E$14),J68) -> 0 | U68: =MIN(N('My Debts'!$E$15),K68) -> 0 | V68: =ROUND(B68-L68-MIN(B68-L68,MAX(0,$AF68-SUMPRODUCT(--($B$4:$K$4<B$4),$B68:$K68-$L68:$U68))),2) -> 0 | W68: =ROUND(C68-M68-MIN(C68-M68,MAX(0,$AF68-SUMPRODUCT(--($B$4:$K$4<C$4),$B68:$K68-$L68:$U68))),2) -> 0 | X68: =ROUND(D68-N68-MIN(D68-N68,MAX(0,$AF68-SUMPRODUCT(--($B$4:$K$4<D$4),$B68:$K68-$L68:$U68))),2) -> 0 | Y68: =ROUND(E68-O68-MIN(E68-O68,MAX(0,$AF68-SUMPRODUCT(--($B$4:$K$4<E$4),$B68:$K68-$L68:$U68))),2) -> 0 | Z68: =ROUND(F68-P68-MIN(F68-P68,MAX(0,$AF68-SUMPRODUCT(--($B$4:$K$4<F$4),$B68:$K68-$L68:$U68))),2) -> 0 | AA68: =ROUND(G68-Q68-MIN(G68-Q68,MAX(0,$AF68-SUMPRODUCT(--($B$4:$K$4<G$4),$B68:$K68-$L68:$U68))),2) -> 0 | AB68: =ROUND(H68-R68-MIN(H68-R68,MAX(0,$AF68-SUMPRODUCT(--($B$4:$K$4<H$4),$B68:$K68-$L68:$U68))),2) -> 0 | AC68: =ROUND(I68-S68-MIN(I68-S68,MAX(0,$AF68-SUMPRODUCT(--($B$4:$K$4<I$4),$B68:$K68-$L68:$U68))),2) -> 0 | ... AE68: =ROUND(K68-U68-MIN(K68-U68,MAX(0,$AF68-SUMPRODUCT(--($B$4:$K$4<K$4),$B68:$K68-$L68:$U68))),2) -> 0 | AF68: =MAX(0,'Start Here'!$C$5-SUM($L68:$U68)) -> 1200 | AG68: =SUM(V68:AE68) -> 0 | AH68: =SUM(B68:K68)-AG67 -> 0
A69: =DATE(YEAR('Start Here'!$C$6),MONTH('Start Here'!$C$6)+62,1) -> 48183 | B69: =ROUND(V68*(1+N('My Debts'!$D$6)/12),2) -> 0 | C69: =ROUND(W68*(1+N('My Debts'!$D$7)/12),2) -> 0 | D69: =ROUND(X68*(1+N('My Debts'!$D$8)/12),2) -> 0 | E69: =ROUND(Y68*(1+N('My Debts'!$D$9)/12),2) -> 0 | F69: =ROUND(Z68*(1+N('My Debts'!$D$10)/12),2) -> 0 | G69: =ROUND(AA68*(1+N('My Debts'!$D$11)/12),2) -> 0 | H69: =ROUND(AB68*(1+N('My Debts'!$D$12)/12),2) -> 0 | I69: =ROUND(AC68*(1+N('My Debts'!$D$13)/12),2) -> 0 | J69: =ROUND(AD68*(1+N('My Debts'!$D$14)/12),2) -> 0 | K69: =ROUND(AE68*(1+N('My Debts'!$D$15)/12),2) -> 0 | L69: =MIN(N('My Debts'!$E$6),B69) -> 0 | M69: =MIN(N('My Debts'!$E$7),C69) -> 0 | N69: =MIN(N('My Debts'!$E$8),D69) -> 0 | O69: =MIN(N('My Debts'!$E$9),E69) -> 0 | P69: =MIN(N('My Debts'!$E$10),F69) -> 0 | Q69: =MIN(N('My Debts'!$E$11),G69) -> 0 | R69: =MIN(N('My Debts'!$E$12),H69) -> 0 | S69: =MIN(N('My Debts'!$E$13),I69) -> 0 | T69: =MIN(N('My Debts'!$E$14),J69) -> 0 | U69: =MIN(N('My Debts'!$E$15),K69) -> 0 | V69: =ROUND(B69-L69-MIN(B69-L69,MAX(0,$AF69-SUMPRODUCT(--($B$4:$K$4<B$4),$B69:$K69-$L69:$U69))),2) -> 0 | W69: =ROUND(C69-M69-MIN(C69-M69,MAX(0,$AF69-SUMPRODUCT(--($B$4:$K$4<C$4),$B69:$K69-$L69:$U69))),2) -> 0 | X69: =ROUND(D69-N69-MIN(D69-N69,MAX(0,$AF69-SUMPRODUCT(--($B$4:$K$4<D$4),$B69:$K69-$L69:$U69))),2) -> 0 | Y69: =ROUND(E69-O69-MIN(E69-O69,MAX(0,$AF69-SUMPRODUCT(--($B$4:$K$4<E$4),$B69:$K69-$L69:$U69))),2) -> 0 | Z69: =ROUND(F69-P69-MIN(F69-P69,MAX(0,$AF69-SUMPRODUCT(--($B$4:$K$4<F$4),$B69:$K69-$L69:$U69))),2) -> 0 | AA69: =ROUND(G69-Q69-MIN(G69-Q69,MAX(0,$AF69-SUMPRODUCT(--($B$4:$K$4<G$4),$B69:$K69-$L69:$U69))),2) -> 0 | AB69: =ROUND(H69-R69-MIN(H69-R69,MAX(0,$AF69-SUMPRODUCT(--($B$4:$K$4<H$4),$B69:$K69-$L69:$U69))),2) -> 0 | AC69: =ROUND(I69-S69-MIN(I69-S69,MAX(0,$AF69-SUMPRODUCT(--($B$4:$K$4<I$4),$B69:$K69-$L69:$U69))),2) -> 0 | ... AE69: =ROUND(K69-U69-MIN(K69-U69,MAX(0,$AF69-SUMPRODUCT(--($B$4:$K$4<K$4),$B69:$K69-$L69:$U69))),2) -> 0 | AF69: =MAX(0,'Start Here'!$C$5-SUM($L69:$U69)) -> 1200 | AG69: =SUM(V69:AE69) -> 0 | AH69: =SUM(B69:K69)-AG68 -> 0
A70: =DATE(YEAR('Start Here'!$C$6),MONTH('Start Here'!$C$6)+63,1) -> 48214 | B70: =ROUND(V69*(1+N('My Debts'!$D$6)/12),2) -> 0 | C70: =ROUND(W69*(1+N('My Debts'!$D$7)/12),2) -> 0 | D70: =ROUND(X69*(1+N('My Debts'!$D$8)/12),2) -> 0 | E70: =ROUND(Y69*(1+N('My Debts'!$D$9)/12),2) -> 0 | F70: =ROUND(Z69*(1+N('My Debts'!$D$10)/12),2) -> 0 | G70: =ROUND(AA69*(1+N('My Debts'!$D$11)/12),2) -> 0 | H70: =ROUND(AB69*(1+N('My Debts'!$D$12)/12),2) -> 0 | I70: =ROUND(AC69*(1+N('My Debts'!$D$13)/12),2) -> 0 | J70: =ROUND(AD69*(1+N('My Debts'!$D$14)/12),2) -> 0 | K70: =ROUND(AE69*(1+N('My Debts'!$D$15)/12),2) -> 0 | L70: =MIN(N('My Debts'!$E$6),B70) -> 0 | M70: =MIN(N('My Debts'!$E$7),C70) -> 0 | N70: =MIN(N('My Debts'!$E$8),D70) -> 0 | O70: =MIN(N('My Debts'!$E$9),E70) -> 0 | P70: =MIN(N('My Debts'!$E$10),F70) -> 0 | Q70: =MIN(N('My Debts'!$E$11),G70) -> 0 | R70: =MIN(N('My Debts'!$E$12),H70) -> 0 | S70: =MIN(N('My Debts'!$E$13),I70) -> 0 | T70: =MIN(N('My Debts'!$E$14),J70) -> 0 | U70: =MIN(N('My Debts'!$E$15),K70) -> 0 | V70: =ROUND(B70-L70-MIN(B70-L70,MAX(0,$AF70-SUMPRODUCT(--($B$4:$K$4<B$4),$B70:$K70-$L70:$U70))),2) -> 0 | W70: =ROUND(C70-M70-MIN(C70-M70,MAX(0,$AF70-SUMPRODUCT(--($B$4:$K$4<C$4),$B70:$K70-$L70:$U70))),2) -> 0 | X70: =ROUND(D70-N70-MIN(D70-N70,MAX(0,$AF70-SUMPRODUCT(--($B$4:$K$4<D$4),$B70:$K70-$L70:$U70))),2) -> 0 | Y70: =ROUND(E70-O70-MIN(E70-O70,MAX(0,$AF70-SUMPRODUCT(--($B$4:$K$4<E$4),$B70:$K70-$L70:$U70))),2) -> 0 | Z70: =ROUND(F70-P70-MIN(F70-P70,MAX(0,$AF70-SUMPRODUCT(--($B$4:$K$4<F$4),$B70:$K70-$L70:$U70))),2) -> 0 | AA70: =ROUND(G70-Q70-MIN(G70-Q70,MAX(0,$AF70-SUMPRODUCT(--($B$4:$K$4<G$4),$B70:$K70-$L70:$U70))),2) -> 0 | AB70: =ROUND(H70-R70-MIN(H70-R70,MAX(0,$AF70-SUMPRODUCT(--($B$4:$K$4<H$4),$B70:$K70-$L70:$U70))),2) -> 0 | AC70: =ROUND(I70-S70-MIN(I70-S70,MAX(0,$AF70-SUMPRODUCT(--($B$4:$K$4<I$4),$B70:$K70-$L70:$U70))),2) -> 0 | ... AE70: =ROUND(K70-U70-MIN(K70-U70,MAX(0,$AF70-SUMPRODUCT(--($B$4:$K$4<K$4),$B70:$K70-$L70:$U70))),2) -> 0 | AF70: =MAX(0,'Start Here'!$C$5-SUM($L70:$U70)) -> 1200 | AG70: =SUM(V70:AE70) -> 0 | AH70: =SUM(B70:K70)-AG69 -> 0
A71: =DATE(YEAR('Start Here'!$C$6),MONTH('Start Here'!$C$6)+64,1) -> 48245 | B71: =ROUND(V70*(1+N('My Debts'!$D$6)/12),2) -> 0 | C71: =ROUND(W70*(1+N('My Debts'!$D$7)/12),2) -> 0 | D71: =ROUND(X70*(1+N('My Debts'!$D$8)/12),2) -> 0 | E71: =ROUND(Y70*(1+N('My Debts'!$D$9)/12),2) -> 0 | F71: =ROUND(Z70*(1+N('My Debts'!$D$10)/12),2) -> 0 | G71: =ROUND(AA70*(1+N('My Debts'!$D$11)/12),2) -> 0 | H71: =ROUND(AB70*(1+N('My Debts'!$D$12)/12),2) -> 0 | I71: =ROUND(AC70*(1+N('My Debts'!$D$13)/12),2) -> 0 | J71: =ROUND(AD70*(1+N('My Debts'!$D$14)/12),2) -> 0 | K71: =ROUND(AE70*(1+N('My Debts'!$D$15)/12),2) -> 0 | L71: =MIN(N('My Debts'!$E$6),B71) -> 0 | M71: =MIN(N('My Debts'!$E$7),C71) -> 0 | N71: =MIN(N('My Debts'!$E$8),D71) -> 0 | O71: =MIN(N('My Debts'!$E$9),E71) -> 0 | P71: =MIN(N('My Debts'!$E$10),F71) -> 0 | Q71: =MIN(N('My Debts'!$E$11),G71) -> 0 | R71: =MIN(N('My Debts'!$E$12),H71) -> 0 | S71: =MIN(N('My Debts'!$E$13),I71) -> 0 | T71: =MIN(N('My Debts'!$E$14),J71) -> 0 | U71: =MIN(N('My Debts'!$E$15),K71) -> 0 | V71: =ROUND(B71-L71-MIN(B71-L71,MAX(0,$AF71-SUMPRODUCT(--($B$4:$K$4<B$4),$B71:$K71-$L71:$U71))),2) -> 0 | W71: =ROUND(C71-M71-MIN(C71-M71,MAX(0,$AF71-SUMPRODUCT(--($B$4:$K$4<C$4),$B71:$K71-$L71:$U71))),2) -> 0 | X71: =ROUND(D71-N71-MIN(D71-N71,MAX(0,$AF71-SUMPRODUCT(--($B$4:$K$4<D$4),$B71:$K71-$L71:$U71))),2) -> 0 | Y71: =ROUND(E71-O71-MIN(E71-O71,MAX(0,$AF71-SUMPRODUCT(--($B$4:$K$4<E$4),$B71:$K71-$L71:$U71))),2) -> 0 | Z71: =ROUND(F71-P71-MIN(F71-P71,MAX(0,$AF71-SUMPRODUCT(--($B$4:$K$4<F$4),$B71:$K71-$L71:$U71))),2) -> 0 | AA71: =ROUND(G71-Q71-MIN(G71-Q71,MAX(0,$AF71-SUMPRODUCT(--($B$4:$K$4<G$4),$B71:$K71-$L71:$U71))),2) -> 0 | AB71: =ROUND(H71-R71-MIN(H71-R71,MAX(0,$AF71-SUMPRODUCT(--($B$4:$K$4<H$4),$B71:$K71-$L71:$U71))),2) -> 0 | AC71: =ROUND(I71-S71-MIN(I71-S71,MAX(0,$AF71-SUMPRODUCT(--($B$4:$K$4<I$4),$B71:$K71-$L71:$U71))),2) -> 0 | ... AE71: =ROUND(K71-U71-MIN(K71-U71,MAX(0,$AF71-SUMPRODUCT(--($B$4:$K$4<K$4),$B71:$K71-$L71:$U71))),2) -> 0 | AF71: =MAX(0,'Start Here'!$C$5-SUM($L71:$U71)) -> 1200 | AG71: =SUM(V71:AE71) -> 0 | AH71: =SUM(B71:K71)-AG70 -> 0
A72: =DATE(YEAR('Start Here'!$C$6),MONTH('Start Here'!$C$6)+65,1) -> 48274 | B72: =ROUND(V71*(1+N('My Debts'!$D$6)/12),2) -> 0 | C72: =ROUND(W71*(1+N('My Debts'!$D$7)/12),2) -> 0 | D72: =ROUND(X71*(1+N('My Debts'!$D$8)/12),2) -> 0 | E72: =ROUND(Y71*(1+N('My Debts'!$D$9)/12),2) -> 0 | F72: =ROUND(Z71*(1+N('My Debts'!$D$10)/12),2) -> 0 | G72: =ROUND(AA71*(1+N('My Debts'!$D$11)/12),2) -> 0 | H72: =ROUND(AB71*(1+N('My Debts'!$D$12)/12),2) -> 0 | I72: =ROUND(AC71*(1+N('My Debts'!$D$13)/12),2) -> 0 | J72: =ROUND(AD71*(1+N('My Debts'!$D$14)/12),2) -> 0 | K72: =ROUND(AE71*(1+N('My Debts'!$D$15)/12),2) -> 0 | L72: =MIN(N('My Debts'!$E$6),B72) -> 0 | M72: =MIN(N('My Debts'!$E$7),C72) -> 0 | N72: =MIN(N('My Debts'!$E$8),D72) -> 0 | O72: =MIN(N('My Debts'!$E$9),E72) -> 0 | P72: =MIN(N('My Debts'!$E$10),F72) -> 0 | Q72: =MIN(N('My Debts'!$E$11),G72) -> 0 | R72: =MIN(N('My Debts'!$E$12),H72) -> 0 | S72: =MIN(N('My Debts'!$E$13),I72) -> 0 | T72: =MIN(N('My Debts'!$E$14),J72) -> 0 | U72: =MIN(N('My Debts'!$E$15),K72) -> 0 | V72: =ROUND(B72-L72-MIN(B72-L72,MAX(0,$AF72-SUMPRODUCT(--($B$4:$K$4<B$4),$B72:$K72-$L72:$U72))),2) -> 0 | W72: =ROUND(C72-M72-MIN(C72-M72,MAX(0,$AF72-SUMPRODUCT(--($B$4:$K$4<C$4),$B72:$K72-$L72:$U72))),2) -> 0 | X72: =ROUND(D72-N72-MIN(D72-N72,MAX(0,$AF72-SUMPRODUCT(--($B$4:$K$4<D$4),$B72:$K72-$L72:$U72))),2) -> 0 | Y72: =ROUND(E72-O72-MIN(E72-O72,MAX(0,$AF72-SUMPRODUCT(--($B$4:$K$4<E$4),$B72:$K72-$L72:$U72))),2) -> 0 | Z72: =ROUND(F72-P72-MIN(F72-P72,MAX(0,$AF72-SUMPRODUCT(--($B$4:$K$4<F$4),$B72:$K72-$L72:$U72))),2) -> 0 | AA72: =ROUND(G72-Q72-MIN(G72-Q72,MAX(0,$AF72-SUMPRODUCT(--($B$4:$K$4<G$4),$B72:$K72-$L72:$U72))),2) -> 0 | AB72: =ROUND(H72-R72-MIN(H72-R72,MAX(0,$AF72-SUMPRODUCT(--($B$4:$K$4<H$4),$B72:$K72-$L72:$U72))),2) -> 0 | AC72: =ROUND(I72-S72-MIN(I72-S72,MAX(0,$AF72-SUMPRODUCT(--($B$4:$K$4<I$4),$B72:$K72-$L72:$U72))),2) -> 0 | ... AE72: =ROUND(K72-U72-MIN(K72-U72,MAX(0,$AF72-SUMPRODUCT(--($B$4:$K$4<K$4),$B72:$K72-$L72:$U72))),2) -> 0 | AF72: =MAX(0,'Start Here'!$C$5-SUM($L72:$U72)) -> 1200 | AG72: =SUM(V72:AE72) -> 0 | AH72: =SUM(B72:K72)-AG71 -> 0
A73: =DATE(YEAR('Start Here'!$C$6),MONTH('Start Here'!$C$6)+66,1) -> 48305 | B73: =ROUND(V72*(1+N('My Debts'!$D$6)/12),2) -> 0 | C73: =ROUND(W72*(1+N('My Debts'!$D$7)/12),2) -> 0 | D73: =ROUND(X72*(1+N('My Debts'!$D$8)/12),2) -> 0 | E73: =ROUND(Y72*(1+N('My Debts'!$D$9)/12),2) -> 0 | F73: =ROUND(Z72*(1+N('My Debts'!$D$10)/12),2) -> 0 | G73: =ROUND(AA72*(1+N('My Debts'!$D$11)/12),2) -> 0 | H73: =ROUND(AB72*(1+N('My Debts'!$D$12)/12),2) -> 0 | I73: =ROUND(AC72*(1+N('My Debts'!$D$13)/12),2) -> 0 | J73: =ROUND(AD72*(1+N('My Debts'!$D$14)/12),2) -> 0 | K73: =ROUND(AE72*(1+N('My Debts'!$D$15)/12),2) -> 0 | L73: =MIN(N('My Debts'!$E$6),B73) -> 0 | M73: =MIN(N('My Debts'!$E$7),C73) -> 0 | N73: =MIN(N('My Debts'!$E$8),D73) -> 0 | O73: =MIN(N('My Debts'!$E$9),E73) -> 0 | P73: =MIN(N('My Debts'!$E$10),F73) -> 0 | Q73: =MIN(N('My Debts'!$E$11),G73) -> 0 | R73: =MIN(N('My Debts'!$E$12),H73) -> 0 | S73: =MIN(N('My Debts'!$E$13),I73) -> 0 | T73: =MIN(N('My Debts'!$E$14),J73) -> 0 | U73: =MIN(N('My Debts'!$E$15),K73) -> 0 | V73: =ROUND(B73-L73-MIN(B73-L73,MAX(0,$AF73-SUMPRODUCT(--($B$4:$K$4<B$4),$B73:$K73-$L73:$U73))),2) -> 0 | W73: =ROUND(C73-M73-MIN(C73-M73,MAX(0,$AF73-SUMPRODUCT(--($B$4:$K$4<C$4),$B73:$K73-$L73:$U73))),2) -> 0 | X73: =ROUND(D73-N73-MIN(D73-N73,MAX(0,$AF73-SUMPRODUCT(--($B$4:$K$4<D$4),$B73:$K73-$L73:$U73))),2) -> 0 | Y73: =ROUND(E73-O73-MIN(E73-O73,MAX(0,$AF73-SUMPRODUCT(--($B$4:$K$4<E$4),$B73:$K73-$L73:$U73))),2) -> 0 | Z73: =ROUND(F73-P73-MIN(F73-P73,MAX(0,$AF73-SUMPRODUCT(--($B$4:$K$4<F$4),$B73:$K73-$L73:$U73))),2) -> 0 | AA73: =ROUND(G73-Q73-MIN(G73-Q73,MAX(0,$AF73-SUMPRODUCT(--($B$4:$K$4<G$4),$B73:$K73-$L73:$U73))),2) -> 0 | AB73: =ROUND(H73-R73-MIN(H73-R73,MAX(0,$AF73-SUMPRODUCT(--($B$4:$K$4<H$4),$B73:$K73-$L73:$U73))),2) -> 0 | AC73: =ROUND(I73-S73-MIN(I73-S73,MAX(0,$AF73-SUMPRODUCT(--($B$4:$K$4<I$4),$B73:$K73-$L73:$U73))),2) -> 0 | ... AE73: =ROUND(K73-U73-MIN(K73-U73,MAX(0,$AF73-SUMPRODUCT(--($B$4:$K$4<K$4),$B73:$K73-$L73:$U73))),2) -> 0 | AF73: =MAX(0,'Start Here'!$C$5-SUM($L73:$U73)) -> 1200 | AG73: =SUM(V73:AE73) -> 0 | AH73: =SUM(B73:K73)-AG72 -> 0
A74: =DATE(YEAR('Start Here'!$C$6),MONTH('Start Here'!$C$6)+67,1) -> 48335 | B74: =ROUND(V73*(1+N('My Debts'!$D$6)/12),2) -> 0 | C74: =ROUND(W73*(1+N('My Debts'!$D$7)/12),2) -> 0 | D74: =ROUND(X73*(1+N('My Debts'!$D$8)/12),2) -> 0 | E74: =ROUND(Y73*(1+N('My Debts'!$D$9)/12),2) -> 0 | F74: =ROUND(Z73*(1+N('My Debts'!$D$10)/12),2) -> 0 | G74: =ROUND(AA73*(1+N('My Debts'!$D$11)/12),2) -> 0 | H74: =ROUND(AB73*(1+N('My Debts'!$D$12)/12),2) -> 0 | I74: =ROUND(AC73*(1+N('My Debts'!$D$13)/12),2) -> 0 | J74: =ROUND(AD73*(1+N('My Debts'!$D$14)/12),2) -> 0 | K74: =ROUND(AE73*(1+N('My Debts'!$D$15)/12),2) -> 0 | L74: =MIN(N('My Debts'!$E$6),B74) -> 0 | M74: =MIN(N('My Debts'!$E$7),C74) -> 0 | N74: =MIN(N('My Debts'!$E$8),D74) -> 0 | O74: =MIN(N('My Debts'!$E$9),E74) -> 0 | P74: =MIN(N('My Debts'!$E$10),F74) -> 0 | Q74: =MIN(N('My Debts'!$E$11),G74) -> 0 | R74: =MIN(N('My Debts'!$E$12),H74) -> 0 | S74: =MIN(N('My Debts'!$E$13),I74) -> 0 | T74: =MIN(N('My Debts'!$E$14),J74) -> 0 | U74: =MIN(N('My Debts'!$E$15),K74) -> 0 | V74: =ROUND(B74-L74-MIN(B74-L74,MAX(0,$AF74-SUMPRODUCT(--($B$4:$K$4<B$4),$B74:$K74-$L74:$U74))),2) -> 0 | W74: =ROUND(C74-M74-MIN(C74-M74,MAX(0,$AF74-SUMPRODUCT(--($B$4:$K$4<C$4),$B74:$K74-$L74:$U74))),2) -> 0 | X74: =ROUND(D74-N74-MIN(D74-N74,MAX(0,$AF74-SUMPRODUCT(--($B$4:$K$4<D$4),$B74:$K74-$L74:$U74))),2) -> 0 | Y74: =ROUND(E74-O74-MIN(E74-O74,MAX(0,$AF74-SUMPRODUCT(--($B$4:$K$4<E$4),$B74:$K74-$L74:$U74))),2) -> 0 | Z74: =ROUND(F74-P74-MIN(F74-P74,MAX(0,$AF74-SUMPRODUCT(--($B$4:$K$4<F$4),$B74:$K74-$L74:$U74))),2) -> 0 | AA74: =ROUND(G74-Q74-MIN(G74-Q74,MAX(0,$AF74-SUMPRODUCT(--($B$4:$K$4<G$4),$B74:$K74-$L74:$U74))),2) -> 0 | AB74: =ROUND(H74-R74-MIN(H74-R74,MAX(0,$AF74-SUMPRODUCT(--($B$4:$K$4<H$4),$B74:$K74-$L74:$U74))),2) -> 0 | AC74: =ROUND(I74-S74-MIN(I74-S74,MAX(0,$AF74-SUMPRODUCT(--($B$4:$K$4<I$4),$B74:$K74-$L74:$U74))),2) -> 0 | ... AE74: =ROUND(K74-U74-MIN(K74-U74,MAX(0,$AF74-SUMPRODUCT(--($B$4:$K$4<K$4),$B74:$K74-$L74:$U74))),2) -> 0 | AF74: =MAX(0,'Start Here'!$C$5-SUM($L74:$U74)) -> 1200 | AG74: =SUM(V74:AE74) -> 0 | AH74: =SUM(B74:K74)-AG73 -> 0
A75: =DATE(YEAR('Start Here'!$C$6),MONTH('Start Here'!$C$6)+68,1) -> 48366 | B75: =ROUND(V74*(1+N('My Debts'!$D$6)/12),2) -> 0 | C75: =ROUND(W74*(1+N('My Debts'!$D$7)/12),2) -> 0 | D75: =ROUND(X74*(1+N('My Debts'!$D$8)/12),2) -> 0 | E75: =ROUND(Y74*(1+N('My Debts'!$D$9)/12),2) -> 0 | F75: =ROUND(Z74*(1+N('My Debts'!$D$10)/12),2) -> 0 | G75: =ROUND(AA74*(1+N('My Debts'!$D$11)/12),2) -> 0 | H75: =ROUND(AB74*(1+N('My Debts'!$D$12)/12),2) -> 0 | I75: =ROUND(AC74*(1+N('My Debts'!$D$13)/12),2) -> 0 | J75: =ROUND(AD74*(1+N('My Debts'!$D$14)/12),2) -> 0 | K75: =ROUND(AE74*(1+N('My Debts'!$D$15)/12),2) -> 0 | L75: =MIN(N('My Debts'!$E$6),B75) -> 0 | M75: =MIN(N('My Debts'!$E$7),C75) -> 0 | N75: =MIN(N('My Debts'!$E$8),D75) -> 0 | O75: =MIN(N('My Debts'!$E$9),E75) -> 0 | P75: =MIN(N('My Debts'!$E$10),F75) -> 0 | Q75: =MIN(N('My Debts'!$E$11),G75) -> 0 | R75: =MIN(N('My Debts'!$E$12),H75) -> 0 | S75: =MIN(N('My Debts'!$E$13),I75) -> 0 | T75: =MIN(N('My Debts'!$E$14),J75) -> 0 | U75: =MIN(N('My Debts'!$E$15),K75) -> 0 | V75: =ROUND(B75-L75-MIN(B75-L75,MAX(0,$AF75-SUMPRODUCT(--($B$4:$K$4<B$4),$B75:$K75-$L75:$U75))),2) -> 0 | W75: =ROUND(C75-M75-MIN(C75-M75,MAX(0,$AF75-SUMPRODUCT(--($B$4:$K$4<C$4),$B75:$K75-$L75:$U75))),2) -> 0 | X75: =ROUND(D75-N75-MIN(D75-N75,MAX(0,$AF75-SUMPRODUCT(--($B$4:$K$4<D$4),$B75:$K75-$L75:$U75))),2) -> 0 | Y75: =ROUND(E75-O75-MIN(E75-O75,MAX(0,$AF75-SUMPRODUCT(--($B$4:$K$4<E$4),$B75:$K75-$L75:$U75))),2) -> 0 | Z75: =ROUND(F75-P75-MIN(F75-P75,MAX(0,$AF75-SUMPRODUCT(--($B$4:$K$4<F$4),$B75:$K75-$L75:$U75))),2) -> 0 | AA75: =ROUND(G75-Q75-MIN(G75-Q75,MAX(0,$AF75-SUMPRODUCT(--($B$4:$K$4<G$4),$B75:$K75-$L75:$U75))),2) -> 0 | AB75: =ROUND(H75-R75-MIN(H75-R75,MAX(0,$AF75-SUMPRODUCT(--($B$4:$K$4<H$4),$B75:$K75-$L75:$U75))),2) -> 0 | AC75: =ROUND(I75-S75-MIN(I75-S75,MAX(0,$AF75-SUMPRODUCT(--($B$4:$K$4<I$4),$B75:$K75-$L75:$U75))),2) -> 0 | ... AE75: =ROUND(K75-U75-MIN(K75-U75,MAX(0,$AF75-SUMPRODUCT(--($B$4:$K$4<K$4),$B75:$K75-$L75:$U75))),2) -> 0 | AF75: =MAX(0,'Start Here'!$C$5-SUM($L75:$U75)) -> 1200 | AG75: =SUM(V75:AE75) -> 0 | AH75: =SUM(B75:K75)-AG74 -> 0
A76: =DATE(YEAR('Start Here'!$C$6),MONTH('Start Here'!$C$6)+69,1) -> 48396 | B76: =ROUND(V75*(1+N('My Debts'!$D$6)/12),2) -> 0 | C76: =ROUND(W75*(1+N('My Debts'!$D$7)/12),2) -> 0 | D76: =ROUND(X75*(1+N('My Debts'!$D$8)/12),2) -> 0 | E76: =ROUND(Y75*(1+N('My Debts'!$D$9)/12),2) -> 0 | F76: =ROUND(Z75*(1+N('My Debts'!$D$10)/12),2) -> 0 | G76: =ROUND(AA75*(1+N('My Debts'!$D$11)/12),2) -> 0 | H76: =ROUND(AB75*(1+N('My Debts'!$D$12)/12),2) -> 0 | I76: =ROUND(AC75*(1+N('My Debts'!$D$13)/12),2) -> 0 | J76: =ROUND(AD75*(1+N('My Debts'!$D$14)/12),2) -> 0 | K76: =ROUND(AE75*(1+N('My Debts'!$D$15)/12),2) -> 0 | L76: =MIN(N('My Debts'!$E$6),B76) -> 0 | M76: =MIN(N('My Debts'!$E$7),C76) -> 0 | N76: =MIN(N('My Debts'!$E$8),D76) -> 0 | O76: =MIN(N('My Debts'!$E$9),E76) -> 0 | P76: =MIN(N('My Debts'!$E$10),F76) -> 0 | Q76: =MIN(N('My Debts'!$E$11),G76) -> 0 | R76: =MIN(N('My Debts'!$E$12),H76) -> 0 | S76: =MIN(N('My Debts'!$E$13),I76) -> 0 | T76: =MIN(N('My Debts'!$E$14),J76) -> 0 | U76: =MIN(N('My Debts'!$E$15),K76) -> 0 | V76: =ROUND(B76-L76-MIN(B76-L76,MAX(0,$AF76-SUMPRODUCT(--($B$4:$K$4<B$4),$B76:$K76-$L76:$U76))),2) -> 0 | W76: =ROUND(C76-M76-MIN(C76-M76,MAX(0,$AF76-SUMPRODUCT(--($B$4:$K$4<C$4),$B76:$K76-$L76:$U76))),2) -> 0 | X76: =ROUND(D76-N76-MIN(D76-N76,MAX(0,$AF76-SUMPRODUCT(--($B$4:$K$4<D$4),$B76:$K76-$L76:$U76))),2) -> 0 | Y76: =ROUND(E76-O76-MIN(E76-O76,MAX(0,$AF76-SUMPRODUCT(--($B$4:$K$4<E$4),$B76:$K76-$L76:$U76))),2) -> 0 | Z76: =ROUND(F76-P76-MIN(F76-P76,MAX(0,$AF76-SUMPRODUCT(--($B$4:$K$4<F$4),$B76:$K76-$L76:$U76))),2) -> 0 | AA76: =ROUND(G76-Q76-MIN(G76-Q76,MAX(0,$AF76-SUMPRODUCT(--($B$4:$K$4<G$4),$B76:$K76-$L76:$U76))),2) -> 0 | AB76: =ROUND(H76-R76-MIN(H76-R76,MAX(0,$AF76-SUMPRODUCT(--($B$4:$K$4<H$4),$B76:$K76-$L76:$U76))),2) -> 0 | AC76: =ROUND(I76-S76-MIN(I76-S76,MAX(0,$AF76-SUMPRODUCT(--($B$4:$K$4<I$4),$B76:$K76-$L76:$U76))),2) -> 0 | ... AE76: =ROUND(K76-U76-MIN(K76-U76,MAX(0,$AF76-SUMPRODUCT(--($B$4:$K$4<K$4),$B76:$K76-$L76:$U76))),2) -> 0 | AF76: =MAX(0,'Start Here'!$C$5-SUM($L76:$U76)) -> 1200 | AG76: =SUM(V76:AE76) -> 0 | AH76: =SUM(B76:K76)-AG75 -> 0
A77: =DATE(YEAR('Start Here'!$C$6),MONTH('Start Here'!$C$6)+70,1) -> 48427 | B77: =ROUND(V76*(1+N('My Debts'!$D$6)/12),2) -> 0 | C77: =ROUND(W76*(1+N('My Debts'!$D$7)/12),2) -> 0 | D77: =ROUND(X76*(1+N('My Debts'!$D$8)/12),2) -> 0 | E77: =ROUND(Y76*(1+N('My Debts'!$D$9)/12),2) -> 0 | F77: =ROUND(Z76*(1+N('My Debts'!$D$10)/12),2) -> 0 | G77: =ROUND(AA76*(1+N('My Debts'!$D$11)/12),2) -> 0 | H77: =ROUND(AB76*(1+N('My Debts'!$D$12)/12),2) -> 0 | I77: =ROUND(AC76*(1+N('My Debts'!$D$13)/12),2) -> 0 | J77: =ROUND(AD76*(1+N('My Debts'!$D$14)/12),2) -> 0 | K77: =ROUND(AE76*(1+N('My Debts'!$D$15)/12),2) -> 0 | L77: =MIN(N('My Debts'!$E$6),B77) -> 0 | M77: =MIN(N('My Debts'!$E$7),C77) -> 0 | N77: =MIN(N('My Debts'!$E$8),D77) -> 0 | O77: =MIN(N('My Debts'!$E$9),E77) -> 0 | P77: =MIN(N('My Debts'!$E$10),F77) -> 0 | Q77: =MIN(N('My Debts'!$E$11),G77) -> 0 | R77: =MIN(N('My Debts'!$E$12),H77) -> 0 | S77: =MIN(N('My Debts'!$E$13),I77) -> 0 | T77: =MIN(N('My Debts'!$E$14),J77) -> 0 | U77: =MIN(N('My Debts'!$E$15),K77) -> 0 | V77: =ROUND(B77-L77-MIN(B77-L77,MAX(0,$AF77-SUMPRODUCT(--($B$4:$K$4<B$4),$B77:$K77-$L77:$U77))),2) -> 0 | W77: =ROUND(C77-M77-MIN(C77-M77,MAX(0,$AF77-SUMPRODUCT(--($B$4:$K$4<C$4),$B77:$K77-$L77:$U77))),2) -> 0 | X77: =ROUND(D77-N77-MIN(D77-N77,MAX(0,$AF77-SUMPRODUCT(--($B$4:$K$4<D$4),$B77:$K77-$L77:$U77))),2) -> 0 | Y77: =ROUND(E77-O77-MIN(E77-O77,MAX(0,$AF77-SUMPRODUCT(--($B$4:$K$4<E$4),$B77:$K77-$L77:$U77))),2) -> 0 | Z77: =ROUND(F77-P77-MIN(F77-P77,MAX(0,$AF77-SUMPRODUCT(--($B$4:$K$4<F$4),$B77:$K77-$L77:$U77))),2) -> 0 | AA77: =ROUND(G77-Q77-MIN(G77-Q77,MAX(0,$AF77-SUMPRODUCT(--($B$4:$K$4<G$4),$B77:$K77-$L77:$U77))),2) -> 0 | AB77: =ROUND(H77-R77-MIN(H77-R77,MAX(0,$AF77-SUMPRODUCT(--($B$4:$K$4<H$4),$B77:$K77-$L77:$U77))),2) -> 0 | AC77: =ROUND(I77-S77-MIN(I77-S77,MAX(0,$AF77-SUMPRODUCT(--($B$4:$K$4<I$4),$B77:$K77-$L77:$U77))),2) -> 0 | ... AE77: =ROUND(K77-U77-MIN(K77-U77,MAX(0,$AF77-SUMPRODUCT(--($B$4:$K$4<K$4),$B77:$K77-$L77:$U77))),2) -> 0 | AF77: =MAX(0,'Start Here'!$C$5-SUM($L77:$U77)) -> 1200 | AG77: =SUM(V77:AE77) -> 0 | AH77: =SUM(B77:K77)-AG76 -> 0
A78: =DATE(YEAR('Start Here'!$C$6),MONTH('Start Here'!$C$6)+71,1) -> 48458 | B78: =ROUND(V77*(1+N('My Debts'!$D$6)/12),2) -> 0 | C78: =ROUND(W77*(1+N('My Debts'!$D$7)/12),2) -> 0 | D78: =ROUND(X77*(1+N('My Debts'!$D$8)/12),2) -> 0 | E78: =ROUND(Y77*(1+N('My Debts'!$D$9)/12),2) -> 0 | F78: =ROUND(Z77*(1+N('My Debts'!$D$10)/12),2) -> 0 | G78: =ROUND(AA77*(1+N('My Debts'!$D$11)/12),2) -> 0 | H78: =ROUND(AB77*(1+N('My Debts'!$D$12)/12),2) -> 0 | I78: =ROUND(AC77*(1+N('My Debts'!$D$13)/12),2) -> 0 | J78: =ROUND(AD77*(1+N('My Debts'!$D$14)/12),2) -> 0 | K78: =ROUND(AE77*(1+N('My Debts'!$D$15)/12),2) -> 0 | L78: =MIN(N('My Debts'!$E$6),B78) -> 0 | M78: =MIN(N('My Debts'!$E$7),C78) -> 0 | N78: =MIN(N('My Debts'!$E$8),D78) -> 0 | O78: =MIN(N('My Debts'!$E$9),E78) -> 0 | P78: =MIN(N('My Debts'!$E$10),F78) -> 0 | Q78: =MIN(N('My Debts'!$E$11),G78) -> 0 | R78: =MIN(N('My Debts'!$E$12),H78) -> 0 | S78: =MIN(N('My Debts'!$E$13),I78) -> 0 | T78: =MIN(N('My Debts'!$E$14),J78) -> 0 | U78: =MIN(N('My Debts'!$E$15),K78) -> 0 | V78: =ROUND(B78-L78-MIN(B78-L78,MAX(0,$AF78-SUMPRODUCT(--($B$4:$K$4<B$4),$B78:$K78-$L78:$U78))),2) -> 0 | W78: =ROUND(C78-M78-MIN(C78-M78,MAX(0,$AF78-SUMPRODUCT(--($B$4:$K$4<C$4),$B78:$K78-$L78:$U78))),2) -> 0 | X78: =ROUND(D78-N78-MIN(D78-N78,MAX(0,$AF78-SUMPRODUCT(--($B$4:$K$4<D$4),$B78:$K78-$L78:$U78))),2) -> 0 | Y78: =ROUND(E78-O78-MIN(E78-O78,MAX(0,$AF78-SUMPRODUCT(--($B$4:$K$4<E$4),$B78:$K78-$L78:$U78))),2) -> 0 | Z78: =ROUND(F78-P78-MIN(F78-P78,MAX(0,$AF78-SUMPRODUCT(--($B$4:$K$4<F$4),$B78:$K78-$L78:$U78))),2) -> 0 | AA78: =ROUND(G78-Q78-MIN(G78-Q78,MAX(0,$AF78-SUMPRODUCT(--($B$4:$K$4<G$4),$B78:$K78-$L78:$U78))),2) -> 0 | AB78: =ROUND(H78-R78-MIN(H78-R78,MAX(0,$AF78-SUMPRODUCT(--($B$4:$K$4<H$4),$B78:$K78-$L78:$U78))),2) -> 0 | AC78: =ROUND(I78-S78-MIN(I78-S78,MAX(0,$AF78-SUMPRODUCT(--($B$4:$K$4<I$4),$B78:$K78-$L78:$U78))),2) -> 0 | ... AE78: =ROUND(K78-U78-MIN(K78-U78,MAX(0,$AF78-SUMPRODUCT(--($B$4:$K$4<K$4),$B78:$K78-$L78:$U78))),2) -> 0 | AF78: =MAX(0,'Start Here'!$C$5-SUM($L78:$U78)) -> 1200 | AG78: =SUM(V78:AE78) -> 0 | AH78: =SUM(B78:K78)-AG77 -> 0
A79: =DATE(YEAR('Start Here'!$C$6),MONTH('Start Here'!$C$6)+72,1) -> 48488 | B79: =ROUND(V78*(1+N('My Debts'!$D$6)/12),2) -> 0 | C79: =ROUND(W78*(1+N('My Debts'!$D$7)/12),2) -> 0 | D79: =ROUND(X78*(1+N('My Debts'!$D$8)/12),2) -> 0 | E79: =ROUND(Y78*(1+N('My Debts'!$D$9)/12),2) -> 0 | F79: =ROUND(Z78*(1+N('My Debts'!$D$10)/12),2) -> 0 | G79: =ROUND(AA78*(1+N('My Debts'!$D$11)/12),2) -> 0 | H79: =ROUND(AB78*(1+N('My Debts'!$D$12)/12),2) -> 0 | I79: =ROUND(AC78*(1+N('My Debts'!$D$13)/12),2) -> 0 | J79: =ROUND(AD78*(1+N('My Debts'!$D$14)/12),2) -> 0 | K79: =ROUND(AE78*(1+N('My Debts'!$D$15)/12),2) -> 0 | L79: =MIN(N('My Debts'!$E$6),B79) -> 0 | M79: =MIN(N('My Debts'!$E$7),C79) -> 0 | N79: =MIN(N('My Debts'!$E$8),D79) -> 0 | O79: =MIN(N('My Debts'!$E$9),E79) -> 0 | P79: =MIN(N('My Debts'!$E$10),F79) -> 0 | Q79: =MIN(N('My Debts'!$E$11),G79) -> 0 | R79: =MIN(N('My Debts'!$E$12),H79) -> 0 | S79: =MIN(N('My Debts'!$E$13),I79) -> 0 | T79: =MIN(N('My Debts'!$E$14),J79) -> 0 | U79: =MIN(N('My Debts'!$E$15),K79) -> 0 | V79: =ROUND(B79-L79-MIN(B79-L79,MAX(0,$AF79-SUMPRODUCT(--($B$4:$K$4<B$4),$B79:$K79-$L79:$U79))),2) -> 0 | W79: =ROUND(C79-M79-MIN(C79-M79,MAX(0,$AF79-SUMPRODUCT(--($B$4:$K$4<C$4),$B79:$K79-$L79:$U79))),2) -> 0 | X79: =ROUND(D79-N79-MIN(D79-N79,MAX(0,$AF79-SUMPRODUCT(--($B$4:$K$4<D$4),$B79:$K79-$L79:$U79))),2) -> 0 | Y79: =ROUND(E79-O79-MIN(E79-O79,MAX(0,$AF79-SUMPRODUCT(--($B$4:$K$4<E$4),$B79:$K79-$L79:$U79))),2) -> 0 | Z79: =ROUND(F79-P79-MIN(F79-P79,MAX(0,$AF79-SUMPRODUCT(--($B$4:$K$4<F$4),$B79:$K79-$L79:$U79))),2) -> 0 | AA79: =ROUND(G79-Q79-MIN(G79-Q79,MAX(0,$AF79-SUMPRODUCT(--($B$4:$K$4<G$4),$B79:$K79-$L79:$U79))),2) -> 0 | AB79: =ROUND(H79-R79-MIN(H79-R79,MAX(0,$AF79-SUMPRODUCT(--($B$4:$K$4<H$4),$B79:$K79-$L79:$U79))),2) -> 0 | AC79: =ROUND(I79-S79-MIN(I79-S79,MAX(0,$AF79-SUMPRODUCT(--($B$4:$K$4<I$4),$B79:$K79-$L79:$U79))),2) -> 0 | ... AE79: =ROUND(K79-U79-MIN(K79-U79,MAX(0,$AF79-SUMPRODUCT(--($B$4:$K$4<K$4),$B79:$K79-$L79:$U79))),2) -> 0 | AF79: =MAX(0,'Start Here'!$C$5-SUM($L79:$U79)) -> 1200 | AG79: =SUM(V79:AE79) -> 0 | AH79: =SUM(B79:K79)-AG78 -> 0
A80: =DATE(YEAR('Start Here'!$C$6),MONTH('Start Here'!$C$6)+73,1) -> 48519 | B80: =ROUND(V79*(1+N('My Debts'!$D$6)/12),2) -> 0 | C80: =ROUND(W79*(1+N('My Debts'!$D$7)/12),2) -> 0 | D80: =ROUND(X79*(1+N('My Debts'!$D$8)/12),2) -> 0 | E80: =ROUND(Y79*(1+N('My Debts'!$D$9)/12),2) -> 0 | F80: =ROUND(Z79*(1+N('My Debts'!$D$10)/12),2) -> 0 | G80: =ROUND(AA79*(1+N('My Debts'!$D$11)/12),2) -> 0 | H80: =ROUND(AB79*(1+N('My Debts'!$D$12)/12),2) -> 0 | I80: =ROUND(AC79*(1+N('My Debts'!$D$13)/12),2) -> 0 | J80: =ROUND(AD79*(1+N('My Debts'!$D$14)/12),2) -> 0 | K80: =ROUND(AE79*(1+N('My Debts'!$D$15)/12),2) -> 0 | L80: =MIN(N('My Debts'!$E$6),B80) -> 0 | M80: =MIN(N('My Debts'!$E$7),C80) -> 0 | N80: =MIN(N('My Debts'!$E$8),D80) -> 0 | O80: =MIN(N('My Debts'!$E$9),E80) -> 0 | P80: =MIN(N('My Debts'!$E$10),F80) -> 0 | Q80: =MIN(N('My Debts'!$E$11),G80) -> 0 | R80: =MIN(N('My Debts'!$E$12),H80) -> 0 | S80: =MIN(N('My Debts'!$E$13),I80) -> 0 | T80: =MIN(N('My Debts'!$E$14),J80) -> 0 | U80: =MIN(N('My Debts'!$E$15),K80) -> 0 | V80: =ROUND(B80-L80-MIN(B80-L80,MAX(0,$AF80-SUMPRODUCT(--($B$4:$K$4<B$4),$B80:$K80-$L80:$U80))),2) -> 0 | W80: =ROUND(C80-M80-MIN(C80-M80,MAX(0,$AF80-SUMPRODUCT(--($B$4:$K$4<C$4),$B80:$K80-$L80:$U80))),2) -> 0 | X80: =ROUND(D80-N80-MIN(D80-N80,MAX(0,$AF80-SUMPRODUCT(--($B$4:$K$4<D$4),$B80:$K80-$L80:$U80))),2) -> 0 | Y80: =ROUND(E80-O80-MIN(E80-O80,MAX(0,$AF80-SUMPRODUCT(--($B$4:$K$4<E$4),$B80:$K80-$L80:$U80))),2) -> 0 | Z80: =ROUND(F80-P80-MIN(F80-P80,MAX(0,$AF80-SUMPRODUCT(--($B$4:$K$4<F$4),$B80:$K80-$L80:$U80))),2) -> 0 | AA80: =ROUND(G80-Q80-MIN(G80-Q80,MAX(0,$AF80-SUMPRODUCT(--($B$4:$K$4<G$4),$B80:$K80-$L80:$U80))),2) -> 0 | AB80: =ROUND(H80-R80-MIN(H80-R80,MAX(0,$AF80-SUMPRODUCT(--($B$4:$K$4<H$4),$B80:$K80-$L80:$U80))),2) -> 0 | AC80: =ROUND(I80-S80-MIN(I80-S80,MAX(0,$AF80-SUMPRODUCT(--($B$4:$K$4<I$4),$B80:$K80-$L80:$U80))),2) -> 0 | ... AE80: =ROUND(K80-U80-MIN(K80-U80,MAX(0,$AF80-SUMPRODUCT(--($B$4:$K$4<K$4),$B80:$K80-$L80:$U80))),2) -> 0 | AF80: =MAX(0,'Start Here'!$C$5-SUM($L80:$U80)) -> 1200 | AG80: =SUM(V80:AE80) -> 0 | AH80: =SUM(B80:K80)-AG79 -> 0
A81: =DATE(YEAR('Start Here'!$C$6),MONTH('Start Here'!$C$6)+74,1) -> 48549 | B81: =ROUND(V80*(1+N('My Debts'!$D$6)/12),2) -> 0 | C81: =ROUND(W80*(1+N('My Debts'!$D$7)/12),2) -> 0 | D81: =ROUND(X80*(1+N('My Debts'!$D$8)/12),2) -> 0 | E81: =ROUND(Y80*(1+N('My Debts'!$D$9)/12),2) -> 0 | F81: =ROUND(Z80*(1+N('My Debts'!$D$10)/12),2) -> 0 | G81: =ROUND(AA80*(1+N('My Debts'!$D$11)/12),2) -> 0 | H81: =ROUND(AB80*(1+N('My Debts'!$D$12)/12),2) -> 0 | I81: =ROUND(AC80*(1+N('My Debts'!$D$13)/12),2) -> 0 | J81: =ROUND(AD80*(1+N('My Debts'!$D$14)/12),2) -> 0 | K81: =ROUND(AE80*(1+N('My Debts'!$D$15)/12),2) -> 0 | L81: =MIN(N('My Debts'!$E$6),B81) -> 0 | M81: =MIN(N('My Debts'!$E$7),C81) -> 0 | N81: =MIN(N('My Debts'!$E$8),D81) -> 0 | O81: =MIN(N('My Debts'!$E$9),E81) -> 0 | P81: =MIN(N('My Debts'!$E$10),F81) -> 0 | Q81: =MIN(N('My Debts'!$E$11),G81) -> 0 | R81: =MIN(N('My Debts'!$E$12),H81) -> 0 | S81: =MIN(N('My Debts'!$E$13),I81) -> 0 | T81: =MIN(N('My Debts'!$E$14),J81) -> 0 | U81: =MIN(N('My Debts'!$E$15),K81) -> 0 | V81: =ROUND(B81-L81-MIN(B81-L81,MAX(0,$AF81-SUMPRODUCT(--($B$4:$K$4<B$4),$B81:$K81-$L81:$U81))),2) -> 0 | W81: =ROUND(C81-M81-MIN(C81-M81,MAX(0,$AF81-SUMPRODUCT(--($B$4:$K$4<C$4),$B81:$K81-$L81:$U81))),2) -> 0 | X81: =ROUND(D81-N81-MIN(D81-N81,MAX(0,$AF81-SUMPRODUCT(--($B$4:$K$4<D$4),$B81:$K81-$L81:$U81))),2) -> 0 | Y81: =ROUND(E81-O81-MIN(E81-O81,MAX(0,$AF81-SUMPRODUCT(--($B$4:$K$4<E$4),$B81:$K81-$L81:$U81))),2) -> 0 | Z81: =ROUND(F81-P81-MIN(F81-P81,MAX(0,$AF81-SUMPRODUCT(--($B$4:$K$4<F$4),$B81:$K81-$L81:$U81))),2) -> 0 | AA81: =ROUND(G81-Q81-MIN(G81-Q81,MAX(0,$AF81-SUMPRODUCT(--($B$4:$K$4<G$4),$B81:$K81-$L81:$U81))),2) -> 0 | AB81: =ROUND(H81-R81-MIN(H81-R81,MAX(0,$AF81-SUMPRODUCT(--($B$4:$K$4<H$4),$B81:$K81-$L81:$U81))),2) -> 0 | AC81: =ROUND(I81-S81-MIN(I81-S81,MAX(0,$AF81-SUMPRODUCT(--($B$4:$K$4<I$4),$B81:$K81-$L81:$U81))),2) -> 0 | ... AE81: =ROUND(K81-U81-MIN(K81-U81,MAX(0,$AF81-SUMPRODUCT(--($B$4:$K$4<K$4),$B81:$K81-$L81:$U81))),2) -> 0 | AF81: =MAX(0,'Start Here'!$C$5-SUM($L81:$U81)) -> 1200 | AG81: =SUM(V81:AE81) -> 0 | AH81: =SUM(B81:K81)-AG80 -> 0
A82: =DATE(YEAR('Start Here'!$C$6),MONTH('Start Here'!$C$6)+75,1) -> 48580 | B82: =ROUND(V81*(1+N('My Debts'!$D$6)/12),2) -> 0 | C82: =ROUND(W81*(1+N('My Debts'!$D$7)/12),2) -> 0 | D82: =ROUND(X81*(1+N('My Debts'!$D$8)/12),2) -> 0 | E82: =ROUND(Y81*(1+N('My Debts'!$D$9)/12),2) -> 0 | F82: =ROUND(Z81*(1+N('My Debts'!$D$10)/12),2) -> 0 | G82: =ROUND(AA81*(1+N('My Debts'!$D$11)/12),2) -> 0 | H82: =ROUND(AB81*(1+N('My Debts'!$D$12)/12),2) -> 0 | I82: =ROUND(AC81*(1+N('My Debts'!$D$13)/12),2) -> 0 | J82: =ROUND(AD81*(1+N('My Debts'!$D$14)/12),2) -> 0 | K82: =ROUND(AE81*(1+N('My Debts'!$D$15)/12),2) -> 0 | L82: =MIN(N('My Debts'!$E$6),B82) -> 0 | M82: =MIN(N('My Debts'!$E$7),C82) -> 0 | N82: =MIN(N('My Debts'!$E$8),D82) -> 0 | O82: =MIN(N('My Debts'!$E$9),E82) -> 0 | P82: =MIN(N('My Debts'!$E$10),F82) -> 0 | Q82: =MIN(N('My Debts'!$E$11),G82) -> 0 | R82: =MIN(N('My Debts'!$E$12),H82) -> 0 | S82: =MIN(N('My Debts'!$E$13),I82) -> 0 | T82: =MIN(N('My Debts'!$E$14),J82) -> 0 | U82: =MIN(N('My Debts'!$E$15),K82) -> 0 | V82: =ROUND(B82-L82-MIN(B82-L82,MAX(0,$AF82-SUMPRODUCT(--($B$4:$K$4<B$4),$B82:$K82-$L82:$U82))),2) -> 0 | W82: =ROUND(C82-M82-MIN(C82-M82,MAX(0,$AF82-SUMPRODUCT(--($B$4:$K$4<C$4),$B82:$K82-$L82:$U82))),2) -> 0 | X82: =ROUND(D82-N82-MIN(D82-N82,MAX(0,$AF82-SUMPRODUCT(--($B$4:$K$4<D$4),$B82:$K82-$L82:$U82))),2) -> 0 | Y82: =ROUND(E82-O82-MIN(E82-O82,MAX(0,$AF82-SUMPRODUCT(--($B$4:$K$4<E$4),$B82:$K82-$L82:$U82))),2) -> 0 | Z82: =ROUND(F82-P82-MIN(F82-P82,MAX(0,$AF82-SUMPRODUCT(--($B$4:$K$4<F$4),$B82:$K82-$L82:$U82))),2) -> 0 | AA82: =ROUND(G82-Q82-MIN(G82-Q82,MAX(0,$AF82-SUMPRODUCT(--($B$4:$K$4<G$4),$B82:$K82-$L82:$U82))),2) -> 0 | AB82: =ROUND(H82-R82-MIN(H82-R82,MAX(0,$AF82-SUMPRODUCT(--($B$4:$K$4<H$4),$B82:$K82-$L82:$U82))),2) -> 0 | AC82: =ROUND(I82-S82-MIN(I82-S82,MAX(0,$AF82-SUMPRODUCT(--($B$4:$K$4<I$4),$B82:$K82-$L82:$U82))),2) -> 0 | ... AE82: =ROUND(K82-U82-MIN(K82-U82,MAX(0,$AF82-SUMPRODUCT(--($B$4:$K$4<K$4),$B82:$K82-$L82:$U82))),2) -> 0 | AF82: =MAX(0,'Start Here'!$C$5-SUM($L82:$U82)) -> 1200 | AG82: =SUM(V82:AE82) -> 0 | AH82: =SUM(B82:K82)-AG81 -> 0
A83: =DATE(YEAR('Start Here'!$C$6),MONTH('Start Here'!$C$6)+76,1) -> 48611 | B83: =ROUND(V82*(1+N('My Debts'!$D$6)/12),2) -> 0 | C83: =ROUND(W82*(1+N('My Debts'!$D$7)/12),2) -> 0 | D83: =ROUND(X82*(1+N('My Debts'!$D$8)/12),2) -> 0 | E83: =ROUND(Y82*(1+N('My Debts'!$D$9)/12),2) -> 0 | F83: =ROUND(Z82*(1+N('My Debts'!$D$10)/12),2) -> 0 | G83: =ROUND(AA82*(1+N('My Debts'!$D$11)/12),2) -> 0 | H83: =ROUND(AB82*(1+N('My Debts'!$D$12)/12),2) -> 0 | I83: =ROUND(AC82*(1+N('My Debts'!$D$13)/12),2) -> 0 | J83: =ROUND(AD82*(1+N('My Debts'!$D$14)/12),2) -> 0 | K83: =ROUND(AE82*(1+N('My Debts'!$D$15)/12),2) -> 0 | L83: =MIN(N('My Debts'!$E$6),B83) -> 0 | M83: =MIN(N('My Debts'!$E$7),C83) -> 0 | N83: =MIN(N('My Debts'!$E$8),D83) -> 0 | O83: =MIN(N('My Debts'!$E$9),E83) -> 0 | P83: =MIN(N('My Debts'!$E$10),F83) -> 0 | Q83: =MIN(N('My Debts'!$E$11),G83) -> 0 | R83: =MIN(N('My Debts'!$E$12),H83) -> 0 | S83: =MIN(N('My Debts'!$E$13),I83) -> 0 | T83: =MIN(N('My Debts'!$E$14),J83) -> 0 | U83: =MIN(N('My Debts'!$E$15),K83) -> 0 | V83: =ROUND(B83-L83-MIN(B83-L83,MAX(0,$AF83-SUMPRODUCT(--($B$4:$K$4<B$4),$B83:$K83-$L83:$U83))),2) -> 0 | W83: =ROUND(C83-M83-MIN(C83-M83,MAX(0,$AF83-SUMPRODUCT(--($B$4:$K$4<C$4),$B83:$K83-$L83:$U83))),2) -> 0 | X83: =ROUND(D83-N83-MIN(D83-N83,MAX(0,$AF83-SUMPRODUCT(--($B$4:$K$4<D$4),$B83:$K83-$L83:$U83))),2) -> 0 | Y83: =ROUND(E83-O83-MIN(E83-O83,MAX(0,$AF83-SUMPRODUCT(--($B$4:$K$4<E$4),$B83:$K83-$L83:$U83))),2) -> 0 | Z83: =ROUND(F83-P83-MIN(F83-P83,MAX(0,$AF83-SUMPRODUCT(--($B$4:$K$4<F$4),$B83:$K83-$L83:$U83))),2) -> 0 | AA83: =ROUND(G83-Q83-MIN(G83-Q83,MAX(0,$AF83-SUMPRODUCT(--($B$4:$K$4<G$4),$B83:$K83-$L83:$U83))),2) -> 0 | AB83: =ROUND(H83-R83-MIN(H83-R83,MAX(0,$AF83-SUMPRODUCT(--($B$4:$K$4<H$4),$B83:$K83-$L83:$U83))),2) -> 0 | AC83: =ROUND(I83-S83-MIN(I83-S83,MAX(0,$AF83-SUMPRODUCT(--($B$4:$K$4<I$4),$B83:$K83-$L83:$U83))),2) -> 0 | ... AE83: =ROUND(K83-U83-MIN(K83-U83,MAX(0,$AF83-SUMPRODUCT(--($B$4:$K$4<K$4),$B83:$K83-$L83:$U83))),2) -> 0 | AF83: =MAX(0,'Start Here'!$C$5-SUM($L83:$U83)) -> 1200 | AG83: =SUM(V83:AE83) -> 0 | AH83: =SUM(B83:K83)-AG82 -> 0
A84: =DATE(YEAR('Start Here'!$C$6),MONTH('Start Here'!$C$6)+77,1) -> 48639 | B84: =ROUND(V83*(1+N('My Debts'!$D$6)/12),2) -> 0 | C84: =ROUND(W83*(1+N('My Debts'!$D$7)/12),2) -> 0 | D84: =ROUND(X83*(1+N('My Debts'!$D$8)/12),2) -> 0 | E84: =ROUND(Y83*(1+N('My Debts'!$D$9)/12),2) -> 0 | F84: =ROUND(Z83*(1+N('My Debts'!$D$10)/12),2) -> 0 | G84: =ROUND(AA83*(1+N('My Debts'!$D$11)/12),2) -> 0 | H84: =ROUND(AB83*(1+N('My Debts'!$D$12)/12),2) -> 0 | I84: =ROUND(AC83*(1+N('My Debts'!$D$13)/12),2) -> 0 | J84: =ROUND(AD83*(1+N('My Debts'!$D$14)/12),2) -> 0 | K84: =ROUND(AE83*(1+N('My Debts'!$D$15)/12),2) -> 0 | L84: =MIN(N('My Debts'!$E$6),B84) -> 0 | M84: =MIN(N('My Debts'!$E$7),C84) -> 0 | N84: =MIN(N('My Debts'!$E$8),D84) -> 0 | O84: =MIN(N('My Debts'!$E$9),E84) -> 0 | P84: =MIN(N('My Debts'!$E$10),F84) -> 0 | Q84: =MIN(N('My Debts'!$E$11),G84) -> 0 | R84: =MIN(N('My Debts'!$E$12),H84) -> 0 | S84: =MIN(N('My Debts'!$E$13),I84) -> 0 | T84: =MIN(N('My Debts'!$E$14),J84) -> 0 | U84: =MIN(N('My Debts'!$E$15),K84) -> 0 | V84: =ROUND(B84-L84-MIN(B84-L84,MAX(0,$AF84-SUMPRODUCT(--($B$4:$K$4<B$4),$B84:$K84-$L84:$U84))),2) -> 0 | W84: =ROUND(C84-M84-MIN(C84-M84,MAX(0,$AF84-SUMPRODUCT(--($B$4:$K$4<C$4),$B84:$K84-$L84:$U84))),2) -> 0 | X84: =ROUND(D84-N84-MIN(D84-N84,MAX(0,$AF84-SUMPRODUCT(--($B$4:$K$4<D$4),$B84:$K84-$L84:$U84))),2) -> 0 | Y84: =ROUND(E84-O84-MIN(E84-O84,MAX(0,$AF84-SUMPRODUCT(--($B$4:$K$4<E$4),$B84:$K84-$L84:$U84))),2) -> 0 | Z84: =ROUND(F84-P84-MIN(F84-P84,MAX(0,$AF84-SUMPRODUCT(--($B$4:$K$4<F$4),$B84:$K84-$L84:$U84))),2) -> 0 | AA84: =ROUND(G84-Q84-MIN(G84-Q84,MAX(0,$AF84-SUMPRODUCT(--($B$4:$K$4<G$4),$B84:$K84-$L84:$U84))),2) -> 0 | AB84: =ROUND(H84-R84-MIN(H84-R84,MAX(0,$AF84-SUMPRODUCT(--($B$4:$K$4<H$4),$B84:$K84-$L84:$U84))),2) -> 0 | AC84: =ROUND(I84-S84-MIN(I84-S84,MAX(0,$AF84-SUMPRODUCT(--($B$4:$K$4<I$4),$B84:$K84-$L84:$U84))),2) -> 0 | ... AE84: =ROUND(K84-U84-MIN(K84-U84,MAX(0,$AF84-SUMPRODUCT(--($B$4:$K$4<K$4),$B84:$K84-$L84:$U84))),2) -> 0 | AF84: =MAX(0,'Start Here'!$C$5-SUM($L84:$U84)) -> 1200 | AG84: =SUM(V84:AE84) -> 0 | AH84: =SUM(B84:K84)-AG83 -> 0
A85: =DATE(YEAR('Start Here'!$C$6),MONTH('Start Here'!$C$6)+78,1) -> 48670 | B85: =ROUND(V84*(1+N('My Debts'!$D$6)/12),2) -> 0 | C85: =ROUND(W84*(1+N('My Debts'!$D$7)/12),2) -> 0 | D85: =ROUND(X84*(1+N('My Debts'!$D$8)/12),2) -> 0 | E85: =ROUND(Y84*(1+N('My Debts'!$D$9)/12),2) -> 0 | F85: =ROUND(Z84*(1+N('My Debts'!$D$10)/12),2) -> 0 | G85: =ROUND(AA84*(1+N('My Debts'!$D$11)/12),2) -> 0 | H85: =ROUND(AB84*(1+N('My Debts'!$D$12)/12),2) -> 0 | I85: =ROUND(AC84*(1+N('My Debts'!$D$13)/12),2) -> 0 | J85: =ROUND(AD84*(1+N('My Debts'!$D$14)/12),2) -> 0 | K85: =ROUND(AE84*(1+N('My Debts'!$D$15)/12),2) -> 0 | L85: =MIN(N('My Debts'!$E$6),B85) -> 0 | M85: =MIN(N('My Debts'!$E$7),C85) -> 0 | N85: =MIN(N('My Debts'!$E$8),D85) -> 0 | O85: =MIN(N('My Debts'!$E$9),E85) -> 0 | P85: =MIN(N('My Debts'!$E$10),F85) -> 0 | Q85: =MIN(N('My Debts'!$E$11),G85) -> 0 | R85: =MIN(N('My Debts'!$E$12),H85) -> 0 | S85: =MIN(N('My Debts'!$E$13),I85) -> 0 | T85: =MIN(N('My Debts'!$E$14),J85) -> 0 | U85: =MIN(N('My Debts'!$E$15),K85) -> 0 | V85: =ROUND(B85-L85-MIN(B85-L85,MAX(0,$AF85-SUMPRODUCT(--($B$4:$K$4<B$4),$B85:$K85-$L85:$U85))),2) -> 0 | W85: =ROUND(C85-M85-MIN(C85-M85,MAX(0,$AF85-SUMPRODUCT(--($B$4:$K$4<C$4),$B85:$K85-$L85:$U85))),2) -> 0 | X85: =ROUND(D85-N85-MIN(D85-N85,MAX(0,$AF85-SUMPRODUCT(--($B$4:$K$4<D$4),$B85:$K85-$L85:$U85))),2) -> 0 | Y85: =ROUND(E85-O85-MIN(E85-O85,MAX(0,$AF85-SUMPRODUCT(--($B$4:$K$4<E$4),$B85:$K85-$L85:$U85))),2) -> 0 | Z85: =ROUND(F85-P85-MIN(F85-P85,MAX(0,$AF85-SUMPRODUCT(--($B$4:$K$4<F$4),$B85:$K85-$L85:$U85))),2) -> 0 | AA85: =ROUND(G85-Q85-MIN(G85-Q85,MAX(0,$AF85-SUMPRODUCT(--($B$4:$K$4<G$4),$B85:$K85-$L85:$U85))),2) -> 0 | AB85: =ROUND(H85-R85-MIN(H85-R85,MAX(0,$AF85-SUMPRODUCT(--($B$4:$K$4<H$4),$B85:$K85-$L85:$U85))),2) -> 0 | AC85: =ROUND(I85-S85-MIN(I85-S85,MAX(0,$AF85-SUMPRODUCT(--($B$4:$K$4<I$4),$B85:$K85-$L85:$U85))),2) -> 0 | ... AE85: =ROUND(K85-U85-MIN(K85-U85,MAX(0,$AF85-SUMPRODUCT(--($B$4:$K$4<K$4),$B85:$K85-$L85:$U85))),2) -> 0 | AF85: =MAX(0,'Start Here'!$C$5-SUM($L85:$U85)) -> 1200 | AG85: =SUM(V85:AE85) -> 0 | AH85: =SUM(B85:K85)-AG84 -> 0
A86: =DATE(YEAR('Start Here'!$C$6),MONTH('Start Here'!$C$6)+79,1) -> 48700 | B86: =ROUND(V85*(1+N('My Debts'!$D$6)/12),2) -> 0 | C86: =ROUND(W85*(1+N('My Debts'!$D$7)/12),2) -> 0 | D86: =ROUND(X85*(1+N('My Debts'!$D$8)/12),2) -> 0 | E86: =ROUND(Y85*(1+N('My Debts'!$D$9)/12),2) -> 0 | F86: =ROUND(Z85*(1+N('My Debts'!$D$10)/12),2) -> 0 | G86: =ROUND(AA85*(1+N('My Debts'!$D$11)/12),2) -> 0 | H86: =ROUND(AB85*(1+N('My Debts'!$D$12)/12),2) -> 0 | I86: =ROUND(AC85*(1+N('My Debts'!$D$13)/12),2) -> 0 | J86: =ROUND(AD85*(1+N('My Debts'!$D$14)/12),2) -> 0 | K86: =ROUND(AE85*(1+N('My Debts'!$D$15)/12),2) -> 0 | L86: =MIN(N('My Debts'!$E$6),B86) -> 0 | M86: =MIN(N('My Debts'!$E$7),C86) -> 0 | N86: =MIN(N('My Debts'!$E$8),D86) -> 0 | O86: =MIN(N('My Debts'!$E$9),E86) -> 0 | P86: =MIN(N('My Debts'!$E$10),F86) -> 0 | Q86: =MIN(N('My Debts'!$E$11),G86) -> 0 | R86: =MIN(N('My Debts'!$E$12),H86) -> 0 | S86: =MIN(N('My Debts'!$E$13),I86) -> 0 | T86: =MIN(N('My Debts'!$E$14),J86) -> 0 | U86: =MIN(N('My Debts'!$E$15),K86) -> 0 | V86: =ROUND(B86-L86-MIN(B86-L86,MAX(0,$AF86-SUMPRODUCT(--($B$4:$K$4<B$4),$B86:$K86-$L86:$U86))),2) -> 0 | W86: =ROUND(C86-M86-MIN(C86-M86,MAX(0,$AF86-SUMPRODUCT(--($B$4:$K$4<C$4),$B86:$K86-$L86:$U86))),2) -> 0 | X86: =ROUND(D86-N86-MIN(D86-N86,MAX(0,$AF86-SUMPRODUCT(--($B$4:$K$4<D$4),$B86:$K86-$L86:$U86))),2) -> 0 | Y86: =ROUND(E86-O86-MIN(E86-O86,MAX(0,$AF86-SUMPRODUCT(--($B$4:$K$4<E$4),$B86:$K86-$L86:$U86))),2) -> 0 | Z86: =ROUND(F86-P86-MIN(F86-P86,MAX(0,$AF86-SUMPRODUCT(--($B$4:$K$4<F$4),$B86:$K86-$L86:$U86))),2) -> 0 | AA86: =ROUND(G86-Q86-MIN(G86-Q86,MAX(0,$AF86-SUMPRODUCT(--($B$4:$K$4<G$4),$B86:$K86-$L86:$U86))),2) -> 0 | AB86: =ROUND(H86-R86-MIN(H86-R86,MAX(0,$AF86-SUMPRODUCT(--($B$4:$K$4<H$4),$B86:$K86-$L86:$U86))),2) -> 0 | AC86: =ROUND(I86-S86-MIN(I86-S86,MAX(0,$AF86-SUMPRODUCT(--($B$4:$K$4<I$4),$B86:$K86-$L86:$U86))),2) -> 0 | ... AE86: =ROUND(K86-U86-MIN(K86-U86,MAX(0,$AF86-SUMPRODUCT(--($B$4:$K$4<K$4),$B86:$K86-$L86:$U86))),2) -> 0 | AF86: =MAX(0,'Start Here'!$C$5-SUM($L86:$U86)) -> 1200 | AG86: =SUM(V86:AE86) -> 0 | AH86: =SUM(B86:K86)-AG85 -> 0
A87: =DATE(YEAR('Start Here'!$C$6),MONTH('Start Here'!$C$6)+80,1) -> 48731 | B87: =ROUND(V86*(1+N('My Debts'!$D$6)/12),2) -> 0 | C87: =ROUND(W86*(1+N('My Debts'!$D$7)/12),2) -> 0 | D87: =ROUND(X86*(1+N('My Debts'!$D$8)/12),2) -> 0 | E87: =ROUND(Y86*(1+N('My Debts'!$D$9)/12),2) -> 0 | F87: =ROUND(Z86*(1+N('My Debts'!$D$10)/12),2) -> 0 | G87: =ROUND(AA86*(1+N('My Debts'!$D$11)/12),2) -> 0 | H87: =ROUND(AB86*(1+N('My Debts'!$D$12)/12),2) -> 0 | I87: =ROUND(AC86*(1+N('My Debts'!$D$13)/12),2) -> 0 | J87: =ROUND(AD86*(1+N('My Debts'!$D$14)/12),2) -> 0 | K87: =ROUND(AE86*(1+N('My Debts'!$D$15)/12),2) -> 0 | L87: =MIN(N('My Debts'!$E$6),B87) -> 0 | M87: =MIN(N('My Debts'!$E$7),C87) -> 0 | N87: =MIN(N('My Debts'!$E$8),D87) -> 0 | O87: =MIN(N('My Debts'!$E$9),E87) -> 0 | P87: =MIN(N('My Debts'!$E$10),F87) -> 0 | Q87: =MIN(N('My Debts'!$E$11),G87) -> 0 | R87: =MIN(N('My Debts'!$E$12),H87) -> 0 | S87: =MIN(N('My Debts'!$E$13),I87) -> 0 | T87: =MIN(N('My Debts'!$E$14),J87) -> 0 | U87: =MIN(N('My Debts'!$E$15),K87) -> 0 | V87: =ROUND(B87-L87-MIN(B87-L87,MAX(0,$AF87-SUMPRODUCT(--($B$4:$K$4<B$4),$B87:$K87-$L87:$U87))),2) -> 0 | W87: =ROUND(C87-M87-MIN(C87-M87,MAX(0,$AF87-SUMPRODUCT(--($B$4:$K$4<C$4),$B87:$K87-$L87:$U87))),2) -> 0 | X87: =ROUND(D87-N87-MIN(D87-N87,MAX(0,$AF87-SUMPRODUCT(--($B$4:$K$4<D$4),$B87:$K87-$L87:$U87))),2) -> 0 | Y87: =ROUND(E87-O87-MIN(E87-O87,MAX(0,$AF87-SUMPRODUCT(--($B$4:$K$4<E$4),$B87:$K87-$L87:$U87))),2) -> 0 | Z87: =ROUND(F87-P87-MIN(F87-P87,MAX(0,$AF87-SUMPRODUCT(--($B$4:$K$4<F$4),$B87:$K87-$L87:$U87))),2) -> 0 | AA87: =ROUND(G87-Q87-MIN(G87-Q87,MAX(0,$AF87-SUMPRODUCT(--($B$4:$K$4<G$4),$B87:$K87-$L87:$U87))),2) -> 0 | AB87: =ROUND(H87-R87-MIN(H87-R87,MAX(0,$AF87-SUMPRODUCT(--($B$4:$K$4<H$4),$B87:$K87-$L87:$U87))),2) -> 0 | AC87: =ROUND(I87-S87-MIN(I87-S87,MAX(0,$AF87-SUMPRODUCT(--($B$4:$K$4<I$4),$B87:$K87-$L87:$U87))),2) -> 0 | ... AE87: =ROUND(K87-U87-MIN(K87-U87,MAX(0,$AF87-SUMPRODUCT(--($B$4:$K$4<K$4),$B87:$K87-$L87:$U87))),2) -> 0 | AF87: =MAX(0,'Start Here'!$C$5-SUM($L87:$U87)) -> 1200 | AG87: =SUM(V87:AE87) -> 0 | AH87: =SUM(B87:K87)-AG86 -> 0
A88: =DATE(YEAR('Start Here'!$C$6),MONTH('Start Here'!$C$6)+81,1) -> 48761 | B88: =ROUND(V87*(1+N('My Debts'!$D$6)/12),2) -> 0 | C88: =ROUND(W87*(1+N('My Debts'!$D$7)/12),2) -> 0 | D88: =ROUND(X87*(1+N('My Debts'!$D$8)/12),2) -> 0 | E88: =ROUND(Y87*(1+N('My Debts'!$D$9)/12),2) -> 0 | F88: =ROUND(Z87*(1+N('My Debts'!$D$10)/12),2) -> 0 | G88: =ROUND(AA87*(1+N('My Debts'!$D$11)/12),2) -> 0 | H88: =ROUND(AB87*(1+N('My Debts'!$D$12)/12),2) -> 0 | I88: =ROUND(AC87*(1+N('My Debts'!$D$13)/12),2) -> 0 | J88: =ROUND(AD87*(1+N('My Debts'!$D$14)/12),2) -> 0 | K88: =ROUND(AE87*(1+N('My Debts'!$D$15)/12),2) -> 0 | L88: =MIN(N('My Debts'!$E$6),B88) -> 0 | M88: =MIN(N('My Debts'!$E$7),C88) -> 0 | N88: =MIN(N('My Debts'!$E$8),D88) -> 0 | O88: =MIN(N('My Debts'!$E$9),E88) -> 0 | P88: =MIN(N('My Debts'!$E$10),F88) -> 0 | Q88: =MIN(N('My Debts'!$E$11),G88) -> 0 | R88: =MIN(N('My Debts'!$E$12),H88) -> 0 | S88: =MIN(N('My Debts'!$E$13),I88) -> 0 | T88: =MIN(N('My Debts'!$E$14),J88) -> 0 | U88: =MIN(N('My Debts'!$E$15),K88) -> 0 | V88: =ROUND(B88-L88-MIN(B88-L88,MAX(0,$AF88-SUMPRODUCT(--($B$4:$K$4<B$4),$B88:$K88-$L88:$U88))),2) -> 0 | W88: =ROUND(C88-M88-MIN(C88-M88,MAX(0,$AF88-SUMPRODUCT(--($B$4:$K$4<C$4),$B88:$K88-$L88:$U88))),2) -> 0 | X88: =ROUND(D88-N88-MIN(D88-N88,MAX(0,$AF88-SUMPRODUCT(--($B$4:$K$4<D$4),$B88:$K88-$L88:$U88))),2) -> 0 | Y88: =ROUND(E88-O88-MIN(E88-O88,MAX(0,$AF88-SUMPRODUCT(--($B$4:$K$4<E$4),$B88:$K88-$L88:$U88))),2) -> 0 | Z88: =ROUND(F88-P88-MIN(F88-P88,MAX(0,$AF88-SUMPRODUCT(--($B$4:$K$4<F$4),$B88:$K88-$L88:$U88))),2) -> 0 | AA88: =ROUND(G88-Q88-MIN(G88-Q88,MAX(0,$AF88-SUMPRODUCT(--($B$4:$K$4<G$4),$B88:$K88-$L88:$U88))),2) -> 0 | AB88: =ROUND(H88-R88-MIN(H88-R88,MAX(0,$AF88-SUMPRODUCT(--($B$4:$K$4<H$4),$B88:$K88-$L88:$U88))),2) -> 0 | AC88: =ROUND(I88-S88-MIN(I88-S88,MAX(0,$AF88-SUMPRODUCT(--($B$4:$K$4<I$4),$B88:$K88-$L88:$U88))),2) -> 0 | ... AE88: =ROUND(K88-U88-MIN(K88-U88,MAX(0,$AF88-SUMPRODUCT(--($B$4:$K$4<K$4),$B88:$K88-$L88:$U88))),2) -> 0 | AF88: =MAX(0,'Start Here'!$C$5-SUM($L88:$U88)) -> 1200 | AG88: =SUM(V88:AE88) -> 0 | AH88: =SUM(B88:K88)-AG87 -> 0
