Workbook

Sheet Start Here
A1: Hustle Ledger
A2: Side-hustle & freelance income, expense and tax tracker
B4: YOUR SETTINGS
B5: Business name | C5: My Side Hustle | D5: Shown on the Dashboard.
B6: Tax year | C6: 2026 | D6: Only entries dated in this year are counted.
B7: Monthly income goal | C7: 3000 | D7: Used for goal progress on the Dashboard.
B8: Federal income tax rate (estimate) | C8: 0.12 | D8: Your expected federal bracket, e.g. 10%, 12%, 22%.
B9: State income tax rate (estimate) | C9: 0.05 | D9: Use 0% if your state has no income tax.
B10: Self-employment tax rate | C10: 0.153 | D10: US SE tax: 12.4% Social Security + 2.9% Medicare.
B11: Share of profit subject to SE tax | C11: 0.9235 | D11: IRS Schedule SE uses 92.35% of net profit.
B12: Mileage rate ($ per mile) | C12: 0.7 | D12: IRS standard rate for 2025 was $0.70. Update to the current year's rate at irs.gov.
B15: HOW TO USE
B16: 1. Fill in the yellow cells above. Yellow = type here. Everything else calculates itself.
B17: 2. Log every payment you receive on the Income tab (date, source, amount).
B18: 3. Log every business purchase on the Expenses tab. Pick a category from the dropdown.
B19: 4. Log business driving on the Mileage tab. Deductions are calculated for you.
B20: 5. Check the Dashboard for monthly profit, goal progress and where your money goes.
B21: 6. Check Tax Estimate for how much to set aside and your quarterly payment amounts.
B22: 7. Delete the example row on each log tab (row 5) when you add your own data.
B23: Tip: in Google Sheets, use File > Import > Upload, or open the file from Google Drive.
B24: Tip: edit category names on the Lists tab. The dropdowns and Dashboard update automatically.
B27: IMPORTANT
B28: Tax figures are simplified estimates for planning only, not tax advice. They do not include the standard deduction, QBI deduction, credits, other income or the Social Security wage cap. Confirm amounts with a tax professional or IRS Form 1040-ES.

Sheet Dashboard
A1: Dashboard
B2: ='Start Here'!$C$5&" · "&'Start Here'!$C$6&" overview" -> My Side Hustle · 2026 overview
B4: INCOME | D4: EXPENSES | F4: TAX TO SET ASIDE | H4: TAKE-HOME
B5: =C25 -> 450 | D5: =D25 -> 59.99 | F5: =G25 -> 112.8695 | H5: =H25 -> 277.1405
B8: Yearly goal progress | D8: =I25 -> 0.0125 | E8: ="of "&TEXT('Start Here'!$C$7*12,"$#,##0")&" goal" -> of $36,000 goal | G8: Profit margin | H8: =IF(C25>0,(C25-D25)/C25,0) -> 0.86668889
B11: MONTH BY MONTH | K11: WHERE THE MONEY GOES
B12: Month | C12: Income | D12: Expenses | E12: Deductions | F12: Taxable profit | G12: Tax to set aside | H12: Take-home | I12: Goal progress | K12: Category | L12: Spent | M12: Share
B13: Jan | C13: =SUMIFS(Income!$E$5:$E$504,Income!$A$5:$A$504,">="&DATE('Start Here'!$C$6,1,1),Income!$A$5:$A$504,"<"&DATE('Start Here'!$C$6,1+1,1)) -> 450 | D13: =SUMIFS(Expenses!$E$5:$E$504,Expenses!$A$5:$A$504,">="&DATE('Start Here'!$C$6,1,1),Expenses!$A$5:$A$504,"<"&DATE('Start Here'!$C$6,1+1,1)) -> 59.99 | E13: =SUMIFS(Expenses!$G$5:$G$504,Expenses!$A$5:$A$504,">="&DATE('Start Here'!$C$6,1,1),Expenses!$A$5:$A$504,"<"&DATE('Start Here'!$C$6,1+1,1))+SUMIFS(Mileage!$F$5:$F$504,Mileage!$A$5:$A$504,">="&DATE('Start Here'!$C$6,1,1),Mileage!$A$5:$A$504,"<"&DATE('Start Here'!$C$6,1+1,1)) -> 72.87 | F13: =C13-E13 -> 377.13 | G13: =MAX(0,F13)*'Tax Estimate'!$C$18 -> 112.8695 | H13: =C13-D13-G13 -> 277.1405 | I13: =IF('Start Here'!$C$7>0,C13/'Start Here'!$C$7,0) -> 0.15 | K13: =IF(Lists!$C$5="","",Lists!$C$5) -> Advertising | L13: =IF(K13="","",SUMIFS(Expenses!$E$5:$E$504,Expenses!$D$5:$D$504,K13,Expenses!$A$5:$A$504,">="&DATE('Start Here'!$C$6,1,1),Expenses!$A$5:$A$504,"<"&DATE('Start Here'!$C$6+1,1,1))) -> 0 | M13: =IF(OR(K13="",$D$25=0),"",L13/$D$25) -> 0
B14: Feb | C14: =SUMIFS(Income!$E$5:$E$504,Income!$A$5:$A$504,">="&DATE('Start Here'!$C$6,2,1),Income!$A$5:$A$504,"<"&DATE('Start Here'!$C$6,2+1,1)) -> 0 | D14: =SUMIFS(Expenses!$E$5:$E$504,Expenses!$A$5:$A$504,">="&DATE('Start Here'!$C$6,2,1),Expenses!$A$5:$A$504,"<"&DATE('Start Here'!$C$6,2+1,1)) -> 0 | E14: =SUMIFS(Expenses!$G$5:$G$504,Expenses!$A$5:$A$504,">="&DATE('Start Here'!$C$6,2,1),Expenses!$A$5:$A$504,"<"&DATE('Start Here'!$C$6,2+1,1))+SUMIFS(Mileage!$F$5:$F$504,Mileage!$A$5:$A$504,">="&DATE('Start Here'!$C$6,2,1),Mileage!$A$5:$A$504,"<"&DATE('Start Here'!$C$6,2+1,1)) -> 0 | F14: =C14-E14 -> 0 | G14: =MAX(0,F14)*'Tax Estimate'!$C$18 -> 0 | H14: =C14-D14-G14 -> 0 | I14: =IF('Start Here'!$C$7>0,C14/'Start Here'!$C$7,0) -> 0 | K14: =IF(Lists!$C$6="","",Lists!$C$6) -> Software & subscriptions | L14: =IF(K14="","",SUMIFS(Expenses!$E$5:$E$504,Expenses!$D$5:$D$504,K14,Expenses!$A$5:$A$504,">="&DATE('Start Here'!$C$6,1,1),Expenses!$A$5:$A$504,"<"&DATE('Start Here'!$C$6+1,1,1))) -> 59.99 | M14: =IF(OR(K14="",$D$25=0),"",L14/$D$25) -> 1
B15: Mar | C15: =SUMIFS(Income!$E$5:$E$504,Income!$A$5:$A$504,">="&DATE('Start Here'!$C$6,3,1),Income!$A$5:$A$504,"<"&DATE('Start Here'!$C$6,3+1,1)) -> 0 | D15: =SUMIFS(Expenses!$E$5:$E$504,Expenses!$A$5:$A$504,">="&DATE('Start Here'!$C$6,3,1),Expenses!$A$5:$A$504,"<"&DATE('Start Here'!$C$6,3+1,1)) -> 0 | E15: =SUMIFS(Expenses!$G$5:$G$504,Expenses!$A$5:$A$504,">="&DATE('Start Here'!$C$6,3,1),Expenses!$A$5:$A$504,"<"&DATE('Start Here'!$C$6,3+1,1))+SUMIFS(Mileage!$F$5:$F$504,Mileage!$A$5:$A$504,">="&DATE('Start Here'!$C$6,3,1),Mileage!$A$5:$A$504,"<"&DATE('Start Here'!$C$6,3+1,1)) -> 0 | F15: =C15-E15 -> 0 | G15: =MAX(0,F15)*'Tax Estimate'!$C$18 -> 0 | H15: =C15-D15-G15 -> 0 | I15: =IF('Start Here'!$C$7>0,C15/'Start Here'!$C$7,0) -> 0 | K15: =IF(Lists!$C$7="","",Lists!$C$7) -> Supplies & materials | L15: =IF(K15="","",SUMIFS(Expenses!$E$5:$E$504,Expenses!$D$5:$D$504,K15,Expenses!$A$5:$A$504,">="&DATE('Start Here'!$C$6,1,1),Expenses!$A$5:$A$504,"<"&DATE('Start Here'!$C$6+1,1,1))) -> 0 | M15: =IF(OR(K15="",$D$25=0),"",L15/$D$25) -> 0
B16: Apr | C16: =SUMIFS(Income!$E$5:$E$504,Income!$A$5:$A$504,">="&DATE('Start Here'!$C$6,4,1),Income!$A$5:$A$504,"<"&DATE('Start Here'!$C$6,4+1,1)) -> 0 | D16: =SUMIFS(Expenses!$E$5:$E$504,Expenses!$A$5:$A$504,">="&DATE('Start Here'!$C$6,4,1),Expenses!$A$5:$A$504,"<"&DATE('Start Here'!$C$6,4+1,1)) -> 0 | E16: =SUMIFS(Expenses!$G$5:$G$504,Expenses!$A$5:$A$504,">="&DATE('Start Here'!$C$6,4,1),Expenses!$A$5:$A$504,"<"&DATE('Start Here'!$C$6,4+1,1))+SUMIFS(Mileage!$F$5:$F$504,Mileage!$A$5:$A$504,">="&DATE('Start Here'!$C$6,4,1),Mileage!$A$5:$A$504,"<"&DATE('Start Here'!$C$6,4+1,1)) -> 0 | F16: =C16-E16 -> 0 | G16: =MAX(0,F16)*'Tax Estimate'!$C$18 -> 0 | H16: =C16-D16-G16 -> 0 | I16: =IF('Start Here'!$C$7>0,C16/'Start Here'!$C$7,0) -> 0 | K16: =IF(Lists!$C$8="","",Lists!$C$8) -> Equipment | L16: =IF(K16="","",SUMIFS(Expenses!$E$5:$E$504,Expenses!$D$5:$D$504,K16,Expenses!$A$5:$A$504,">="&DATE('Start Here'!$C$6,1,1),Expenses!$A$5:$A$504,"<"&DATE('Start Here'!$C$6+1,1,1))) -> 0 | M16: =IF(OR(K16="",$D$25=0),"",L16/$D$25) -> 0
B17: May | C17: =SUMIFS(Income!$E$5:$E$504,Income!$A$5:$A$504,">="&DATE('Start Here'!$C$6,5,1),Income!$A$5:$A$504,"<"&DATE('Start Here'!$C$6,5+1,1)) -> 0 | D17: =SUMIFS(Expenses!$E$5:$E$504,Expenses!$A$5:$A$504,">="&DATE('Start Here'!$C$6,5,1),Expenses!$A$5:$A$504,"<"&DATE('Start Here'!$C$6,5+1,1)) -> 0 | E17: =SUMIFS(Expenses!$G$5:$G$504,Expenses!$A$5:$A$504,">="&DATE('Start Here'!$C$6,5,1),Expenses!$A$5:$A$504,"<"&DATE('Start Here'!$C$6,5+1,1))+SUMIFS(Mileage!$F$5:$F$504,Mileage!$A$5:$A$504,">="&DATE('Start Here'!$C$6,5,1),Mileage!$A$5:$A$504,"<"&DATE('Start Here'!$C$6,5+1,1)) -> 0 | F17: =C17-E17 -> 0 | G17: =MAX(0,F17)*'Tax Estimate'!$C$18 -> 0 | H17: =C17-D17-G17 -> 0 | I17: =IF('Start Here'!$C$7>0,C17/'Start Here'!$C$7,0) -> 0 | K17: =IF(Lists!$C$9="","",Lists!$C$9) -> Phone & internet | L17: =IF(K17="","",SUMIFS(Expenses!$E$5:$E$504,Expenses!$D$5:$D$504,K17,Expenses!$A$5:$A$504,">="&DATE('Start Here'!$C$6,1,1),Expenses!$A$5:$A$504,"<"&DATE('Start Here'!$C$6+1,1,1))) -> 0 | M17: =IF(OR(K17="",$D$25=0),"",L17/$D$25) -> 0
B18: Jun | C18: =SUMIFS(Income!$E$5:$E$504,Income!$A$5:$A$504,">="&DATE('Start Here'!$C$6,6,1),Income!$A$5:$A$504,"<"&DATE('Start Here'!$C$6,6+1,1)) -> 0 | D18: =SUMIFS(Expenses!$E$5:$E$504,Expenses!$A$5:$A$504,">="&DATE('Start Here'!$C$6,6,1),Expenses!$A$5:$A$504,"<"&DATE('Start Here'!$C$6,6+1,1)) -> 0 | E18: =SUMIFS(Expenses!$G$5:$G$504,Expenses!$A$5:$A$504,">="&DATE('Start Here'!$C$6,6,1),Expenses!$A$5:$A$504,"<"&DATE('Start Here'!$C$6,6+1,1))+SUMIFS(Mileage!$F$5:$F$504,Mileage!$A$5:$A$504,">="&DATE('Start Here'!$C$6,6,1),Mileage!$A$5:$A$504,"<"&DATE('Start Here'!$C$6,6+1,1)) -> 0 | F18: =C18-E18 -> 0 | G18: =MAX(0,F18)*'Tax Estimate'!$C$18 -> 0 | H18: =C18-D18-G18 -> 0 | I18: =IF('Start Here'!$C$7>0,C18/'Start Here'!$C$7,0) -> 0 | K18: =IF(Lists!$C$10="","",Lists!$C$10) -> Home office | L18: =IF(K18="","",SUMIFS(Expenses!$E$5:$E$504,Expenses!$D$5:$D$504,K18,Expenses!$A$5:$A$504,">="&DATE('Start Here'!$C$6,1,1),Expenses!$A$5:$A$504,"<"&DATE('Start Here'!$C$6+1,1,1))) -> 0 | M18: =IF(OR(K18="",$D$25=0),"",L18/$D$25) -> 0
B19: Jul | C19: =SUMIFS(Income!$E$5:$E$504,Income!$A$5:$A$504,">="&DATE('Start Here'!$C$6,7,1),Income!$A$5:$A$504,"<"&DATE('Start Here'!$C$6,7+1,1)) -> 0 | D19: =SUMIFS(Expenses!$E$5:$E$504,Expenses!$A$5:$A$504,">="&DATE('Start Here'!$C$6,7,1),Expenses!$A$5:$A$504,"<"&DATE('Start Here'!$C$6,7+1,1)) -> 0 | E19: =SUMIFS(Expenses!$G$5:$G$504,Expenses!$A$5:$A$504,">="&DATE('Start Here'!$C$6,7,1),Expenses!$A$5:$A$504,"<"&DATE('Start Here'!$C$6,7+1,1))+SUMIFS(Mileage!$F$5:$F$504,Mileage!$A$5:$A$504,">="&DATE('Start Here'!$C$6,7,1),Mileage!$A$5:$A$504,"<"&DATE('Start Here'!$C$6,7+1,1)) -> 0 | F19: =C19-E19 -> 0 | G19: =MAX(0,F19)*'Tax Estimate'!$C$18 -> 0 | H19: =C19-D19-G19 -> 0 | I19: =IF('Start Here'!$C$7>0,C19/'Start Here'!$C$7,0) -> 0 | K19: =IF(Lists!$C$11="","",Lists!$C$11) -> Platform & payment fees | L19: =IF(K19="","",SUMIFS(Expenses!$E$5:$E$504,Expenses!$D$5:$D$504,K19,Expenses!$A$5:$A$504,">="&DATE('Start Here'!$C$6,1,1),Expenses!$A$5:$A$504,"<"&DATE('Start Here'!$C$6+1,1,1))) -> 0 | M19: =IF(OR(K19="",$D$25=0),"",L19/$D$25) -> 0
B20: Aug | C20: =SUMIFS(Income!$E$5:$E$504,Income!$A$5:$A$504,">="&DATE('Start Here'!$C$6,8,1),Income!$A$5:$A$504,"<"&DATE('Start Here'!$C$6,8+1,1)) -> 0 | D20: =SUMIFS(Expenses!$E$5:$E$504,Expenses!$A$5:$A$504,">="&DATE('Start Here'!$C$6,8,1),Expenses!$A$5:$A$504,"<"&DATE('Start Here'!$C$6,8+1,1)) -> 0 | E20: =SUMIFS(Expenses!$G$5:$G$504,Expenses!$A$5:$A$504,">="&DATE('Start Here'!$C$6,8,1),Expenses!$A$5:$A$504,"<"&DATE('Start Here'!$C$6,8+1,1))+SUMIFS(Mileage!$F$5:$F$504,Mileage!$A$5:$A$504,">="&DATE('Start Here'!$C$6,8,1),Mileage!$A$5:$A$504,"<"&DATE('Start Here'!$C$6,8+1,1)) -> 0 | F20: =C20-E20 -> 0 | G20: =MAX(0,F20)*'Tax Estimate'!$C$18 -> 0 | H20: =C20-D20-G20 -> 0 | I20: =IF('Start Here'!$C$7>0,C20/'Start Here'!$C$7,0) -> 0 | K20: =IF(Lists!$C$12="","",Lists!$C$12) -> Shipping | L20: =IF(K20="","",SUMIFS(Expenses!$E$5:$E$504,Expenses!$D$5:$D$504,K20,Expenses!$A$5:$A$504,">="&DATE('Start Here'!$C$6,1,1),Expenses!$A$5:$A$504,"<"&DATE('Start Here'!$C$6+1,1,1))) -> 0 | M20: =IF(OR(K20="",$D$25=0),"",L20/$D$25) -> 0
B21: Sep | C21: =SUMIFS(Income!$E$5:$E$504,Income!$A$5:$A$504,">="&DATE('Start Here'!$C$6,9,1),Income!$A$5:$A$504,"<"&DATE('Start Here'!$C$6,9+1,1)) -> 0 | D21: =SUMIFS(Expenses!$E$5:$E$504,Expenses!$A$5:$A$504,">="&DATE('Start Here'!$C$6,9,1),Expenses!$A$5:$A$504,"<"&DATE('Start Here'!$C$6,9+1,1)) -> 0 | E21: =SUMIFS(Expenses!$G$5:$G$504,Expenses!$A$5:$A$504,">="&DATE('Start Here'!$C$6,9,1),Expenses!$A$5:$A$504,"<"&DATE('Start Here'!$C$6,9+1,1))+SUMIFS(Mileage!$F$5:$F$504,Mileage!$A$5:$A$504,">="&DATE('Start Here'!$C$6,9,1),Mileage!$A$5:$A$504,"<"&DATE('Start Here'!$C$6,9+1,1)) -> 0 | F21: =C21-E21 -> 0 | G21: =MAX(0,F21)*'Tax Estimate'!$C$18 -> 0 | H21: =C21-D21-G21 -> 0 | I21: =IF('Start Here'!$C$7>0,C21/'Start Here'!$C$7,0) -> 0 | K21: =IF(Lists!$C$13="","",Lists!$C$13) -> Education & training | L21: =IF(K21="","",SUMIFS(Expenses!$E$5:$E$504,Expenses!$D$5:$D$504,K21,Expenses!$A$5:$A$504,">="&DATE('Start Here'!$C$6,1,1),Expenses!$A$5:$A$504,"<"&DATE('Start Here'!$C$6+1,1,1))) -> 0 | M21: =IF(OR(K21="",$D$25=0),"",L21/$D$25) -> 0
B22: Oct | C22: =SUMIFS(Income!$E$5:$E$504,Income!$A$5:$A$504,">="&DATE('Start Here'!$C$6,10,1),Income!$A$5:$A$504,"<"&DATE('Start Here'!$C$6,10+1,1)) -> 0 | D22: =SUMIFS(Expenses!$E$5:$E$504,Expenses!$A$5:$A$504,">="&DATE('Start Here'!$C$6,10,1),Expenses!$A$5:$A$504,"<"&DATE('Start Here'!$C$6,10+1,1)) -> 0 | E22: =SUMIFS(Expenses!$G$5:$G$504,Expenses!$A$5:$A$504,">="&DATE('Start Here'!$C$6,10,1),Expenses!$A$5:$A$504,"<"&DATE('Start Here'!$C$6,10+1,1))+SUMIFS(Mileage!$F$5:$F$504,Mileage!$A$5:$A$504,">="&DATE('Start Here'!$C$6,10,1),Mileage!$A$5:$A$504,"<"&DATE('Start Here'!$C$6,10+1,1)) -> 0 | F22: =C22-E22 -> 0 | G22: =MAX(0,F22)*'Tax Estimate'!$C$18 -> 0 | H22: =C22-D22-G22 -> 0 | I22: =IF('Start Here'!$C$7>0,C22/'Start Here'!$C$7,0) -> 0 | K22: =IF(Lists!$C$14="","",Lists!$C$14) -> Travel | L22: =IF(K22="","",SUMIFS(Expenses!$E$5:$E$504,Expenses!$D$5:$D$504,K22,Expenses!$A$5:$A$504,">="&DATE('Start Here'!$C$6,1,1),Expenses!$A$5:$A$504,"<"&DATE('Start Here'!$C$6+1,1,1))) -> 0 | M22: =IF(OR(K22="",$D$25=0),"",L22/$D$25) -> 0
B23: Nov | C23: =SUMIFS(Income!$E$5:$E$504,Income!$A$5:$A$504,">="&DATE('Start Here'!$C$6,11,1),Income!$A$5:$A$504,"<"&DATE('Start Here'!$C$6,11+1,1)) -> 0 | D23: =SUMIFS(Expenses!$E$5:$E$504,Expenses!$A$5:$A$504,">="&DATE('Start Here'!$C$6,11,1),Expenses!$A$5:$A$504,"<"&DATE('Start Here'!$C$6,11+1,1)) -> 0 | E23: =SUMIFS(Expenses!$G$5:$G$504,Expenses!$A$5:$A$504,">="&DATE('Start Here'!$C$6,11,1),Expenses!$A$5:$A$504,"<"&DATE('Start Here'!$C$6,11+1,1))+SUMIFS(Mileage!$F$5:$F$504,Mileage!$A$5:$A$504,">="&DATE('Start Here'!$C$6,11,1),Mileage!$A$5:$A$504,"<"&DATE('Start Here'!$C$6,11+1,1)) -> 0 | F23: =C23-E23 -> 0 | G23: =MAX(0,F23)*'Tax Estimate'!$C$18 -> 0 | H23: =C23-D23-G23 -> 0 | I23: =IF('Start Here'!$C$7>0,C23/'Start Here'!$C$7,0) -> 0 | K23: =IF(Lists!$C$15="","",Lists!$C$15) -> Meals (business) | L23: =IF(K23="","",SUMIFS(Expenses!$E$5:$E$504,Expenses!$D$5:$D$504,K23,Expenses!$A$5:$A$504,">="&DATE('Start Here'!$C$6,1,1),Expenses!$A$5:$A$504,"<"&DATE('Start Here'!$C$6+1,1,1))) -> 0 | M23: =IF(OR(K23="",$D$25=0),"",L23/$D$25) -> 0
B24: Dec | C24: =SUMIFS(Income!$E$5:$E$504,Income!$A$5:$A$504,">="&DATE('Start Here'!$C$6,12,1),Income!$A$5:$A$504,"<"&DATE('Start Here'!$C$6,12+1,1)) -> 0 | D24: =SUMIFS(Expenses!$E$5:$E$504,Expenses!$A$5:$A$504,">="&DATE('Start Here'!$C$6,12,1),Expenses!$A$5:$A$504,"<"&DATE('Start Here'!$C$6,12+1,1)) -> 0 | E24: =SUMIFS(Expenses!$G$5:$G$504,Expenses!$A$5:$A$504,">="&DATE('Start Here'!$C$6,12,1),Expenses!$A$5:$A$504,"<"&DATE('Start Here'!$C$6,12+1,1))+SUMIFS(Mileage!$F$5:$F$504,Mileage!$A$5:$A$504,">="&DATE('Start Here'!$C$6,12,1),Mileage!$A$5:$A$504,"<"&DATE('Start Here'!$C$6,12+1,1)) -> 0 | F24: =C24-E24 -> 0 | G24: =MAX(0,F24)*'Tax Estimate'!$C$18 -> 0 | H24: =C24-D24-G24 -> 0 | I24: =IF('Start Here'!$C$7>0,C24/'Start Here'!$C$7,0) -> 0 | K24: =IF(Lists!$C$16="","",Lists!$C$16) -> Professional services | L24: =IF(K24="","",SUMIFS(Expenses!$E$5:$E$504,Expenses!$D$5:$D$504,K24,Expenses!$A$5:$A$504,">="&DATE('Start Here'!$C$6,1,1),Expenses!$A$5:$A$504,"<"&DATE('Start Here'!$C$6+1,1,1))) -> 0 | M24: =IF(OR(K24="",$D$25=0),"",L24/$D$25) -> 0
B25: Total | C25: =SUM(C13:C24) -> 450 | D25: =SUM(D13:D24) -> 59.99 | E25: =SUM(E13:E24) -> 72.87 | F25: =SUM(F13:F24) -> 377.13 | G25: =SUM(G13:G24) -> 112.8695 | H25: =SUM(H13:H24) -> 277.1405 | I25: =IF('Start Here'!$C$7>0,C25/('Start Here'!$C$7*12),0) -> 0.0125 | K25: =IF(Lists!$C$17="","",Lists!$C$17) -> Insurance | L25: =IF(K25="","",SUMIFS(Expenses!$E$5:$E$504,Expenses!$D$5:$D$504,K25,Expenses!$A$5:$A$504,">="&DATE('Start Here'!$C$6,1,1),Expenses!$A$5:$A$504,"<"&DATE('Start Here'!$C$6+1,1,1))) -> 0 | M25: =IF(OR(K25="",$D$25=0),"",L25/$D$25) -> 0
K26: =IF(Lists!$C$18="","",Lists!$C$18) -> Other | L26: =IF(K26="","",SUMIFS(Expenses!$E$5:$E$504,Expenses!$D$5:$D$504,K26,Expenses!$A$5:$A$504,">="&DATE('Start Here'!$C$6,1,1),Expenses!$A$5:$A$504,"<"&DATE('Start Here'!$C$6+1,1,1))) -> 0 | M26: =IF(OR(K26="",$D$25=0),"",L26/$D$25) -> 0
K27: =IF(Lists!$C$19="","",Lists!$C$19) | L27: =IF(K27="","",SUMIFS(Expenses!$E$5:$E$504,Expenses!$D$5:$D$504,K27,Expenses!$A$5:$A$504,">="&DATE('Start Here'!$C$6,1,1),Expenses!$A$5:$A$504,"<"&DATE('Start Here'!$C$6+1,1,1))) | M27: =IF(OR(K27="",$D$25=0),"",L27/$D$25)
K28: =IF(Lists!$C$20="","",Lists!$C$20) | L28: =IF(K28="","",SUMIFS(Expenses!$E$5:$E$504,Expenses!$D$5:$D$504,K28,Expenses!$A$5:$A$504,">="&DATE('Start Here'!$C$6,1,1),Expenses!$A$5:$A$504,"<"&DATE('Start Here'!$C$6+1,1,1))) | M28: =IF(OR(K28="",$D$25=0),"",L28/$D$25)
K29: =IF(Lists!$C$21="","",Lists!$C$21) | L29: =IF(K29="","",SUMIFS(Expenses!$E$5:$E$504,Expenses!$D$5:$D$504,K29,Expenses!$A$5:$A$504,">="&DATE('Start Here'!$C$6,1,1),Expenses!$A$5:$A$504,"<"&DATE('Start Here'!$C$6+1,1,1))) | M29: =IF(OR(K29="",$D$25=0),"",L29/$D$25)
K30: =IF(Lists!$C$22="","",Lists!$C$22) | L30: =IF(K30="","",SUMIFS(Expenses!$E$5:$E$504,Expenses!$D$5:$D$504,K30,Expenses!$A$5:$A$504,">="&DATE('Start Here'!$C$6,1,1),Expenses!$A$5:$A$504,"<"&DATE('Start Here'!$C$6+1,1,1))) | M30: =IF(OR(K30="",$D$25=0),"",L30/$D$25)
K31: =IF(Lists!$C$23="","",Lists!$C$23) | L31: =IF(K31="","",SUMIFS(Expenses!$E$5:$E$504,Expenses!$D$5:$D$504,K31,Expenses!$A$5:$A$504,">="&DATE('Start Here'!$C$6,1,1),Expenses!$A$5:$A$504,"<"&DATE('Start Here'!$C$6+1,1,1))) | M31: =IF(OR(K31="",$D$25=0),"",L31/$D$25)
K32: =IF(Lists!$C$24="","",Lists!$C$24) | L32: =IF(K32="","",SUMIFS(Expenses!$E$5:$E$504,Expenses!$D$5:$D$504,K32,Expenses!$A$5:$A$504,">="&DATE('Start Here'!$C$6,1,1),Expenses!$A$5:$A$504,"<"&DATE('Start Here'!$C$6+1,1,1))) | M32: =IF(OR(K32="",$D$25=0),"",L32/$D$25)
K33: =IF(Lists!$C$25="","",Lists!$C$25) | L33: =IF(K33="","",SUMIFS(Expenses!$E$5:$E$504,Expenses!$D$5:$D$504,K33,Expenses!$A$5:$A$504,">="&DATE('Start Here'!$C$6,1,1),Expenses!$A$5:$A$504,"<"&DATE('Start Here'!$C$6+1,1,1))) | M33: =IF(OR(K33="",$D$25=0),"",L33/$D$25)
K34: =IF(Lists!$C$26="","",Lists!$C$26) | L34: =IF(K34="","",SUMIFS(Expenses!$E$5:$E$504,Expenses!$D$5:$D$504,K34,Expenses!$A$5:$A$504,">="&DATE('Start Here'!$C$6,1,1),Expenses!$A$5:$A$504,"<"&DATE('Start Here'!$C$6+1,1,1))) | M34: =IF(OR(K34="",$D$25=0),"",L34/$D$25)
K35: =IF(Lists!$C$27="","",Lists!$C$27) | L35: =IF(K35="","",SUMIFS(Expenses!$E$5:$E$504,Expenses!$D$5:$D$504,K35,Expenses!$A$5:$A$504,">="&DATE('Start Here'!$C$6,1,1),Expenses!$A$5:$A$504,"<"&DATE('Start Here'!$C$6+1,1,1))) | M35: =IF(OR(K35="",$D$25=0),"",L35/$D$25)
K36: =IF(Lists!$C$28="","",Lists!$C$28) | L36: =IF(K36="","",SUMIFS(Expenses!$E$5:$E$504,Expenses!$D$5:$D$504,K36,Expenses!$A$5:$A$504,">="&DATE('Start Here'!$C$6,1,1),Expenses!$A$5:$A$504,"<"&DATE('Start Here'!$C$6+1,1,1))) | M36: =IF(OR(K36="",$D$25=0),"",L36/$D$25)
K37: =IF(Lists!$C$29="","",Lists!$C$29) | L37: =IF(K37="","",SUMIFS(Expenses!$E$5:$E$504,Expenses!$D$5:$D$504,K37,Expenses!$A$5:$A$504,">="&DATE('Start Here'!$C$6,1,1),Expenses!$A$5:$A$504,"<"&DATE('Start Here'!$C$6+1,1,1))) | M37: =IF(OR(K37="",$D$25=0),"",L37/$D$25)

Sheet Tax Estimate
A1: Tax Estimate
A2: Simplified US self-employment estimate for planning. Not tax advice. See Start Here.
B4: YEAR TO DATE
B5: Gross income | C5: =Dashboard!C25 -> 450
B6: Deductible expenses | C6: =SUMIFS(Expenses!$G$5:$G$504,Expenses!$A$5:$A$504,">="&DATE('Start Here'!$C$6,1,1),Expenses!$A$5:$A$504,"<"&DATE('Start Here'!$C$6+1,1,1)) -> 59.99
B7: Mileage deduction | C7: =SUMIFS(Mileage!$F$5:$F$504,Mileage!$A$5:$A$504,">="&DATE('Start Here'!$C$6,1,1),Mileage!$A$5:$A$504,"<"&DATE('Start Here'!$C$6+1,1,1)) -> 12.88
B8: Net profit (Schedule C estimate) | C8: =MAX(0,C5-C6-C7) -> 377.13
B10: Profit subject to SE tax | C10: =C8*'Start Here'!$C$11 -> 348.27956
B11: Self-employment tax | C11: =C10*'Start Here'!$C$10 -> 53.286772
B12: Deduction for half of SE tax | C12: =C11/2 -> 26.643386
B13: Profit subject to income tax | C13: =MAX(0,C8-C12) -> 350.48661
B14: Federal income tax | C14: =C13*'Start Here'!$C$8 -> 42.058394
B15: State income tax | C15: =C13*'Start Here'!$C$9 -> 17.524331
B17: TOTAL ESTIMATED TAX | C17: =C11+C14+C15 -> 112.8695
B18: Effective rate on net profit | C18: =IF(C8>0,C17/C8,0) -> 0.29928538
B19: Set aside this % of every payment | C19: =IF(C5>0,C17/C5,0) -> 0.2508211
B22: QUARTERLY ESTIMATED PAYMENTS (IRS Form 1040-ES)
B23: Period | C23: Due date | D23: Profit in period | E23: Suggested payment | F23: You paid | G23: Still owed
B24: Q1: Jan 1 - Mar 31 | C24: =DATE('Start Here'!$C$6,4,15) -> 46127 | D24: =SUM(Dashboard!F13:F15) -> 377.13 | E24: =MAX(0,D24)*$C$18 -> 112.8695 | G24: =MAX(0,E24-N(F24)) -> 112.8695
B25: Q2: Apr 1 - May 31 | C25: =DATE('Start Here'!$C$6,6,15) -> 46188 | D25: =SUM(Dashboard!F16:F17) -> 0 | E25: =MAX(0,D25)*$C$18 -> 0 | G25: =MAX(0,E25-N(F25)) -> 0
B26: Q3: Jun 1 - Aug 31 | C26: =DATE('Start Here'!$C$6,9,15) -> 46280 | D26: =SUM(Dashboard!F18:F20) -> 0 | E26: =MAX(0,D26)*$C$18 -> 0 | G26: =MAX(0,E26-N(F26)) -> 0
B27: Q4: Sep 1 - Dec 31 | C27: =DATE('Start Here'!$C$6+1,1,15) -> 46402 | D27: =SUM(Dashboard!F21:F24) -> 0 | E27: =MAX(0,D27)*$C$18 -> 0 | G27: =MAX(0,E27-N(F27)) -> 0
B29: Due dates that fall on a weekend or holiday move to the next business day. Enter what you actually paid in the yellow cells.

Sheet Income
A1: Income
A2: Log every payment you receive. Type in the white cells; totals update everywhere automatically.
A3: Total income logged (all years): | E3: =SUM(E5:E504) -> 450
A4: Date | B4: Client / source | C4: Description | D4: Category | E4: Amount ($) | F4: Paid via
A5: 46037 | B5: Acme Co. | C5: Logo design (example - delete me) | D5: Client work | E5: 450 | F5: PayPal

Sheet Expenses
A1: Expenses
A2: Log business purchases. Grey cells calculate the deductible amount for you.
A3: Totals (all years): | E3: =SUM(E5:E504) -> 59.99 | G3: =SUM(G5:G504) -> 59.99
A4: Date | B4: Vendor | C4: Description | D4: Category | E4: Amount ($) | F4: Business use % | G4: Deductible ($)
A5: 46031 | B5: Adobe | C5: Creative Cloud (example - delete me) | D5: Software & subscriptions | E5: 59.99 | G5: =IF(E5="","",E5*IFERROR(INDEX(Lists!$D$5:$D$29,MATCH(D5,Lists!$C$5:$C$29,0)),1)*IF(F5="",1,F5)) -> 59.99
G6: =IF(E6="","",E6*IFERROR(INDEX(Lists!$D$5:$D$29,MATCH(D6,Lists!$C$5:$C$29,0)),1)*IF(F6="",1,F6))
G7: =IF(E7="","",E7*IFERROR(INDEX(Lists!$D$5:$D$29,MATCH(D7,Lists!$C$5:$C$29,0)),1)*IF(F7="",1,F7))
G8: =IF(E8="","",E8*IFERROR(INDEX(Lists!$D$5:$D$29,MATCH(D8,Lists!$C$5:$C$29,0)),1)*IF(F8="",1,F8))
G9: =IF(E9="","",E9*IFERROR(INDEX(Lists!$D$5:$D$29,MATCH(D9,Lists!$C$5:$C$29,0)),1)*IF(F9="",1,F9))
G10: =IF(E10="","",E10*IFERROR(INDEX(Lists!$D$5:$D$29,MATCH(D10,Lists!$C$5:$C$29,0)),1)*IF(F10="",1,F10))
G11: =IF(E11="","",E11*IFERROR(INDEX(Lists!$D$5:$D$29,MATCH(D11,Lists!$C$5:$C$29,0)),1)*IF(F11="",1,F11))
G12: =IF(E12="","",E12*IFERROR(INDEX(Lists!$D$5:$D$29,MATCH(D12,Lists!$C$5:$C$29,0)),1)*IF(F12="",1,F12))
G13: =IF(E13="","",E13*IFERROR(INDEX(Lists!$D$5:$D$29,MATCH(D13,Lists!$C$5:$C$29,0)),1)*IF(F13="",1,F13))
G14: =IF(E14="","",E14*IFERROR(INDEX(Lists!$D$5:$D$29,MATCH(D14,Lists!$C$5:$C$29,0)),1)*IF(F14="",1,F14))
G15: =IF(E15="","",E15*IFERROR(INDEX(Lists!$D$5:$D$29,MATCH(D15,Lists!$C$5:$C$29,0)),1)*IF(F15="",1,F15))
G16: =IF(E16="","",E16*IFERROR(INDEX(Lists!$D$5:$D$29,MATCH(D16,Lists!$C$5:$C$29,0)),1)*IF(F16="",1,F16))
G17: =IF(E17="","",E17*IFERROR(INDEX(Lists!$D$5:$D$29,MATCH(D17,Lists!$C$5:$C$29,0)),1)*IF(F17="",1,F17))
... G504: =IF(E504="","",E504*IFERROR(INDEX(Lists!$D$5:$D$29,MATCH(D504,Lists!$C$5:$C$29,0)),1)*IF(F504="",1,F504))

Sheet Mileage
A1: Mileage
A2: Log business trips (not your commute). Grey cells calculate the deduction for you.
A3: Totals (all years): | E3: =SUM(E5:E504) -> 18.4 | F3: =SUM(F5:F504) -> 12.88
A4: Date | B4: From | C4: To | D4: Purpose | E4: Miles | F4: Deduction ($)
A5: 46042 | B5: Home | C5: Client office | D5: Kickoff meeting (example - delete me) | E5: 18.4 | F5: =IF(E5="","",E5*'Start Here'!$C$12) -> 12.88
F6: =IF(E6="","",E6*'Start Here'!$C$12)
F7: =IF(E7="","",E7*'Start Here'!$C$12)
F8: =IF(E8="","",E8*'Start Here'!$C$12)
F9: =IF(E9="","",E9*'Start Here'!$C$12)
F10: =IF(E10="","",E10*'Start Here'!$C$12)
F11: =IF(E11="","",E11*'Start Here'!$C$12)
F12: =IF(E12="","",E12*'Start Here'!$C$12)
F13: =IF(E13="","",E13*'Start Here'!$C$12)
F14: =IF(E14="","",E14*'Start Here'!$C$12)
F15: =IF(E15="","",E15*'Start Here'!$C$12)
F16: =IF(E16="","",E16*'Start Here'!$C$12)
F17: =IF(E17="","",E17*'Start Here'!$C$12)
... F504: =IF(E504="","",E504*'Start Here'!$C$12)

Sheet Lists
A1: Lists
A2: Edit these to customize dropdowns. Keep deductible % between 0% and 100%.
A4: Income categories | C4: Expense categories | D4: Deductible % | F4: Payment methods
A5: Client work | C5: Advertising | D5: 1 | F5: Bank transfer
A6: Product sales | C6: Software & subscriptions | D6: 1 | F6: PayPal
A7: Services | C7: Supplies & materials | D7: 1 | F7: Stripe
A8: Tips | C8: Equipment | D8: 1 | F8: Cash
A9: Affiliate / ads | C9: Phone & internet | D9: 1 | F9: Card
A10: Rental | C10: Home office | D10: 1 | F10: Venmo
A11: Other income | C11: Platform & payment fees | D11: 1 | F11: Zelle
C12: Shipping | D12: 1 | F12: Check
C13: Education & training | D13: 1 | F13: Platform payout
C14: Travel | D14: 1
C15: Meals (business) | D15: 0.5
C16: Professional services | D16: 1
C17: Insurance | D17: 1
C18: Other | D18: 1
